Workbook
Name canjes: Tabla6[]
Name COMPILADO: Resumen!$B$3:$C$12
Name DatosExternos_1: PONDERADAS!#REF!
Name lastreview: #REF!
Name lastreview1: #REF!
Name lastreview2: #REF!
Name Nemotecnicos: Emisiones[Mnemotécnico SEN]
Name RNG_Actions: #REF!
Name RNG_AGENT: #REF!
Name RNG_ARROWS: #REF!
Name RNG_CHART1: #REF!
Name RNG_CHART2: #REF!
Name RNG_CHART3: #REF!
Name RNG_CHART4: #REF!
Name RNG_CHART5: #REF!
Name RNG_CHART6: #REF!
Name RNG_CHART7: #REF!
Name RNG_CHART8: #REF!
Name RNG_CLASS_CE_ABS: #REF!
Name RNG_CURRENT_DATE: #REF!
Name RNG_DEAL_HEADER: #REF!
Name RNG_GO_BACK: #REF!
Name RNG_HYP: #REF!
Name RNG_Industry: #REF!
Name RNG_INFORMATION: #REF!
Name RNG_LAST_DATE: #REF!
Name RNG_Markers: #REF!
Name RNG_PERFORM_SUM_ABS: #REF!
Name RNG_PERFORM_SUM_PERCENT: #REF!
Name RNG_PERFORMANCE_ABS: #REF!
Name RNG_PERFORMANCE_Number: #REF!
Name RNG_PERFORMANCE_SUMMARY: #REF!
Name RNG_PREPAYMENT: #REF!
Name RNG_PREVIOUS_DATE: #REF!
Name RNG_ROW_DOWN: #REF!
Name RNG_RTNG: #REF!
Name RNG_Scale: #REF!
Name Transaction_Data_Int: #REF!
Name Type: '[2]All Actions 1 Mar - 15 May'!#REF!
Name VALOR_OP: Resumen!$C$3

Sheet Resumen
B3: Operación | C3: 657
B4: Fecha | C4: =_xlfn.XLOOKUP(C3,'Canjes desagregado'!B:B,'Canjes desagregado'!C:C,0) -> 46003
B5: Monto Canjeado (MC) | C5: {=+_xlfn.XLOOKUP($C$4&$C$3,HISTORICO!D:D&HISTORICO!$B:$B,HISTORICO!H:H,"",0,1)} -> 213678300000
B6: Valor de giro | C6: {=+_xlfn.XLOOKUP($C$4&$C$3,HISTORICO!D:D&HISTORICO!$B:$B,HISTORICO!I:I,"",0,1)} -> 75740
B7: Efecto cupones | C7: {=+_xlfn.XLOOKUP($C$4&$C$3,HISTORICO!D:D&HISTORICO!$B:$B,HISTORICO!J:J,"",0,1)} -> 0
B8: Indexaciones | C8: {=+_xlfn.XLOOKUP($C$4&$C$3,HISTORICO!D:D&HISTORICO!$B:$B,HISTORICO!L:L,"",0,1)} -> 0
B9: Saldo de la deuda | C9: {=+_xlfn.XLOOKUP($C$4&$C$3,HISTORICO!D:D&HISTORICO!$B:$B,HISTORICO!N:N,"",0,1)} -> -7678300000
B10: Costo Fiscal Neto | C10: {=+_xlfn.XLOOKUP($C$4&$C$3,HISTORICO!D:D&HISTORICO!$B:$B,HISTORICO!U:U,"",0,1)} -> -7678224260
B11: Efecto Fiscal Neto (EFN) | C11: {=+_xlfn.XLOOKUP($C$4&$C$3,HISTORICO!D:D&HISTORICO!$B:$B,HISTORICO!X:X,"",0,1)} -> -0.035933571
B12: Costo de Oportunidad | C12: =+_xlfn.XLOOKUP(C4,COSTO_OPORTUNIDAD!C:C,COSTO_OPORTUNIDAD!EA:EA) -> 0.12279
B13: E.F.N - C.O | C13: =C12-C11 -> 0.15872357
B16: Indicador | C16: Valor | E16: =B16 -> Indicador | F16: =C16 -> Valor
B17: Monto Canjeado (Valor nominal recibido) | C17: =-SUMIFS('Canjes desagregado'!S:S, 'Canjes desagregado'!B:B, C3, 'Canjes desagregado'!E:E, "Títulos Recogidos por la Nación") -> 213678300000 | E17: =B17 -> Monto Canjeado (Valor nominal recibido) | F17: =C17 -> 213678300000
B18: Valor nominal entregado | C18: =SUMIFS('Canjes desagregado'!S:S, 'Canjes desagregado'!B:B, C3, 'Canjes desagregado'!E:E, "Títulos Entregados por la Nación") -> 206000000000 | E18: =B18 -> Valor nominal entregado | F18: =C18 -> 206000000000
B19: Diferencia nominal (reducción de deuda) | C19: =C18-C17 -> -7678300000 | E19: =B19 -> Diferencia nominal (reducción de deuda) | F19: =C19 -> -7678300000
B20: Costo total entregado | C20: =SUMIFS('Canjes desagregado'!U:U, 'Canjes desagregado'!B:B, C3, 'Canjes desagregado'!E:E, "*Entregados*") -> 204661000000 | E20: =B20 -> Costo total entregado | F20: =C20 -> 204661000000
B21: Diferencia en costo | C21: =SUMIFS('Canjes desagregado'!U:U, 'Canjes desagregado'!B:B, C3, 'Canjes desagregado'!E:E, "Títulos Recogidos por la Nación")+C20 -> -75740 | E21: =B21 -> Diferencia en costo | F21: =C21 -> -75740
B22: Precio promedio recibido (coste/nominal) | C22: =AVERAGEIF(pond[Concepto],"*Recogidos*",pond[Precio Sucio]) -> 95.78 | E22: =B22 -> Precio promedio recibido (coste/nominal) | F22: =C22 -> 95.78
B23: Precio promedio entregado (coste/nominal) | C23: =AVERAGEIF(pond[Concepto],"*Entregados*",pond[Precio Sucio]) -> 99.35 | E23: =B23 -> Precio promedio entregado (coste/nominal) | F23: =C23 -> 99.35
B24: Tasa de cupón ponderada (Recibidos) | C24: =SUMPRODUCT(PONDERADAS!D2:D2,PONDERADAS!K2:K2)/100 -> 0 | E24: =B24 -> Tasa de cupón ponderada (Recibidos) | F24: =IFERROR(C24,"-") -> 0
B25: Tasa de cupón ponderada (Entregados) | C25: =SUMPRODUCT(PONDERADAS!D3:D3,PONDERADAS!K3:K3)/100 -> 0.11 | E25: =B25 -> Tasa de cupón ponderada (Entregados) | F25: =C25 -> 0.11
B26: Rendimiento promedio ponderado recibido | C26: =SUMPRODUCT(PONDERADAS!E2:E2,PONDERADAS!K2:K2)/100 -> 0.09581
B27: Rendimiento promedio ponderado entregado | C27: =SUMPRODUCT(PONDERADAS!E3:E3,PONDERADAS!K3:K3)/100 -> 0.12375
B28: Madurez promedio ponderada recibida (años) | C28: =SUMPRODUCT(PONDERADAS!I2:I2,PONDERADAS!K2:K2) -> 0.47123288
B29: Madurez promedio ponderada entregada (años) | C29: =SUMPRODUCT(PONDERADAS!I3:I3,PONDERADAS!K3:K3) -> 3.6958904
B30: Impacto en la vida media VPP en años | C30: =VPP!O3 -> #REF!

Sheet PONDERADAS
A1: Operación | B1: Concepto | C1: Fecha Vto | D1: Cupon | E1: Tasa de Corte (%) | F1: Precio Sucio | G1: Precio Limpio | H1: Nominal COP | I1: Madurez | J1: Costo COP | K1: % DE PESO | L1: nom_abs | M1: cost_abs2 | N1: AÑO
A2: 657 | B2: Títulos Recogidos por la Nación | C2: 46175 | D2: 0 | E2: 9.581 | F2: 95.78 | G2: 95.680154 | H2: -213678300000 | I2: 0.47123288 | J2: -204661075740 | K2: =IF(pond[[#This Row],[Concepto]] = "Títulos Recogidos por la Nación", pond[[#This Row],[Nominal COP]] / SUMIF(pond[Concepto], "Títulos Recogidos por la Nación", pond[Nominal COP]), IF(pond[[#This Row],[Concepto]] = "Títulos Entregados por la Nación", pond[[#This Row],[Nominal COP]] / SUMIF(pond[Concepto], "Títulos Entregados por la Nación", pond[Nominal COP]), 0)) -> 1 | L2: =ABS(pond[[#This Row],[Nominal COP]]) -> 213678300000 | M2: =ABS(pond[[#This Row],[Costo COP]]) -> 204661075740 | N2: =YEAR(pond[[#This Row],[Fecha Vto]]) -> 2026
A3: 657 | B3: Títulos Entregados por la Nación | C3: 47352 | D3: 11 | E3: 12.375 | F3: 99.35 | G3: 95.97495 | H3: 206000000000 | I3: 3.6958904 | J3: 204661000000 | K3: =IF(pond[[#This Row],[Concepto]] = "Títulos Recogidos por la Nación", pond[[#This Row],[Nominal COP]] / SUMIF(pond[Concepto], "Títulos Recogidos por la Nación", pond[Nominal COP]), IF(pond[[#This Row],[Concepto]] = "Títulos Entregados por la Nación", pond[[#This Row],[Nominal COP]] / SUMIF(pond[Concepto], "Títulos Entregados por la Nación", pond[Nominal COP]), 0)) -> 1 | L3: =ABS(pond[[#This Row],[Nominal COP]]) -> 206000000000 | M3: =ABS(pond[[#This Row],[Costo COP]]) -> 204661000000 | N3: =YEAR(pond[[#This Row],[Fecha Vto]]) -> 2029
A4: Total | L4: =SUBTOTAL(109,pond[nom_abs]) -> 419678300000 | M4: =SUBTOTAL(109,pond[cost_abs2]) -> 409322075740

Sheet VPP
A1: ='[3]Resumen Interna'!H13 -> Perfil de vencimientos | B1: ='[3]Resumen Interna'!J14 -> Total interna GNC | H1: VPP - Antes de OMD | K1: VPP - DESPUES de OMD | N1: IMPACTO
A2: ='[3]Resumen Interna'!H14 -> Periodo | B2: ='[3]Resumen Interna'!I14 -> TES | C2: TES-OMD | D2: TOTAL | E2: TOTAL - OMD | F2: ='[3]Resumen Interna'!K14 -> % | H2: VPP TES Principal | I2: {=SUMPRODUCT(($A$3:$A$40-$A$3),$B$3:$B$40)/SUM($B$3:$B$40)} -> 10.619587 | K2: VPP TES Principal | L2: {=SUMPRODUCT(($A$3:$A$40-$A$3),$C$3:$C$40)/SUM($C$3:$C$40)} -> 10.623101 | N2: VPP TES Principal | O2: =L2-I2 -> 0.0035137761
A3: ='[3]Resumen Interna'!H15 -> 2025 | B3: ='[3]Resumen Interna'!I15 -> 13006267 | C3: =B3-PONDERADAS!L2/1000000 -> 12792589 | D3: ='[3]Resumen Interna'!J15 -> 1.2084702e+08 | E3: =D3-PONDERADAS!L2/1000000 -> 1.2063334e+08 | F3: ='[3]Resumen Interna'!K15 -> 0.16961535 | H3: VPP Total | I3: {=SUMPRODUCT(($A$3:$A$40-$A$3),$D$3:$D$40)/SUM($D$3:$D$40)} -> 8.9936927 | K3: VPP Total | L3: {=SUMPRODUCT(($A$3:$A$40-$A$3),$E$3:$E$40)/SUM($E$3:$E$40)} -> #REF! | N3: VPP Total | O3: =L3-I3 -> #REF!
A4: ='[3]Resumen Interna'!H16 -> 2026 | B4: ='[3]Resumen Interna'!I16 -> 40258143 | C4: =B4 -> 40258143 | D4: ='[3]Resumen Interna'!J16 -> 49668966 | E4: =D4-PONDERADAS!#REF!/1000000 -> #REF! | F4: ='[3]Resumen Interna'!K16 -> 0.069713092
A5: ='[3]Resumen Interna'!H17 -> 2027 | B5: ='[3]Resumen Interna'!I17 -> 46505339 | C5: =B5 -> 46505339 | D5: ='[3]Resumen Interna'!J17 -> 46506006 | E5: =D5 -> 46506006 | F5: ='[3]Resumen Interna'!K17 -> 0.065273706
A6: ='[3]Resumen Interna'!H18 -> 2028 | B6: ='[3]Resumen Interna'!I18 -> 40127204 | C6: =B6 -> 40127204 | D6: ='[3]Resumen Interna'!J18 -> 40507588 | E6: =D6 -> 40507588 | F6: ='[3]Resumen Interna'!K18 -> 0.0568546
A7: ='[3]Resumen Interna'!H19 -> 2029 | B7: ='[3]Resumen Interna'!I19 -> 42412431 | C7: =B7 -> 42412431 | D7: ='[3]Resumen Interna'!J19 -> 42412431 | E7: =D7+PONDERADAS!L3/1000000 -> 42618431 | F7: ='[3]Resumen Interna'!K19 -> 0.05952815
A8: ='[3]Resumen Interna'!H20 -> 2030 | B8: ='[3]Resumen Interna'!I20 -> 27749357 | C8: =B8 -> 27749357 | D8: ='[3]Resumen Interna'!J20 -> 27749358 | E8: =D8 -> 27749358 | F8: ='[3]Resumen Interna'!K20 -> 0.038947731
A9: ='[3]Resumen Interna'!H21 -> 2031 | B9: ='[3]Resumen Interna'!I21 -> 35351314 | C9: =B9 -> 35351314 | D9: ='[3]Resumen Interna'!J21 -> 35351320 | E9: =D9 -> 35351320 | F9: ='[3]Resumen Interna'!K21 -> 0.049617498
A10: ='[3]Resumen Interna'!H22 -> 2032 | B10: ='[3]Resumen Interna'!I22 -> 27992627 | C10: =B10 -> 27992627 | D10: ='[3]Resumen Interna'!J22 -> 29468261 | E10: =D10 -> 29468261 | F10: ='[3]Resumen Interna'!K22 -> 0.041360305
A11: ='[3]Resumen Interna'!H23 -> 2033 | B11: ='[3]Resumen Interna'!I23 -> 47461545 | C11: =B11 -> 47461545 | D11: ='[3]Resumen Interna'!J23 -> 47461545 | E11: =D11 -> 47461545 | F11: ='[3]Resumen Interna'!K23 -> 0.066614856
A12: ='[3]Resumen Interna'!H24 -> 2034 | B12: ='[3]Resumen Interna'!I24 -> 28484312 | C12: =B12 -> 28484312 | D12: ='[3]Resumen Interna'!J24 -> 28484312 | E12: =D12 -> 28484312 | F12: ='[3]Resumen Interna'!K24 -> 0.039979279
A13: ='[3]Resumen Interna'!H25 -> 2035 | B13: ='[3]Resumen Interna'!I25 -> 37750683 | C13: =B13 -> 37750683 | D13: ='[3]Resumen Interna'!J25 -> 37750683 | E13: =D13 -> 37750683 | F13: ='[3]Resumen Interna'!K25 -> 0.052985134
A14: ='[3]Resumen Interna'!H26 -> 2036 | B14: ='[3]Resumen Interna'!I26 -> 28868529 | C14: =B14 -> 28868529 | D14: ='[3]Resumen Interna'!J26 -> 28868529 | E14: =D14 -> 28868529 | F14: ='[3]Resumen Interna'!K26 -> 0.040518548
A15: ='[3]Resumen Interna'!H27 -> 2037 | B15: ='[3]Resumen Interna'!I27 -> 43566794 | C15: =B15 -> 43566794 | D15: ='[3]Resumen Interna'!J27 -> 43566794 | E15: =D15 -> 43566794 | F15: ='[3]Resumen Interna'!K27 -> 0.061148361
A16: ='[3]Resumen Interna'!H28 -> 2038 | B16: ='[3]Resumen Interna'!I28 -> 0 | C16: =B16 -> 0 | D16: ='[3]Resumen Interna'!J28 -> 0 | E16: =D16 -> 0 | F16: ='[3]Resumen Interna'!K28 -> 0
A17: ='[3]Resumen Interna'!H29 -> 2039 | B17: ='[3]Resumen Interna'!I29 -> 0 | C17: =B17 -> 0 | D17: ='[3]Resumen Interna'!J29 -> 0 | E17: =D17 -> 0 | F17: ='[3]Resumen Interna'!K29 -> 0
A18: ='[3]Resumen Interna'!H30 -> 2040 | B18: ='[3]Resumen Interna'!I30 -> 2728167.3 | C18: =B18 -> 2728167.3 | D18: ='[3]Resumen Interna'!J30 -> 2728167.3 | E18: =D18 -> 2728167.3 | F18: ='[3]Resumen Interna'!K30 -> 0.003829131
A19: ='[3]Resumen Interna'!H31 -> 2041 | B19: ='[3]Resumen Interna'!I31 -> 4998438.8 | C19: =B19 -> 4998438.8 | D19: ='[3]Resumen Interna'!J31 -> 4998438.8 | E19: =D19 -> 4998438.8 | F19: ='[3]Resumen Interna'!K31 -> 0.0070155803
... A38: ='[3]Resumen Interna'!H50 -> 2060 | B38: ='[3]Resumen Interna'!I50 -> 0 | C38: =B38 -> 0 | D38: ='[3]Resumen Interna'!J50 -> 0 | E38: =D38 -> 0 | F38: ='[3]Resumen Interna'!K50 -> 0
A39: 2061 | B39: ='[3]Resumen Interna'!I51 -> 0 | C39: =B39 -> 0 | D39: ='[3]Resumen Interna'!J51 -> 0 | E39: =D39 -> 0 | F39: ='[3]Resumen Interna'!K51 -> 0
A40: 2062 | B40: ='[3]Resumen Interna'!I52 -> 0 | C40: =B40 -> 0 | D40: ='[3]Resumen Interna'!J52 -> 0 | E40: =D40 -> 0 | F40: ='[3]Resumen Interna'!K52 -> 0

Sheet Emisiones
B2: Titulo | C2: Plazo | D2: Tipo Plazo | E2: Moneda | F2: Emisión | G2: Mnemotécnico SEN | H2: Fecha Inicio Vigencia | I2: Fecha Vencim. | J2: Tasa de Interés | K2: Tasa Spread | L2: Signo | M2: Periodo Interés | N2: Tipo | O2: Código ISIN | P2: Código CFI | Q2: Saldo en Circulación | R2: Base de Ponderación | S2: Conteo de Plazo | T2: Modo de Pago
B3: 21 | C3: 16 | E3: COP | F3: 53059 | G3: TFIT16240724 | H3: 39653 | I3: 45497 | J3: 10 | K3: 0 | M3: A | N3: FIJA | O3: COL17CT02385 | P3: DMFTFR | R3: 365 | S3: Comercial | T3: Vencido
B4: 21 | C4: 8 | E4: COP | F4: 56219 | G4: TFIT08261125 | H4: 43065 | I4: 45987 | J4: 6.25 | K4: 0 | M4: A | N4: FIJA | O4: COL17CT03557 | P4: DMFTFR | R4: 365 | S4: Comercial | T4: Vencido
B5: 21 | C5: 15 | E5: COP | F5: 54542 | G5: TFIT15260826 | H5: 40781 | I5: 46260 | J5: 7.5 | K5: 0 | M5: A | N5: FIJA | O5: COL17CT02625 | P5: DMFTFR | R5: 365 | S5: Comercial | T5: Vencido
B6: 21 | C6: 8 | E6: COP | F6: 56552 | G6: TFIT08031127 | H6: 43772 | I6: 46694 | J6: 5.75 | K6: 0 | M6: A | N6: FIJA | O6: COL17CT03672 | P6: DBFTFR | R6: 365 | S6: Comercial | T6: Vencido
B7: 21 | C7: 16 | E7: COP | F7: 55029 | G7: TFIT16280428 | H7: 41027 | I7: 46871 | J7: 6 | K7: 0 | M7: A | N7: FIJA | O7: COL17CT02914 | P7: DMFTFR | R7: 365 | S7: Comercial | T7: Vencido
B8: 21 | C8: 5 | E8: COP | G8: TFIT05220829 | H8: 45526 | I8: 47352 | J8: 11 | K8: 0 | M8: A | N8: FIJA | O8: COL17CT03995 | P8: DMFTFR | R8: 365 | S8: Comercial | T8: Vencido
B9: 21 | C9: 16 | E9: COP | F9: 55684 | G9: TFIT16180930 | H9: 41900 | I9: 47744 | J9: 7.75 | K9: 0 | M9: A | N9: FIJA | O9: COL17CT03342 | P9: DMFTFR | R9: 365 | S9: Comercial | T9: Vencido
B10: 21 | C10: 10 | E10: COP | F10: 57165 | G10: TFIT10260331 | H10: 44281 | I10: 47933 | J10: 7 | K10: 0 | M10: A | N10: FIJA | O10: COL17CT03771 | P10: DBFTFR | R10: 365 | S10: Comercial | T10: Vencido
B11: 21 | C11: 10 | E11: COP | F11: 57278 | G11: TFVT10260331 | H11: 44281 | I11: 47933 | J11: 7 | K11: 0 | M11: A | N11: FIJA | O11: COL17CT03797 | P11: DBFTFR | R11: 365 | S11: Comercial | T11: Vencido
B12: 21 | C12: 16 | E12: COP | F12: 56059 | G12: TFIT16300632 | H12: 42551 | I12: 48395 | J12: 7 | K12: 0 | M12: A | N12: FIJA | O12: COL17CT03490 | P12: DMFTFR | R12: 365 | S12: Comercial | T12: Vencido
B13: 21 | C13: 11 | E13: COP | F13: 57836 | G13: TFIT11090233 | H13: 44601 | I13: 48619 | J13: 13.25 | K13: 0 | M13: A | N13: FIJA | O13: COL17CT03862 | P13: DBFTFR | R13: 365 | S13: Comercial | T13: Vencido
B14: 21 | C14: 16 | E14: COP | F14: 56377 | G14: TFIT16181034 | H14: 43391 | I14: 49235 | J14: 7.25 | K14: 0 | M14: A | N14: FIJA | O14: COL17CT03615 | P14: DBFTFR | R14: 365 | S14: Comercial | T14: Vencido
B15: 21 | C15: 16 | E15: COP | F15: 56970 | G15: TFIT16090736 | H15: 44021 | I15: 49865 | J15: 6.25 | K15: 0 | M15: A | N15: FIJA | O15: COL17CT03748 | P15: DBFTFR | R15: 365 | S15: Comercial | T15: Vencido
B16: 21 | C16: 16 | E16: COP | G16: TFIT16281140 | H16: 45624 | I16: 51468 | J16: 12.75 | K16: 0 | M16: A | N16: FIJA | O16: COL17CT04001 | P16: DBFTFR | R16: 365 | S16: Comercial | T16: Vencido
B17: 21 | C17: 21 | E17: COP | F17: 57407 | G17: TFIT21280542 | H17: 44344 | I17: 52014 | J17: 9.25 | K17: 0 | M17: A | N17: FIJA | O17: COL17CT03813 | P17: DBFTFR | R17: 365 | S17: Comercial | T17: Vencido
B18: 21 | C18: 23 | E18: COP | G18: TFIT23250746 | H18: 45132 | I18: 53533 | J18: 11.5 | K18: 0 | M18: A | N18: FIJA | O18: COL17CT03938 | R18: 365 | S18: Comercial | T18: Vencido
B19: 21 | C19: 31 | E19: COP | F19: 56840 | G19: TFIT31261050 | H19: 43764 | I19: 55087 | J19: 7.25 | K19: 0 | M19: A | N19: FIJA | O19: COL17CT03722 | P19: DBFTFR | R19: 365 | S19: Comercial | T19: Vencido
B20: 21 | C20: 17 | E20: UVR | F20: 49936 | G20: TUVT17230223 | H20: 38771 | I20: 44980 | J20: 4.75 | K20: 0 | M20: A | N20: FIJA | O20: COL17CT02088 | P20: DMFTFR | R20: 365 | S20: Comercial | T20: Vencido
B21: 21 | C21: 11 | E21: UVR | F21: 55738 | G21: TUVT11070525 | H21: 41766 | I21: 45784 | J21: 3.5 | K21: 0 | M21: A | N21: FIJA | O21: COL17CT03359 | P21: DMFTFR | R21: 365 | S21: Comercial | T21: Vencido
B22: 21 | C22: 11 | E22: UVR | F22: 56091 | G22: TUVT11170327 | H22: 42446 | I22: 46463 | J22: 3.3 | K22: 0 | M22: A | N22: FIJA | O22: COL17CT03508 | P22: DMFTFR | R22: 365 | S22: Comercial | T22: Vencido
B23: 21 | C23: 10 | E23: UVR | F23: 56614 | G23: TUVT10180429 | H23: 43573 | I23: 47226 | J23: 2.25 | K23: 0 | M23: A | N23: FIJA | O23: COL17CT03680 | P23: DBFTFR | R23: 365 | S23: Comercial | T23: Vencido
B24: 21 | C24: 6 | E24: UVR | G24: TUVT07220131 | H24: 47870 | I24: 47870 | J24: 6.5 | K24: 0 | M24: A | N24: FIJA
B25: 21 | C25: 20 | E25: UVR | F25: 55197 | G25: TUVT20250333 | H25: 41358 | I25: 48663 | J25: 3 | K25: 0 | M25: A | N25: FIJA | O25: COL17CT02963 | P25: DMFTFR | R25: 365 | S25: Comercial | T25: Vencido
B26: 21 | C26: 20 | E26: UVR | F26: 55930 | G26: TUVT20040435 | H26: 42098 | I26: 49403 | J26: 4.75 | K26: 0 | M26: A | N26: FIJA | O26: COL17CT03441 | P26: DMFTFR | R26: 365 | S26: Comercial | T26: Vencido
B27: 21 | C27: 18 | E27: UVR | F27: 56414 | G27: TUVT18250237 | H27: 43521 | I27: 50096 | J27: 3.75 | K27: 0 | M27: A | N27: FIJA | O27: COL17CT03623 | P27: DBFTFR | R27: 365 | S27: Comercial | T27: Vencido
B28: 21 | C28: 18 | E28: UVR | G28: TUVT17200341 | H28: 45371 | I28: 51580 | J28: 5 | K28: 0 | M28: A | N28: FIJA | O28: COL17CT03961 | P28: DBFTFR | R28: 365 | S28: Comercial | T28: Vencido
B29: 21 | C29: 32 | E29: UVR | F29: 56246 | G29: TUVT32160649 | H29: 42902 | I29: 54590 | J29: 3.75 | K29: 0 | M29: A | N29: FIJA | O29: COL17CT03565 | P29: DBFTFR | R29: 365 | S29: Comercial | T29: Vencido
B30: 21 | C30: 31 | E30: UVR | G30: TUVT31190555 | H30: 45431 | I30: 56753 | J30: 5.25 | K30: 0 | M30: A | N30: FIJA | O30: COL17CT03979 | P30: DBFTFR | R30: 365 | S30: Comercial | T30: Vencido
B31: 21 | C31: 37 | E31: UVR | G31: TUVT38010262 | I31: 59203 | J31: 6.5 | K31: 0 | M31: A | N31: FIJA | O31: FALTA
E32: COP | G32: COL17CT04084 | I32: 49313 | J32: 11.75 | K32: 0 | M32: A | N32: FIJA | O32: COL17CT04084
E33: COP | G33: COL17CT03987 | I33: 46084 | J33: 0 | K33: 0 | M33: A | N33: FIJA | O33: COL17CT03987
E34: COP | G34: COL17CT04027 | I34: 46175 | J34: 0 | K34: 0 | O34: COL17CT04027
E35: COP | G35: COL17CT03953 | I35: 46236 | J35: 0 | K35: 0

Sheet Canjes desagregado
A1: Año | B1: Operación | C1: Fecha Cumplimiento y/ liquidacion | D1: Canje | E1: Concepto | F1: Nemotécnico | G1: Denom | H1: Plazo | I1: Fecha Emision | J1: Fecha Vto | K1: Cupon | L1: Tasa de Corte (%) | M1: Precio Sucio | N1: Precio Limpio | O1: Intereses acumulados | P1: Intereses por devengar | Q1: Valor Nominal | R1: Valor Costo | S1: Nominal COP | T1: Verificador fecha y nemotécnico | U1: Costo COP | V1: UVR | W1: Efectos cupón | X1: Efecto Cupón (Signo) | Y1: Costo Fiscal | Z1: Saldo de la deuda | AA1: Inflación | AB1: UVR (Fin de periodo) | AC1: Delta_UVR | AD1: Indexaciones | AE1: % de cupón x devengar | AF1: Nuevo efecto cupón | AG1: Madurez | AH1: Operación2 | AI1: UVR (Fin de periodo)2 | AJ1: Indexaciones2 | AL1: Maduración | AM1: Maduración signo | AN1: Próximo cupón | AO1: % de cupón x devengar a 31 de diciembre | AP1: % de cupón x devengar a vencimiento del próximo año | AQ1: Cupón en año en curso | AR1: Cupón en siguiente año | AT1: Cupón en año en curso | AU1: Cupón en siguiente año
A2: =IF(C2="","",YEAR(C2)) -> 2025 | B2: 603 | C2: 45700 | D2: Tesorería | E2: Títulos Recogidos por la Nación | F2: TFIT15260826 | G2: =+_xlfn.XLOOKUP(F2,Emisiones[Mnemotécnico SEN],Emisiones[Moneda],"",0,1) -> COP | J2: =+_xlfn.XLOOKUP(F2,Emisiones[Mnemotécnico SEN],Emisiones[Fecha Vencim.],"",0,1) -> 46260 | K2: =+_xlfn.XLOOKUP(F2,Emisiones[Mnemotécnico SEN],Emisiones[Tasa de Interés],"",0,1) -> 7.5 | L2: 8.755 | M2: 101.683 | N2: =IF(C2="","",PRICE(C2,J2,K2%,L2%,100,1,3)) -> 98.189862 | O2: =IF(C2="","",M2-N2) -> 3.4931382 | P2: =IF(C2="","",100*K2%-O2) -> 4.0068618 | Q2: =IF(C2="","",IF(G2="UVR",S2/V2,S2)) -> -85000000000 | R2: =IF(C2="","",IF('Canjes desagregado'!$G2="UVR",'Canjes desagregado'!$V2*Q2*M2%,Q2*M2%)) -> -8.643055e+10 | S2: -85000000000 | T2: =IFERROR(IF(RIGHT(F2,2)=RIGHT(YEAR(J2),2),1,0),"") -> 1 | U2: =+IF(R2="","",R2) -> -8.643055e+10 | V2: =+IF(F2<>"",(_xlfn.XLOOKUP(C2,UVR[Fecha (dd/mm/aaaa)],UVR[Pesos colombianos por UVR],"",0,1)),"") -> 378.8353 | W2: =IF(C2="","",IF(CONCATENATE(DAY(C2),"/",MONTH(C2),"/",2000)-CONCATENATE(DAY(J2),"/",MONTH(J2),"/",2000)<0,K2%*ABS(S2),0)) -> 6375000000 | X2: =IF(S2<0,-W2,W2) -> -6375000000 | AB2: =IF(C2="","",ROUND(V2*(1+'Inflación observada '!$B$390%)^(("31-12-2025"-C2)/365),3)) -> 396.228 | AD2: =IF(C2="","",IF(G2="UVR",Q2*AB2-S2,0)) -> 0 | AE2: =IF(C2="","",P2/+(O2+P2)) -> 0.53424825 | AF2: =IF(C2="","",AE2*Q2*K2%) -> -3.4058326e+09 | AG2: =(Tabla6[[#This Row],[Fecha Vto]]-TODAY())/365 -> 0.70410959 | AJ2: =IF(C2="","",IF(G2="UVR",Q2*AI2-S2,0)) -> 0
A3: =IF(C3="","",YEAR(C3)) -> 2025 | B3: 603 | C3: 45700 | D3: Tesorería | E3: Títulos Entregados por la Nación | F3: TFIT23250746 | G3: =+_xlfn.XLOOKUP(F3,Emisiones[Mnemotécnico SEN],Emisiones[Moneda],"",0,1) -> COP | J3: =+_xlfn.XLOOKUP(F3,Emisiones[Mnemotécnico SEN],Emisiones[Fecha Vencim.],"",0,1) -> 53533 | K3: =+_xlfn.XLOOKUP(F3,Emisiones[Mnemotécnico SEN],Emisiones[Tasa de Interés],"",0,1) -> 11.5 | L3: 12.549 | M3: 98.499 | N3: =IF(C3="","",PRICE(C3,J3,K3%,L3%,100,1,3)) -> 92.134778 | O3: =IF(C3="","",M3-N3) -> 6.3642218 | P3: =IF(C3="","",100*K3%-O3) -> 5.1357782 | Q3: =IF(C3="","",IF(G3="UVR",S3/V3,S3)) -> 85000000000 | R3: =IF(C3="","",IF('Canjes desagregado'!$G3="UVR",'Canjes desagregado'!$V3*Q3*M3%,Q3*M3%)) -> 83724150000 | S3: 85000000000 | T3: =IFERROR(IF(RIGHT(F3,2)=RIGHT(YEAR(J3),2),1,0),"") -> 1 | U3: =+IF(R3="","",R3) -> 83724150000 | V3: =+IF(F3<>"",(_xlfn.XLOOKUP(C3,UVR[Fecha (dd/mm/aaaa)],UVR[Pesos colombianos por UVR],"",0,1)),"") -> 378.8353 | W3: =IF(C3="","",IF(CONCATENATE(DAY(C3),"/",MONTH(C3),"/",2000)-CONCATENATE(DAY(J3),"/",MONTH(J3),"/",2000)<0,K3%*ABS(S3),0)) -> 9775000000 | X3: =IF(S3<0,-W3,W3) -> 9775000000 | AB3: =IF(C3="","",ROUND(V3*(1+'Inflación observada '!$B$390%)^(("31-12-2025"-C3)/365),3)) -> 396.228 | AD3: =IF(C3="","",IF(G3="UVR",Q3*AB3-S3,0)) -> 0 | AE3: =IF(C3="","",P3/+(O3+P3)) -> 0.44658941 | AF3: =IF(C3="","",AE3*Q3*K3%) -> 4.3654114e+09 | AG3: =(Tabla6[[#This Row],[Fecha Vto]]-TODAY())/365 -> 20.630137 | AJ3: =IF(C3="","",IF(G3="UVR",Q3*AI3-S3,0)) -> 0
A4: =IF(C4="","",YEAR(C4)) -> 2025 | B4: 604 | C4: 45701 | D4: Tesorería | E4: Títulos Recogidos por la Nación | F4: TFIT15260826 | G4: =+_xlfn.XLOOKUP(F4,Emisiones[Mnemotécnico SEN],Emisiones[Moneda],"",0,1) -> COP | J4: =+_xlfn.XLOOKUP(F4,Emisiones[Mnemotécnico SEN],Emisiones[Fecha Vencim.],"",0,1) -> 46260 | K4: =+_xlfn.XLOOKUP(F4,Emisiones[Mnemotécnico SEN],Emisiones[Tasa de Interés],"",0,1) -> 7.5 | L4: 8.701 | M4: 101.78 | N4: =IF(C4="","",PRICE(C4,J4,K4%,L4%,100,1,3)) -> 98.266523 | O4: =IF(C4="","",M4-N4) -> 3.5134768 | P4: =IF(C4="","",100*K4%-O4) -> 3.9865232 | Q4: =IF(C4="","",IF(G4="UVR",S4/V4,S4)) -> -435000000000 | R4: =IF(C4="","",IF('Canjes desagregado'!$G4="UVR",'Canjes desagregado'!$V4*Q4*M4%,Q4*M4%)) -> -442743000000 | S4: -435000000000 | T4: =IFERROR(IF(RIGHT(F4,2)=RIGHT(YEAR(J4),2),1,0),"") -> 1 | U4: =+IF(R4="","",R4) -> -442743000000 | V4: =+IF(F4<>"",(_xlfn.XLOOKUP(C4,UVR[Fecha (dd/mm/aaaa)],UVR[Pesos colombianos por UVR],"",0,1)),"") -> 378.8914 | W4: =IF(C4="","",IF(CONCATENATE(DAY(C4),"/",MONTH(C4),"/",2000)-CONCATENATE(DAY(J4),"/",MONTH(J4),"/",2000)<0,K4%*ABS(S4),0)) -> 32625000000 | X4: =IF(S4<0,-W4,W4) -> -32625000000 | AB4: =IF(C4="","",ROUND(V4*(1+'Inflación observada '!$B$390%)^(("31-12-2025"-C4)/365),3)) -> 396.232 | AD4: =IF(C4="","",IF(G4="UVR",Q4*AB4-S4,0)) -> 0 | AE4: =IF(C4="","",P4/+(O4+P4)) -> 0.53153642 | AF4: =IF(C4="","",AE4*Q4*K4%) -> -1.7341376e+10 | AG4: =(Tabla6[[#This Row],[Fecha Vto]]-TODAY())/365 -> 0.70410959 | AJ4: =IF(C4="","",IF(G4="UVR",Q4*AI4-S4,0)) -> 0
A5: =IF(C5="","",YEAR(C5)) -> 2025 | B5: 604 | C5: 45701 | D5: Tesorería | E5: Títulos Entregados por la Nación | F5: TFIT16180930 | G5: =+_xlfn.XLOOKUP(F5,Emisiones[Mnemotécnico SEN],Emisiones[Moneda],"",0,1) -> COP | J5: =+_xlfn.XLOOKUP(F5,Emisiones[Mnemotécnico SEN],Emisiones[Fecha Vencim.],"",0,1) -> 47744 | K5: =+_xlfn.XLOOKUP(F5,Emisiones[Mnemotécnico SEN],Emisiones[Tasa de Interés],"",0,1) -> 7.75 | L5: 10.872 | M5: 90.451 | N5: =IF(C5="","",PRICE(C5,J5,K5%,L5%,100,1,3)) -> 87.308013 | O5: =IF(C5="","",M5-N5) -> 3.1429867 | P5: =IF(C5="","",100*K5%-O5) -> 4.6070133 | Q5: =IF(C5="","",IF(G5="UVR",S5/V5,S5)) -> 65000000000 | R5: =IF(C5="","",IF('Canjes desagregado'!$G5="UVR",'Canjes desagregado'!$V5*Q5*M5%,Q5*M5%)) -> 5.879315e+10 | S5: 65000000000 | T5: =IFERROR(IF(RIGHT(F5,2)=RIGHT(YEAR(J5),2),1,0),"") -> 1 | U5: =+IF(R5="","",R5) -> 5.879315e+10 | V5: =+IF(F5<>"",(_xlfn.XLOOKUP(C5,UVR[Fecha (dd/mm/aaaa)],UVR[Pesos colombianos por UVR],"",0,1)),"") -> 378.8914 | W5: =IF(C5="","",IF(CONCATENATE(DAY(C5),"/",MONTH(C5),"/",2000)-CONCATENATE(DAY(J5),"/",MONTH(J5),"/",2000)<0,K5%*ABS(S5),0)) -> 5037500000 | X5: =IF(S5<0,-W5,W5) -> 5037500000 | AB5: =IF(C5="","",ROUND(V5*(1+'Inflación observada '!$B$390%)^(("31-12-2025"-C5)/365),3)) -> 396.232 | AD5: =IF(C5="","",IF(G5="UVR",Q5*AB5-S5,0)) -> 0 | AE5: =IF(C5="","",P5/+(O5+P5)) -> 0.59445332 | AF5: =IF(C5="","",AE5*Q5*K5%) -> 2.9945586e+09 | AG5: =(Tabla6[[#This Row],[Fecha Vto]]-TODAY())/365 -> 4.769863 | AJ5: =IF(C5="","",IF(G5="UVR",Q5*AI5-S5,0)) -> 0
A6: =IF(C6="","",YEAR(C6)) -> 2025 | B6: 604 | C6: 45701 | D6: Tesorería | E6: Títulos Entregados por la Nación | F6: TFIT23250746 | G6: =+_xlfn.XLOOKUP(F6,Emisiones[Mnemotécnico SEN],Emisiones[Moneda],"",0,1) -> COP | J6: =+_xlfn.XLOOKUP(F6,Emisiones[Mnemotécnico SEN],Emisiones[Fecha Vencim.],"",0,1) -> 53533 | K6: =+_xlfn.XLOOKUP(F6,Emisiones[Mnemotécnico SEN],Emisiones[Tasa de Interés],"",0,1) -> 11.5 | L6: 12.569 | M6: 98.394 | N6: =IF(C6="","",PRICE(C6,J6,K6%,L6%,100,1,3)) -> 91.998099 | O6: =IF(C6="","",M6-N6) -> 6.3959006 | P6: =IF(C6="","",100*K6%-O6) -> 5.1040994 | Q6: =IF(C6="","",IF(G6="UVR",S6/V6,S6)) -> 370000000000 | R6: =IF(C6="","",IF('Canjes desagregado'!$G6="UVR",'Canjes desagregado'!$V6*Q6*M6%,Q6*M6%)) -> 364057800000 | S6: 370000000000 | T6: =IFERROR(IF(RIGHT(F6,2)=RIGHT(YEAR(J6),2),1,0),"") -> 1 | U6: =+IF(R6="","",R6) -> 364057800000 | V6: =+IF(F6<>"",(_xlfn.XLOOKUP(C6,UVR[Fecha (dd/mm/aaaa)],UVR[Pesos colombianos por UVR],"",0,1)),"") -> 378.8914 | W6: =IF(C6="","",IF(CONCATENATE(DAY(C6),"/",MONTH(C6),"/",2000)-CONCATENATE(DAY(J6),"/",MONTH(J6),"/",2000)<0,K6%*ABS(S6),0)) -> 42550000000 | X6: =IF(S6<0,-W6,W6) -> 42550000000 | AB6: =IF(C6="","",ROUND(V6*(1+'Inflación observada '!$B$390%)^(("31-12-2025"-C6)/365),3)) -> 396.232 | AD6: =IF(C6="","",IF(G6="UVR",Q6*AB6-S6,0)) -> 0 | AE6: =IF(C6="","",P6/+(O6+P6)) -> 0.44383473 | AF6: =IF(C6="","",AE6*Q6*K6%) -> 1.8885168e+10 | AG6: =(Tabla6[[#This Row],[Fecha Vto]]-TODAY())/365 -> 20.630137 | AJ6: =IF(C6="","",IF(G6="UVR",Q6*AI6-S6,0)) -> 0
A7: =IF(C7="","",YEAR(C7)) -> 2025 | B7: 605 | C7: 45702 | D7: Tesorería | E7: Títulos Recogidos por la Nación | F7: TFIT15260826 | G7: =+_xlfn.XLOOKUP(F7,Emisiones[Mnemotécnico SEN],Emisiones[Moneda],"",0,1) -> COP | J7: =+_xlfn.XLOOKUP(F7,Emisiones[Mnemotécnico SEN],Emisiones[Fecha Vencim.],"",0,1) -> 46260 | K7: =+_xlfn.XLOOKUP(F7,Emisiones[Mnemotécnico SEN],Emisiones[Tasa de Interés],"",0,1) -> 7.5 | L7: 8.751 | M7: 101.735 | N7: =IF(C7="","",PRICE(C7,J7,K7%,L7%,100,1,3)) -> 98.200995 | O7: =IF(C7="","",M7-N7) -> 3.5340052 | P7: =IF(C7="","",100*K7%-O7) -> 3.9659948 | Q7: =IF(C7="","",IF(G7="UVR",S7/V7,S7)) -> -85000000000 | R7: =IF(C7="","",IF('Canjes desagregado'!$G7="UVR",'Canjes desagregado'!$V7*Q7*M7%,Q7*M7%)) -> -86474750000 | S7: -85000000000 | T7: =IFERROR(IF(RIGHT(F7,2)=RIGHT(YEAR(J7),2),1,0),"") -> 1 | U7: =+IF(R7="","",R7) -> -86474750000 | V7: =+IF(F7<>"",(_xlfn.XLOOKUP(C7,UVR[Fecha (dd/mm/aaaa)],UVR[Pesos colombianos por UVR],"",0,1)),"") -> 378.9475 | W7: =IF(C7="","",IF(CONCATENATE(DAY(C7),"/",MONTH(C7),"/",2000)-CONCATENATE(DAY(J7),"/",MONTH(J7),"/",2000)<0,K7%*ABS(S7),0)) -> 6375000000 | X7: =IF(S7<0,-W7,W7) -> -6375000000 | AB7: =IF(C7="","",ROUND(V7*(1+'Inflación observada '!$B$390%)^(("31-12-2025"-C7)/365),3)) -> 396.235 | AD7: =IF(C7="","",IF(G7="UVR",Q7*AB7-S7,0)) -> 0 | AE7: =IF(C7="","",P7/+(O7+P7)) -> 0.5287993 | AF7: =IF(C7="","",AE7*Q7*K7%) -> -3.3710955e+09 | AG7: =(Tabla6[[#This Row],[Fecha Vto]]-TODAY())/365 -> 0.70410959 | AJ7: =IF(C7="","",IF(G7="UVR",Q7*AI7-S7,0)) -> 0
A8: =IF(C8="","",YEAR(C8)) -> 2025 | B8: 605 | C8: 45702 | D8: Tesorería | E8: Títulos Entregados por la Nación | F8: TFIT16180930 | G8: =+_xlfn.XLOOKUP(F8,Emisiones[Mnemotécnico SEN],Emisiones[Moneda],"",0,1) -> COP | J8: =+_xlfn.XLOOKUP(F8,Emisiones[Mnemotécnico SEN],Emisiones[Fecha Vencim.],"",0,1) -> 47744 | K8: =+_xlfn.XLOOKUP(F8,Emisiones[Mnemotécnico SEN],Emisiones[Tasa de Interés],"",0,1) -> 7.75 | L8: 10.784 | M8: 90.802 | N8: =IF(C8="","",PRICE(C8,J8,K8%,L8%,100,1,3)) -> 87.638458 | O8: =IF(C8="","",M8-N8) -> 3.1635423 | P8: =IF(C8="","",100*K8%-O8) -> 4.5864577 | Q8: =IF(C8="","",IF(G8="UVR",S8/V8,S8)) -> 15000000000 | R8: =IF(C8="","",IF('Canjes desagregado'!$G8="UVR",'Canjes desagregado'!$V8*Q8*M8%,Q8*M8%)) -> 13620300000 | S8: 15000000000 | T8: =IFERROR(IF(RIGHT(F8,2)=RIGHT(YEAR(J8),2),1,0),"") -> 1 | U8: =+IF(R8="","",R8) -> 13620300000 | V8: =+IF(F8<>"",(_xlfn.XLOOKUP(C8,UVR[Fecha (dd/mm/aaaa)],UVR[Pesos colombianos por UVR],"",0,1)),"") -> 378.9475 | W8: =IF(C8="","",IF(CONCATENATE(DAY(C8),"/",MONTH(C8),"/",2000)-CONCATENATE(DAY(J8),"/",MONTH(J8),"/",2000)<0,K8%*ABS(S8),0)) -> 1162500000 | X8: =IF(S8<0,-W8,W8) -> 1162500000 | AB8: =IF(C8="","",ROUND(V8*(1+'Inflación observada '!$B$390%)^(("31-12-2025"-C8)/365),3)) -> 396.235 | AD8: =IF(C8="","",IF(G8="UVR",Q8*AB8-S8,0)) -> 0 | AE8: =IF(C8="","",P8/+(O8+P8)) -> 0.59180099 | AF8: =IF(C8="","",AE8*Q8*K8%) -> 6.8796865e+08 | AG8: =(Tabla6[[#This Row],[Fecha Vto]]-TODAY())/365 -> 4.769863 | AJ8: =IF(C8="","",IF(G8="UVR",Q8*AI8-S8,0)) -> 0
A9: =IF(C9="","",YEAR(C9)) -> 2025 | B9: 605 | C9: 45702 | D9: Tesorería | E9: Títulos Entregados por la Nación | F9: TFIT23250746 | G9: =+_xlfn.XLOOKUP(F9,Emisiones[Mnemotécnico SEN],Emisiones[Moneda],"",0,1) -> COP | J9: =+_xlfn.XLOOKUP(F9,Emisiones[Mnemotécnico SEN],Emisiones[Fecha Vencim.],"",0,1) -> 53533 | K9: =+_xlfn.XLOOKUP(F9,Emisiones[Mnemotécnico SEN],Emisiones[Tasa de Interés],"",0,1) -> 11.5 | L9: 12.52 | M9: 98.763 | N9: =IF(C9="","",PRICE(C9,J9,K9%,L9%,100,1,3)) -> 92.334973 | O9: =IF(C9="","",M9-N9) -> 6.4280265 | P9: =IF(C9="","",100*K9%-O9) -> 5.0719735 | Q9: =IF(C9="","",IF(G9="UVR",S9/V9,S9)) -> 70000000000 | R9: =IF(C9="","",IF('Canjes desagregado'!$G9="UVR",'Canjes desagregado'!$V9*Q9*M9%,Q9*M9%)) -> 69134100000 | S9: 70000000000 | T9: =IFERROR(IF(RIGHT(F9,2)=RIGHT(YEAR(J9),2),1,0),"") -> 1 | U9: =+IF(R9="","",R9) -> 69134100000 | V9: =+IF(F9<>"",(_xlfn.XLOOKUP(C9,UVR[Fecha (dd/mm/aaaa)],UVR[Pesos colombianos por UVR],"",0,1)),"") -> 378.9475 | W9: =IF(C9="","",IF(CONCATENATE(DAY(C9),"/",MONTH(C9),"/",2000)-CONCATENATE(DAY(J9),"/",MONTH(J9),"/",2000)<0,K9%*ABS(S9),0)) -> 8050000000 | X9: =IF(S9<0,-W9,W9) -> 8050000000 | AB9: =IF(C9="","",ROUND(V9*(1+'Inflación observada '!$B$390%)^(("31-12-2025"-C9)/365),3)) -> 396.235 | AD9: =IF(C9="","",IF(G9="UVR",Q9*AB9-S9,0)) -> 0 | AE9: =IF(C9="","",P9/+(O9+P9)) -> 0.44104117 | AF9: =IF(C9="","",AE9*Q9*K9%) -> 3.5503814e+09 | AG9: =(Tabla6[[#This Row],[Fecha Vto]]-TODAY())/365 -> 20.630137 | AJ9: =IF(C9="","",IF(G9="UVR",Q9*AI9-S9,0)) -> 0
A10: =IF(C10="","",YEAR(C10)) -> 2025 | B10: 606 | C10: 45706 | D10: Tesorería | E10: Títulos Recogidos por la Nación | F10: TFIT15260826 | G10: =+_xlfn.XLOOKUP(F10,Emisiones[Mnemotécnico SEN],Emisiones[Moneda],"",0,1) -> COP | J10: =+_xlfn.XLOOKUP(F10,Emisiones[Mnemotécnico SEN],Emisiones[Fecha Vencim.],"",0,1) -> 46260 | K10: =+_xlfn.XLOOKUP(F10,Emisiones[Mnemotécnico SEN],Emisiones[Tasa de Interés],"",0,1) -> 7.5 | L10: 8.8 | M10: 101.762 | N10: =IF(C10="","",PRICE(C10,J10,K10%,L10%,100,1,3)) -> 98.146011 | O10: =IF(C10="","",M10-N10) -> 3.6159895 | P10: =IF(C10="","",100*K10%-O10) -> 3.8840105 | Q10: =IF(C10="","",IF(G10="UVR",S10/V10,S10)) -> -594000000000 | R10: =IF(C10="","",IF('Canjes desagregado'!$G10="UVR",'Canjes desagregado'!$V10*Q10*M10%,Q10*M10%)) -> -604466280000 | S10: -594000000000 | T10: =IFERROR(IF(RIGHT(F10,2)=RIGHT(YEAR(J10),2),1,0),"") -> 1 | U10: =+IF(R10="","",R10) -> -604466280000 | V10: =+IF(F10<>"",(_xlfn.XLOOKUP(C10,UVR[Fecha (dd/mm/aaaa)],UVR[Pesos colombianos por UVR],"",0,1)),"") -> 379.3837 | W10: =IF(C10="","",IF(CONCATENATE(DAY(C10),"/",MONTH(C10),"/",2000)-CONCATENATE(DAY(J10),"/",MONTH(J10),"/",2000)<0,K10%*ABS(S10),0)) -> 44550000000 | X10: =IF(S10<0,-W10,W10) -> -44550000000 | AB10: =IF(C10="","",ROUND(V10*(1+'Inflación observada '!$B$390%)^(("31-12-2025"-C10)/365),3)) -> 396.47 | AD10: =IF(C10="","",IF(G10="UVR",Q10*AB10-S10,0)) -> 0 | AE10: =IF(C10="","",P10/+(O10+P10)) -> 0.51786807 | AF10: =IF(C10="","",AE10*Q10*K10%) -> -2.3071022e+10 | AG10: =(Tabla6[[#This Row],[Fecha Vto]]-TODAY())/365 -> 0.70410959 | AJ10: =IF(C10="","",IF(G10="UVR",Q10*AI10-S10,0)) -> 0
A11: =IF(C11="","",YEAR(C11)) -> 2025 | B11: 606 | C11: 45706 | D11: Tesorería | E11: Títulos Entregados por la Nación | F11: TFIT23250746 | G11: =+_xlfn.XLOOKUP(F11,Emisiones[Mnemotécnico SEN],Emisiones[Moneda],"",0,1) -> COP | J11: =+_xlfn.XLOOKUP(F11,Emisiones[Mnemotécnico SEN],Emisiones[Fecha Vencim.],"",0,1) -> 53533 | K11: =+_xlfn.XLOOKUP(F11,Emisiones[Mnemotécnico SEN],Emisiones[Tasa de Interés],"",0,1) -> 11.5 | L11: 12.695 | M11: 97.698 | N11: =IF(C11="","",PRICE(C11,J11,K11%,L11%,100,1,3)) -> 91.144772 | O11: =IF(C11="","",M11-N11) -> 6.5532285 | P11: =IF(C11="","",100*K11%-O11) -> 4.9467715 | Q11: =IF(C11="","",IF(G11="UVR",S11/V11,S11)) -> 594000000000 | R11: =IF(C11="","",IF('Canjes desagregado'!$G11="UVR",'Canjes desagregado'!$V11*Q11*M11%,Q11*M11%)) -> 580326120000 | S11: 594000000000 | T11: =IFERROR(IF(RIGHT(F11,2)=RIGHT(YEAR(J11),2),1,0),"") -> 1 | U11: =+IF(R11="","",R11) -> 580326120000 | V11: =+IF(F11<>"",(_xlfn.XLOOKUP(C11,UVR[Fecha (dd/mm/aaaa)],UVR[Pesos colombianos por UVR],"",0,1)),"") -> 379.3837 | W11: =IF(C11="","",IF(CONCATENATE(DAY(C11),"/",MONTH(C11),"/",2000)-CONCATENATE(DAY(J11),"/",MONTH(J11),"/",2000)<0,K11%*ABS(S11),0)) -> 68310000000 | X11: =IF(S11<0,-W11,W11) -> 68310000000 | AB11: =IF(C11="","",ROUND(V11*(1+'Inflación observada '!$B$390%)^(("31-12-2025"-C11)/365),3)) -> 396.47 | AD11: =IF(C11="","",IF(G11="UVR",Q11*AB11-S11,0)) -> 0 | AE11: =IF(C11="","",P11/+(O11+P11)) -> 0.43015404 | AF11: =IF(C11="","",AE11*Q11*K11%) -> 2.9383823e+10 | AG11: =(Tabla6[[#This Row],[Fecha Vto]]-TODAY())/365 -> 20.630137 | AJ11: =IF(C11="","",IF(G11="UVR",Q11*AI11-S11,0)) -> 0
A12: =IF(C12="","",YEAR(C12)) -> 2025 | B12: 607 | C12: 45707 | D12: Tesorería | E12: Títulos Recogidos por la Nación | F12: TFIT15260826 | G12: =+_xlfn.XLOOKUP(F12,Emisiones[Mnemotécnico SEN],Emisiones[Moneda],"",0,1) -> COP | J12: =+_xlfn.XLOOKUP(F12,Emisiones[Mnemotécnico SEN],Emisiones[Fecha Vencim.],"",0,1) -> 46260 | K12: =+_xlfn.XLOOKUP(F12,Emisiones[Mnemotécnico SEN],Emisiones[Tasa de Interés],"",0,1) -> 7.5 | L12: 8.861 | M12: 101.704 | N12: =IF(C12="","",PRICE(C12,J12,K12%,L12%,100,1,3)) -> 98.066602 | O12: =IF(C12="","",M12-N12) -> 3.6373978 | P12: =IF(C12="","",100*K12%-O12) -> 3.8626022 | Q12: =IF(C12="","",IF(G12="UVR",S12/V12,S12)) -> -456000000000 | R12: =IF(C12="","",IF('Canjes desagregado'!$G12="UVR",'Canjes desagregado'!$V12*Q12*M12%,Q12*M12%)) -> -463770240000 | S12: -456000000000 | T12: =IFERROR(IF(RIGHT(F12,2)=RIGHT(YEAR(J12),2),1,0),"") -> 1 | U12: =+IF(R12="","",R12) -> -463770240000 | V12: =+IF(F12<>"",(_xlfn.XLOOKUP(C12,UVR[Fecha (dd/mm/aaaa)],UVR[Pesos colombianos por UVR],"",0,1)),"") -> 379.5105 | W12: =IF(C12="","",IF(CONCATENATE(DAY(C12),"/",MONTH(C12),"/",2000)-CONCATENATE(DAY(J12),"/",MONTH(J12),"/",2000)<0,K12%*ABS(S12),0)) -> 34200000000 | X12: =IF(S12<0,-W12,W12) -> -34200000000 | AB12: =IF(C12="","",ROUND(V12*(1+'Inflación observada '!$B$390%)^(("31-12-2025"-C12)/365),3)) -> 396.547 | AD12: =IF(C12="","",IF(G12="UVR",Q12*AB12-S12,0)) -> 0 | AE12: =IF(C12="","",P12/+(O12+P12)) -> 0.51501363 | AF12: =IF(C12="","",AE12*Q12*K12%) -> -1.7613466e+10 | AG12: =(Tabla6[[#This Row],[Fecha Vto]]-TODAY())/365 -> 0.70410959 | AJ12: =IF(C12="","",IF(G12="UVR",Q12*AI12-S12,0)) -> 0
A13: =IF(C13="","",YEAR(C13)) -> 2025 | B13: 607 | C13: 45707 | D13: Tesorería | E13: Títulos Entregados por la Nación | F13: TFIT23250746 | G13: =+_xlfn.XLOOKUP(F13,Emisiones[Mnemotécnico SEN],Emisiones[Moneda],"",0,1) -> COP | J13: =+_xlfn.XLOOKUP(F13,Emisiones[Mnemotécnico SEN],Emisiones[Fecha Vencim.],"",0,1) -> 53533 | K13: =+_xlfn.XLOOKUP(F13,Emisiones[Mnemotécnico SEN],Emisiones[Tasa de Interés],"",0,1) -> 11.5 | L13: 12.697 | M13: 97.717 | N13: =IF(C13="","",PRICE(C13,J13,K13%,L13%,100,1,3)) -> 91.131791 | O13: =IF(C13="","",M13-N13) -> 6.5852089 | P13: =IF(C13="","",100*K13%-O13) -> 4.9147911 | Q13: =IF(C13="","",IF(G13="UVR",S13/V13,S13)) -> 456000000000 | R13: =IF(C13="","",IF('Canjes desagregado'!$G13="UVR",'Canjes desagregado'!$V13*Q13*M13%,Q13*M13%)) -> 445589520000 | S13: 456000000000 | T13: =IFERROR(IF(RIGHT(F13,2)=RIGHT(YEAR(J13),2),1,0),"") -> 1 | U13: =+IF(R13="","",R13) -> 445589520000 | V13: =+IF(F13<>"",(_xlfn.XLOOKUP(C13,UVR[Fecha (dd/mm/aaaa)],UVR[Pesos colombianos por UVR],"",0,1)),"") -> 379.5105 | W13: =IF(C13="","",IF(CONCATENATE(DAY(C13),"/",MONTH(C13),"/",2000)-CONCATENATE(DAY(J13),"/",MONTH(J13),"/",2000)<0,K13%*ABS(S13),0)) -> 52440000000 | X13: =IF(S13<0,-W13,W13) -> 52440000000 | AB13: =IF(C13="","",ROUND(V13*(1+'Inflación observada '!$B$390%)^(("31-12-2025"-C13)/365),3)) -> 396.547 | AD13: =IF(C13="","",IF(G13="UVR",Q13*AB13-S13,0)) -> 0 | AE13: =IF(C13="","",P13/+(O13+P13)) -> 0.42737314 | AF13: =IF(C13="","",AE13*Q13*K13%) -> 2.2411448e+10 | AG13: =(Tabla6[[#This Row],[Fecha Vto]]-TODAY())/365 -> 20.630137 | AJ13: =IF(C13="","",IF(G13="UVR",Q13*AI13-S13,0)) -> 0
... A37: =IF(C37="","",YEAR(C37)) -> 2025 | B37: 617 | C37: 45722 | D37: Tesorería | E37: Títulos Entregados por la Nación | F37: TFIT23250746 | G37: =+_xlfn.XLOOKUP(F37,Emisiones[Mnemotécnico SEN],Emisiones[Moneda],"",0,1) -> COP | J37: =+_xlfn.XLOOKUP(F37,Emisiones[Mnemotécnico SEN],Emisiones[Fecha Vencim.],"",0,1) -> 53533 | K37: =+_xlfn.XLOOKUP(F37,Emisiones[Mnemotécnico SEN],Emisiones[Tasa de Interés],"",0,1) -> 11.5 | L37: 12.439 | M37: 99.964 | N37: =IF(C37="","",PRICE(C37,J37,K37%,L37%,100,1,3)) -> 92.905789 | O37: =IF(C37="","",M37-N37) -> 7.0582112 | P37: =IF(C37="","",100*K37%-O37) -> 4.4417888 | Q37: =IF(C37="","",IF(G37="UVR",S37/V37,S37)) -> 200000000000 | R37: =IF(C37="","",IF('Canjes desagregado'!$G37="UVR",'Canjes desagregado'!$V37*Q37*M37%,Q37*M37%)) -> 199928000000 | S37: 200000000000 | T37: =IFERROR(IF(RIGHT(F37,2)=RIGHT(YEAR(J37),2),1,0),"") -> 1 | U37: =+IF(R37="","",R37) -> 199928000000 | V37: =+IF(F37<>"",(_xlfn.XLOOKUP(C37,UVR[Fecha (dd/mm/aaaa)],UVR[Pesos colombianos por UVR],"",0,1)),"") -> 381.4175 | W37: =IF(C37="","",IF(CONCATENATE(DAY(C37),"/",MONTH(C37),"/",2000)-CONCATENATE(DAY(J37),"/",MONTH(J37),"/",2000)<0,K37%*ABS(S37),0)) -> 23000000000 | X37: =IF(S37<0,-W37,W37) -> 23000000000 | AB37: =IF(C37="","",ROUND(V37*(1+'Inflación observada '!$B$390%)^(("31-12-2025"-C37)/365),3)) -> 397.707 | AD37: =IF(C37="","",IF(G37="UVR",Q37*AB37-S37,0)) -> 0 | AE37: =IF(C37="","",P37/+(O37+P37)) -> 0.3862425 | AF37: =IF(C37="","",AE37*Q37*K37%) -> 8.8835775e+09 | AG37: =(Tabla6[[#This Row],[Fecha Vto]]-TODAY())/365 -> 20.630137 | AJ37: =IF(C37="","",IF(G37="UVR",Q37*AI37-S37,0)) -> 0
A38: =IF(C38="","",YEAR(C38)) -> 2025 | B38: 618 | C38: 45723 | D38: Tesorería | E38: Títulos Recogidos por la Nación | F38: TUVT11070525 | G38: =+_xlfn.XLOOKUP(F38,Emisiones[Mnemotécnico SEN],Emisiones[Moneda],"",0,1) -> UVR | J38: =+_xlfn.XLOOKUP(F38,Emisiones[Mnemotécnico SEN],Emisiones[Fecha Vencim.],"",0,1) -> 45784 | K38: =+_xlfn.XLOOKUP(F38,Emisiones[Mnemotécnico SEN],Emisiones[Tasa de Interés],"",0,1) -> 3.5 | L38: -0.697 | M38: 103.621 | N38: 98.569 | O38: =IF(C38="","",M38-N38) -> 5.052 | P38: =IF(C38="","",100*K38%-O38) -> -1.552 | Q38: =IF(C38="","",IF(G38="UVR",S38/V38,S38)) -> -135000000 | R38: =IF(C38="","",IF('Canjes desagregado'!$G38="UVR",'Canjes desagregado'!$V38*Q38*M38%,Q38*M38%)) -> -5.3373687e+10 | S38: -51508561500 | T38: =IFERROR(IF(RIGHT(F38,2)=RIGHT(YEAR(J38),2),1,0),"") -> 1 | U38: =+IF(R38="","",R38) -> -5.3373687e+10 | V38: =+IF(F38<>"",(_xlfn.XLOOKUP(C38,UVR[Fecha (dd/mm/aaaa)],UVR[Pesos colombianos por UVR],"",0,1)),"") -> 381.5449 | W38: =IF(C38="","",IF(CONCATENATE(DAY(C38),"/",MONTH(C38),"/",2000)-CONCATENATE(DAY(J38),"/",MONTH(J38),"/",2000)<0,K38%*ABS(S38),0)) -> 1.8027997e+09 | X38: =IF(S38<0,-W38,W38) -> -1.8027997e+09 | AB38: =IF(C38="","",ROUND(V38*(1+'Inflación observada '!$B$390%)^(("31-12-2025"-C38)/365),3)) -> 397.785 | AD38: =IF(C38="","",IF(G38="UVR",Q38*AB38-S38,0)) -> -2192413500 | AE38: =IF(C38="","",P38/+(O38+P38)) -> -0.44342857 | AF38: =IF(C38="","",AE38*Q38*K38%) -> 2095200 | AG38: =(Tabla6[[#This Row],[Fecha Vto]]-TODAY())/365 -> -0.6 | AJ38: =IF(C38="","",IF(G38="UVR",Q38*AI38-S38,0)) -> 51508561500
A39: =IF(C39="","",YEAR(C39)) -> 2025 | B39: 618 | C39: 45723 | D39: Tesorería | E39: Títulos Entregados por la Nación | F39: TUVT31190555 | G39: =+_xlfn.XLOOKUP(F39,Emisiones[Mnemotécnico SEN],Emisiones[Moneda],"",0,1) -> UVR | J39: =+_xlfn.XLOOKUP(F39,Emisiones[Mnemotécnico SEN],Emisiones[Fecha Vencim.],"",0,1) -> 56753 | K39: =+_xlfn.XLOOKUP(F39,Emisiones[Mnemotécnico SEN],Emisiones[Tasa de Interés],"",0,1) -> 5.25 | L39: 5.345 | M39: 102.77 | N39: =IF(C39="","",PRICE(C39,J39,K39%,L39%,100,1,3)) -> 98.569493 | O39: =IF(C39="","",M39-N39) -> 4.200507 | P39: =IF(C39="","",100*K39%-O39) -> 1.049493 | Q39: =IF(C39="","",IF(G39="UVR",S39/V39,S39)) -> 135000000 | R39: =IF(C39="","",IF('Canjes desagregado'!$G39="UVR",'Canjes desagregado'!$V39*Q39*M39%,Q39*M39%)) -> 5.2935349e+10 | S39: 51508561500 | T39: =IFERROR(IF(RIGHT(F39,2)=RIGHT(YEAR(J39),2),1,0),"") -> 1 | U39: =+IF(R39="","",R39) -> 5.2935349e+10 | V39: =+IF(F39<>"",(_xlfn.XLOOKUP(C39,UVR[Fecha (dd/mm/aaaa)],UVR[Pesos colombianos por UVR],"",0,1)),"") -> 381.5449 | W39: =IF(C39="","",IF(CONCATENATE(DAY(C39),"/",MONTH(C39),"/",2000)-CONCATENATE(DAY(J39),"/",MONTH(J39),"/",2000)<0,K39%*ABS(S39),0)) -> 2.7041995e+09 | X39: =IF(S39<0,-W39,W39) -> 2.7041995e+09 | AB39: =IF(C39="","",ROUND(V39*(1+'Inflación observada '!$B$390%)^(("31-12-2025"-C39)/365),3)) -> 397.785 | AD39: =IF(C39="","",IF(G39="UVR",Q39*AB39-S39,0)) -> 2192413500 | AE39: =IF(C39="","",P39/+(O39+P39)) -> 0.19990342 | AF39: =IF(C39="","",AE39*Q39*K39%) -> 1416815.5 | AG39: =(Tabla6[[#This Row],[Fecha Vto]]-TODAY())/365 -> 29.452055 | AJ39: =IF(C39="","",IF(G39="UVR",Q39*AI39-S39,0)) -> -51508561500
A40: =IF(C40="","",YEAR(C40)) -> 2025 | B40: 619 | C40: 45726 | D40: Tesorería | E40: Títulos Recogidos por la Nación | F40: TUVT11070525 | G40: =+_xlfn.XLOOKUP(F40,Emisiones[Mnemotécnico SEN],Emisiones[Moneda],"",0,1) -> UVR | J40: =+_xlfn.XLOOKUP(F40,Emisiones[Mnemotécnico SEN],Emisiones[Fecha Vencim.],"",0,1) -> 45784 | K40: =+_xlfn.XLOOKUP(F40,Emisiones[Mnemotécnico SEN],Emisiones[Tasa de Interés],"",0,1) -> 3.5 | L40: -1.032 | M40: 103.671 | N40: 101.727 | O40: =IF(C40="","",M40-N40) -> 1.944 | P40: =IF(C40="","",100*K40%-O40) -> 1.556 | Q40: =IF(C40="","",IF(G40="UVR",S40/V40,S40)) -> -205000000 | R40: =IF(C40="","",IF('Canjes desagregado'!$G40="UVR",'Canjes desagregado'!$V40*Q40*M40%,Q40*M40%)) -> -8.1169373e+10 | S40: -78295158000 | T40: =IFERROR(IF(RIGHT(F40,2)=RIGHT(YEAR(J40),2),1,0),"") -> 1 | U40: =+IF(R40="","",R40) -> -8.1169373e+10 | V40: =+IF(F40<>"",(_xlfn.XLOOKUP(C40,UVR[Fecha (dd/mm/aaaa)],UVR[Pesos colombianos por UVR],"",0,1)),"") -> 381.9276 | W40: =IF(C40="","",IF(CONCATENATE(DAY(C40),"/",MONTH(C40),"/",2000)-CONCATENATE(DAY(J40),"/",MONTH(J40),"/",2000)<0,K40%*ABS(S40),0)) -> 2.7403305e+09 | X40: =IF(S40<0,-W40,W40) -> -2.7403305e+09 | AB40: =IF(C40="","",ROUND(V40*(1+'Inflación observada '!$B$391%)^(("31-12-2025"-C40)/365),3)) -> 398.201 | AD40: =IF(C40="","",IF(G40="UVR",Q40*AB40-S40,0)) -> -3336047000 | AE40: =IF(C40="","",P40/+(O40+P40)) -> 0.44457143 | AF40: =IF(C40="","",AE40*Q40*K40%) -> -3189800 | AG40: =(Tabla6[[#This Row],[Fecha Vto]]-TODAY())/365 -> -0.6 | AJ40: =IF(C40="","",IF(G40="UVR",Q40*AI40-S40,0)) -> 78295158000
A41: =IF(C41="","",YEAR(C41)) -> 2025 | B41: 619 | C41: 45726 | D41: Tesorería | E41: Títulos Entregados por la Nación | F41: TUVT31190555 | G41: =+_xlfn.XLOOKUP(F41,Emisiones[Mnemotécnico SEN],Emisiones[Moneda],"",0,1) -> UVR | J41: =+_xlfn.XLOOKUP(F41,Emisiones[Mnemotécnico SEN],Emisiones[Fecha Vencim.],"",0,1) -> 56753 | K41: =+_xlfn.XLOOKUP(F41,Emisiones[Mnemotécnico SEN],Emisiones[Tasa de Interés],"",0,1) -> 5.25 | L41: 5.385 | M41: 102.229 | N41: =IF(C41="","",PRICE(C41,J41,K41%,L41%,100,1,3)) -> 97.986117 | O41: =IF(C41="","",M41-N41) -> 4.2428831 | P41: =IF(C41="","",100*K41%-O41) -> 1.0071169 | Q41: =IF(C41="","",IF(G41="UVR",S41/V41,S41)) -> 205000000 | R41: =IF(C41="","",IF('Canjes desagregado'!$G41="UVR",'Canjes desagregado'!$V41*Q41*M41%,Q41*M41%)) -> 8.0040357e+10 | S41: 78295158000 | T41: =IFERROR(IF(RIGHT(F41,2)=RIGHT(YEAR(J41),2),1,0),"") -> 1 | U41: =+IF(R41="","",R41) -> 8.0040357e+10 | V41: =+IF(F41<>"",(_xlfn.XLOOKUP(C41,UVR[Fecha (dd/mm/aaaa)],UVR[Pesos colombianos por UVR],"",0,1)),"") -> 381.9276 | W41: =IF(C41="","",IF(CONCATENATE(DAY(C41),"/",MONTH(C41),"/",2000)-CONCATENATE(DAY(J41),"/",MONTH(J41),"/",2000)<0,K41%*ABS(S41),0)) -> 4110495795 | X41: =IF(S41<0,-W41,W41) -> 4110495795 | AB41: =IF(C41="","",ROUND(V41*(1+'Inflación observada '!$B$391%)^(("31-12-2025"-C41)/365),3)) -> 398.201 | AD41: =IF(C41="","",IF(G41="UVR",Q41*AB41-S41,0)) -> 3336047000 | AE41: =IF(C41="","",P41/+(O41+P41)) -> 0.19183179 | AF41: =IF(C41="","",AE41*Q41*K41%) -> 2064589.7 | AG41: =(Tabla6[[#This Row],[Fecha Vto]]-TODAY())/365 -> 29.452055 | AJ41: =IF(C41="","",IF(G41="UVR",Q41*AI41-S41,0)) -> -78295158000
A42: =IF(C42="","",YEAR(C42)) -> 2025 | B42: 620 | C42: 45727 | D42: Tesorería | E42: Títulos Recogidos por la Nación | F42: TUVT11070525 | G42: =+_xlfn.XLOOKUP(F42,Emisiones[Mnemotécnico SEN],Emisiones[Moneda],"",0,1) -> UVR | J42: =+_xlfn.XLOOKUP(F42,Emisiones[Mnemotécnico SEN],Emisiones[Fecha Vencim.],"",0,1) -> 45784 | K42: =+_xlfn.XLOOKUP(F42,Emisiones[Mnemotécnico SEN],Emisiones[Tasa de Interés],"",0,1) -> 3.5 | L42: -1.188 | M42: 103.693 | N42: 100.74 | O42: =IF(C42="","",M42-N42) -> 2.953 | P42: =IF(C42="","",100*K42%-O42) -> 0.547 | Q42: =IF(C42="","",IF(G42="UVR",S42/V42,S42)) -> -465000000 | R42: =IF(C42="","",IF('Canjes desagregado'!$G42="UVR",'Canjes desagregado'!$V42*Q42*M42%,Q42*M42%)) -> -1.8421649e+11 | S42: -177655668000 | T42: =IFERROR(IF(RIGHT(F42,2)=RIGHT(YEAR(J42),2),1,0),"") -> 1 | U42: =+IF(R42="","",R42) -> -1.8421649e+11 | V42: =+IF(F42<>"",(_xlfn.XLOOKUP(C42,UVR[Fecha (dd/mm/aaaa)],UVR[Pesos colombianos por UVR],"",0,1)),"") -> 382.0552 | W42: =IF(C42="","",IF(CONCATENATE(DAY(C42),"/",MONTH(C42),"/",2000)-CONCATENATE(DAY(J42),"/",MONTH(J42),"/",2000)<0,K42%*ABS(S42),0)) -> 6.2179484e+09 | X42: =IF(S42<0,-W42,W42) -> -6.2179484e+09 | AB42: =IF(C42="","",ROUND(V42*(1+'Inflación observada '!$B$391%)^(("31-12-2025"-C42)/365),3)) -> 398.278 | AD42: =IF(C42="","",IF(G42="UVR",Q42*AB42-S42,0)) -> -7543602000 | AE42: =IF(C42="","",P42/+(O42+P42)) -> 0.15628571 | AF42: =IF(C42="","",AE42*Q42*K42%) -> -2543550 | AG42: =(Tabla6[[#This Row],[Fecha Vto]]-TODAY())/365 -> -0.6 | AJ42: =IF(C42="","",IF(G42="UVR",Q42*AI42-S42,0)) -> 177655668000
A43: =IF(C43="","",YEAR(C43)) -> 2025 | B43: 620 | C43: 45727 | D43: Tesorería | E43: Títulos Entregados por la Nación | F43: TUVT31190555 | G43: =+_xlfn.XLOOKUP(F43,Emisiones[Mnemotécnico SEN],Emisiones[Moneda],"",0,1) -> UVR | J43: =+_xlfn.XLOOKUP(F43,Emisiones[Mnemotécnico SEN],Emisiones[Fecha Vencim.],"",0,1) -> 56753 | K43: =+_xlfn.XLOOKUP(F43,Emisiones[Mnemotécnico SEN],Emisiones[Tasa de Interés],"",0,1) -> 5.25 | L43: 5.39 | M43: 102.171 | N43: =IF(C43="","",PRICE(C43,J43,K43%,L43%,100,1,3)) -> 97.913768 | O43: =IF(C43="","",M43-N43) -> 4.257232 | P43: =IF(C43="","",100*K43%-O43) -> 0.992768 | Q43: =IF(C43="","",IF(G43="UVR",S43/V43,S43)) -> 465000000 | R43: =IF(C43="","",IF('Canjes desagregado'!$G43="UVR",'Canjes desagregado'!$V43*Q43*M43%,Q43*M43%)) -> 1.8151257e+11 | S43: 177655668000 | T43: =IFERROR(IF(RIGHT(F43,2)=RIGHT(YEAR(J43),2),1,0),"") -> 1 | U43: =+IF(R43="","",R43) -> 1.8151257e+11 | V43: =+IF(F43<>"",(_xlfn.XLOOKUP(C43,UVR[Fecha (dd/mm/aaaa)],UVR[Pesos colombianos por UVR],"",0,1)),"") -> 382.0552 | W43: =IF(C43="","",IF(CONCATENATE(DAY(C43),"/",MONTH(C43),"/",2000)-CONCATENATE(DAY(J43),"/",MONTH(J43),"/",2000)<0,K43%*ABS(S43),0)) -> 9326922570 | X43: =IF(S43<0,-W43,W43) -> 9326922570 | AB43: =IF(C43="","",ROUND(V43*(1+'Inflación observada '!$B$391%)^(("31-12-2025"-C43)/365),3)) -> 398.278 | AD43: =IF(C43="","",IF(G43="UVR",Q43*AB43-S43,0)) -> 7543602000 | AE43: =IF(C43="","",P43/+(O43+P43)) -> 0.18909867 | AF43: =IF(C43="","",AE43*Q43*K43%) -> 4616371.2 | AG43: =(Tabla6[[#This Row],[Fecha Vto]]-TODAY())/365 -> 29.452055 | AJ43: =IF(C43="","",IF(G43="UVR",Q43*AI43-S43,0)) -> -177655668000
A44: =IF(C44="","",YEAR(C44)) -> 2025 | B44: 621 | C44: 45728 | D44: Tesorería | E44: Títulos Recogidos por la Nación | F44: TFIT08261125 | G44: =+_xlfn.XLOOKUP(F44,Emisiones[Mnemotécnico SEN],Emisiones[Moneda],"",0,1) -> COP | J44: =+_xlfn.XLOOKUP(F44,Emisiones[Mnemotécnico SEN],Emisiones[Fecha Vencim.],"",0,1) -> 45987 | K44: =+_xlfn.XLOOKUP(F44,Emisiones[Mnemotécnico SEN],Emisiones[Tasa de Interés],"",0,1) -> 6.25 | L44: 8.906 | M44: 100.009 | N44: =IF(C44="","",PRICE(C44,J44,K44%,L44%,100,1,3)) -> 98.119469 | O44: =IF(C44="","",M44-N44) -> 1.8895315 | P44: =IF(C44="","",100*K44%-O44) -> 4.3604685 | Q44: =IF(C44="","",IF(G44="UVR",S44/V44,S44)) -> -90000000000 | R44: =IF(C44="","",IF('Canjes desagregado'!$G44="UVR",'Canjes desagregado'!$V44*Q44*M44%,Q44*M44%)) -> -90008100000 | S44: -90000000000 | T44: =IFERROR(IF(RIGHT(F44,2)=RIGHT(YEAR(J44),2),1,0),"") -> 1 | U44: =+IF(R44="","",R44) -> -90008100000 | V44: =+IF(F44<>"",(_xlfn.XLOOKUP(C44,UVR[Fecha (dd/mm/aaaa)],UVR[Pesos colombianos por UVR],"",0,1)),"") -> 382.1829 | W44: =IF(C44="","",IF(CONCATENATE(DAY(C44),"/",MONTH(C44),"/",2000)-CONCATENATE(DAY(J44),"/",MONTH(J44),"/",2000)<0,K44%*ABS(S44),0)) -> 5625000000 | X44: =IF(S44<0,-W44,W44) -> -5625000000 | AB44: =IF(C44="","",ROUND(V44*(1+'Inflación observada '!$B$391%)^(("31-12-2025"-C44)/365),3)) -> 398.355 | AD44: =IF(C44="","",IF(G44="UVR",Q44*AB44-S44,0)) -> 0 | AE44: =IF(C44="","",P44/+(O44+P44)) -> 0.69767496 | AF44: =IF(C44="","",AE44*Q44*K44%) -> -3.9244217e+09 | AG44: =(Tabla6[[#This Row],[Fecha Vto]]-TODAY())/365 -> -0.043835616 | AJ44: =IF(C44="","",IF(G44="UVR",Q44*AI44-S44,0)) -> 0
A45: =IF(C45="","",YEAR(C45)) -> 2025 | B45: 621 | C45: 45728 | D45: Tesorería | E45: Títulos Recogidos por la Nación | F45: TFIT15260826 | G45: =+_xlfn.XLOOKUP(F45,Emisiones[Mnemotécnico SEN],Emisiones[Moneda],"",0,1) -> COP | J45: =+_xlfn.XLOOKUP(F45,Emisiones[Mnemotécnico SEN],Emisiones[Fecha Vencim.],"",0,1) -> 46260 | K45: =+_xlfn.XLOOKUP(F45,Emisiones[Mnemotécnico SEN],Emisiones[Tasa de Interés],"",0,1) -> 7.5 | L45: 8.889 | M45: 102.165 | N45: =IF(C45="","",PRICE(C45,J45,K45%,L45%,100,1,3)) -> 98.09666 | O45: =IF(C45="","",M45-N45) -> 4.0683398 | P45: =IF(C45="","",100*K45%-O45) -> 3.4316602 | Q45: =IF(C45="","",IF(G45="UVR",S45/V45,S45)) -> -60000000000 | R45: =IF(C45="","",IF('Canjes desagregado'!$G45="UVR",'Canjes desagregado'!$V45*Q45*M45%,Q45*M45%)) -> -6.1299e+10 | S45: -60000000000 | T45: =IFERROR(IF(RIGHT(F45,2)=RIGHT(YEAR(J45),2),1,0),"") -> 1 | U45: =+IF(R45="","",R45) -> -6.1299e+10 | V45: =+IF(F45<>"",(_xlfn.XLOOKUP(C45,UVR[Fecha (dd/mm/aaaa)],UVR[Pesos colombianos por UVR],"",0,1)),"") -> 382.1829 | W45: =IF(C45="","",IF(CONCATENATE(DAY(C45),"/",MONTH(C45),"/",2000)-CONCATENATE(DAY(J45),"/",MONTH(J45),"/",2000)<0,K45%*ABS(S45),0)) -> 4500000000 | X45: =IF(S45<0,-W45,W45) -> -4500000000 | AB45: =IF(C45="","",ROUND(V45*(1+'Inflación observada '!$B$391%)^(("31-12-2025"-C45)/365),3)) -> 398.355 | AD45: =IF(C45="","",IF(G45="UVR",Q45*AB45-S45,0)) -> 0 | AE45: =IF(C45="","",P45/+(O45+P45)) -> 0.45755469 | AF45: =IF(C45="","",AE45*Q45*K45%) -> -2.0589961e+09 | AG45: =(Tabla6[[#This Row],[Fecha Vto]]-TODAY())/365 -> 0.70410959 | AJ45: =IF(C45="","",IF(G45="UVR",Q45*AI45-S45,0)) -> 0
A46: =IF(C46="","",YEAR(C46)) -> 2025 | B46: 621 | C46: 45728 | D46: Tesorería | E46: Títulos Entregados por la Nación | F46: TFIT23250746 | G46: =+_xlfn.XLOOKUP(F46,Emisiones[Mnemotécnico SEN],Emisiones[Moneda],"",0,1) -> COP | J46: =+_xlfn.XLOOKUP(F46,Emisiones[Mnemotécnico SEN],Emisiones[Fecha Vencim.],"",0,1) -> 53533 | K46: =+_xlfn.XLOOKUP(F46,Emisiones[Mnemotécnico SEN],Emisiones[Tasa de Interés],"",0,1) -> 11.5 | L46: 12.49 | M46: 99.803 | N46: =IF(C46="","",PRICE(C46,J46,K46%,L46%,100,1,3)) -> 92.55605 | O46: =IF(C46="","",M46-N46) -> 7.2469499 | P46: =IF(C46="","",100*K46%-O46) -> 4.2530501 | Q46: =IF(C46="","",IF(G46="UVR",S46/V46,S46)) -> 150000000000 | R46: =IF(C46="","",IF('Canjes desagregado'!$G46="UVR",'Canjes desagregado'!$V46*Q46*M46%,Q46*M46%)) -> 149704500000 | S46: 150000000000 | T46: =IFERROR(IF(RIGHT(F46,2)=RIGHT(YEAR(J46),2),1,0),"") -> 1 | U46: =+IF(R46="","",R46) -> 149704500000 | V46: =+IF(F46<>"",(_xlfn.XLOOKUP(C46,UVR[Fecha (dd/mm/aaaa)],UVR[Pesos colombianos por UVR],"",0,1)),"") -> 382.1829 | W46: =IF(C46="","",IF(CONCATENATE(DAY(C46),"/",MONTH(C46),"/",2000)-CONCATENATE(DAY(J46),"/",MONTH(J46),"/",2000)<0,K46%*ABS(S46),0)) -> 17250000000 | X46: =IF(S46<0,-W46,W46) -> 17250000000 | AB46: =IF(C46="","",ROUND(V46*(1+'Inflación observada '!$B$391%)^(("31-12-2025"-C46)/365),3)) -> 398.355 | AD46: =IF(C46="","",IF(G46="UVR",Q46*AB46-S46,0)) -> 0 | AE46: =IF(C46="","",P46/+(O46+P46)) -> 0.36983044 | AF46: =IF(C46="","",AE46*Q46*K46%) -> 6.3795752e+09 | AG46: =(Tabla6[[#This Row],[Fecha Vto]]-TODAY())/365 -> 20.630137 | AJ46: =IF(C46="","",IF(G46="UVR",Q46*AI46-S46,0)) -> 0
A47: =IF(C47="","",YEAR(C47)) -> 2025 | B47: 622 | C47: 45729 | D47: Tesorería | E47: Títulos Recogidos por la Nación | F47: TFIT08261125 | G47: =+_xlfn.XLOOKUP(F47,Emisiones[Mnemotécnico SEN],Emisiones[Moneda],"",0,1) -> COP | J47: =+_xlfn.XLOOKUP(F47,Emisiones[Mnemotécnico SEN],Emisiones[Fecha Vencim.],"",0,1) -> 45987 | K47: =+_xlfn.XLOOKUP(F47,Emisiones[Mnemotécnico SEN],Emisiones[Tasa de Interés],"",0,1) -> 6.25 | L47: 8.905 | M47: 100.033 | N47: =IF(C47="","",PRICE(C47,J47,K47%,L47%,100,1,3)) -> 98.12595 | O47: =IF(C47="","",M47-N47) -> 1.9070502 | P47: =IF(C47="","",100*K47%-O47) -> 4.3429498 | Q47: =IF(C47="","",IF(G47="UVR",S47/V47,S47)) -> -91000000000 | R47: =IF(C47="","",IF('Canjes desagregado'!$G47="UVR",'Canjes desagregado'!$V47*Q47*M47%,Q47*M47%)) -> -91030030000 | S47: -91000000000 | T47: =IFERROR(IF(RIGHT(F47,2)=RIGHT(YEAR(J47),2),1,0),"") -> 1 | U47: =+IF(R47="","",R47) -> -91030030000 | V47: =+IF(F47<>"",(_xlfn.XLOOKUP(C47,UVR[Fecha (dd/mm/aaaa)],UVR[Pesos colombianos por UVR],"",0,1)),"") -> 382.3107 | W47: =IF(C47="","",IF(CONCATENATE(DAY(C47),"/",MONTH(C47),"/",2000)-CONCATENATE(DAY(J47),"/",MONTH(J47),"/",2000)<0,K47%*ABS(S47),0)) -> 5687500000 | X47: =IF(S47<0,-W47,W47) -> -5687500000 | AB47: =IF(C47="","",ROUND(V47*(1+'Inflación observada '!$B$391%)^(("31-12-2025"-C47)/365),3)) -> 398.432 | AD47: =IF(C47="","",IF(G47="UVR",Q47*AB47-S47,0)) -> 0 | AE47: =IF(C47="","",P47/+(O47+P47)) -> 0.69487197 | AF47: =IF(C47="","",AE47*Q47*K47%) -> -3.9520844e+09 | AG47: =(Tabla6[[#This Row],[Fecha Vto]]-TODAY())/365 -> -0.043835616 | AJ47: =IF(C47="","",IF(G47="UVR",Q47*AI47-S47,0)) -> 0
A48: =IF(C48="","",YEAR(C48)) -> 2025 | B48: 622 | C48: 45729 | D48: Tesorería | E48: Títulos Recogidos por la Nación | F48: TFIT15260826 | G48: =+_xlfn.XLOOKUP(F48,Emisiones[Mnemotécnico SEN],Emisiones[Moneda],"",0,1) -> COP | J48: =+_xlfn.XLOOKUP(F48,Emisiones[Mnemotécnico SEN],Emisiones[Fecha Vencim.],"",0,1) -> 46260 | K48: =+_xlfn.XLOOKUP(F48,Emisiones[Mnemotécnico SEN],Emisiones[Tasa de Interés],"",0,1) -> 7.5 | L48: 8.858 | M48: 102.229 | N48: =IF(C48="","",PRICE(C48,J48,K48%,L48%,100,1,3)) -> 98.140235 | O48: =IF(C48="","",M48-N48) -> 4.0887651 | P48: =IF(C48="","",100*K48%-O48) -> 3.4112349 | Q48: =IF(C48="","",IF(G48="UVR",S48/V48,S48)) -> -90000000000 | R48: =IF(C48="","",IF('Canjes desagregado'!$G48="UVR",'Canjes desagregado'!$V48*Q48*M48%,Q48*M48%)) -> -92006100000 | S48: -90000000000 | T48: =IFERROR(IF(RIGHT(F48,2)=RIGHT(YEAR(J48),2),1,0),"") -> 1 | U48: =+IF(R48="","",R48) -> -92006100000 | V48: =+IF(F48<>"",(_xlfn.XLOOKUP(C48,UVR[Fecha (dd/mm/aaaa)],UVR[Pesos colombianos por UVR],"",0,1)),"") -> 382.3107 | W48: =IF(C48="","",IF(CONCATENATE(DAY(C48),"/",MONTH(C48),"/",2000)-CONCATENATE(DAY(J48),"/",MONTH(J48),"/",2000)<0,K48%*ABS(S48),0)) -> 6750000000 | X48: =IF(S48<0,-W48,W48) -> -6750000000 | AB48: =IF(C48="","",ROUND(V48*(1+'Inflación observada '!$B$391%)^(("31-12-2025"-C48)/365),3)) -> 398.432 | AD48: =IF(C48="","",IF(G48="UVR",Q48*AB48-S48,0)) -> 0 | AE48: =IF(C48="","",P48/+(O48+P48)) -> 0.45483132 | AF48: =IF(C48="","",AE48*Q48*K48%) -> -3.0701114e+09 | AG48: =(Tabla6[[#This Row],[Fecha Vto]]-TODAY())/365 -> 0.70410959 | AJ48: =IF(C48="","",IF(G48="UVR",Q48*AI48-S48,0)) -> 0
A49: =IF(C49="","",YEAR(C49)) -> 2025 | B49: 622 | C49: 45729 | D49: Tesorería | E49: Títulos Entregados por la Nación | F49: TFIT23250746 | G49: =+_xlfn.XLOOKUP(F49,Emisiones[Mnemotécnico SEN],Emisiones[Moneda],"",0,1) -> COP | J49: =+_xlfn.XLOOKUP(F49,Emisiones[Mnemotécnico SEN],Emisiones[Fecha Vencim.],"",0,1) -> 53533 | K49: =+_xlfn.XLOOKUP(F49,Emisiones[Mnemotécnico SEN],Emisiones[Tasa de Interés],"",0,1) -> 11.5 | L49: 12.496 | M49: 99.794 | N49: =IF(C49="","",PRICE(C49,J49,K49%,L49%,100,1,3)) -> 92.51529 | O49: =IF(C49="","",M49-N49) -> 7.2787103 | P49: =IF(C49="","",100*K49%-O49) -> 4.2212897 | Q49: =IF(C49="","",IF(G49="UVR",S49/V49,S49)) -> 181000000000 | R49: =IF(C49="","",IF('Canjes desagregado'!$G49="UVR",'Canjes desagregado'!$V49*Q49*M49%,Q49*M49%)) -> 180627140000 | S49: 181000000000 | T49: =IFERROR(IF(RIGHT(F49,2)=RIGHT(YEAR(J49),2),1,0),"") -> 1 | U49: =+IF(R49="","",R49) -> 180627140000 | V49: =+IF(F49<>"",(_xlfn.XLOOKUP(C49,UVR[Fecha (dd/mm/aaaa)],UVR[Pesos colombianos por UVR],"",0,1)),"") -> 382.3107 | W49: =IF(C49="","",IF(CONCATENATE(DAY(C49),"/",MONTH(C49),"/",2000)-CONCATENATE(DAY(J49),"/",MONTH(J49),"/",2000)<0,K49%*ABS(S49),0)) -> 20815000000 | X49: =IF(S49<0,-W49,W49) -> 20815000000 | AB49: =IF(C49="","",ROUND(V49*(1+'Inflación observada '!$B$391%)^(("31-12-2025"-C49)/365),3)) -> 398.432 | AD49: =IF(C49="","",IF(G49="UVR",Q49*AB49-S49,0)) -> 0 | AE49: =IF(C49="","",P49/+(O49+P49)) -> 0.36706867 | AF49: =IF(C49="","",AE49*Q49*K49%) -> 7.6405344e+09 | AG49: =(Tabla6[[#This Row],[Fecha Vto]]-TODAY())/365 -> 20.630137 | AJ49: =IF(C49="","",IF(G49="UVR",Q49*AI49-S49,0)) -> 0
A50: =IF(C50="","",YEAR(C50)) -> 2025 | B50: 623 | C50: 45785 | D50: Tesorería | E50: Títulos Recogidos por la Nación | F50: TFIT15260826 | G50: =+_xlfn.XLOOKUP(F50,Emisiones[Mnemotécnico SEN],Emisiones[Moneda],"",0,1) -> COP | J50: =+_xlfn.XLOOKUP(F50,Emisiones[Mnemotécnico SEN],Emisiones[Fecha Vencim.],"",0,1) -> 46260 | K50: =+_xlfn.XLOOKUP(F50,Emisiones[Mnemotécnico SEN],Emisiones[Tasa de Interés],"",0,1) -> 7.5 | L50: 8.86 | M50: 103.567 | N50: =IF(C50="","",PRICE(C50,J50,K50%,L50%,100,1,3)) -> 98.32712 | O50: =IF(C50="","",M50-N50) -> 5.2398799 | P50: =IF(C50="","",100*K50%-O50) -> 2.2601201 | Q50: =IF(C50="","",IF(G50="UVR",S50/V50,S50)) -> -147500000000 | R50: =IF(C50="","",IF('Canjes desagregado'!$G50="UVR",'Canjes desagregado'!$V50*Q50*M50%,Q50*M50%)) -> -1.5276132e+11 | S50: -147500000000 | T50: =IFERROR(IF(RIGHT(F50,2)=RIGHT(YEAR(J50),2),1,0),"") -> 1 | U50: =+IF(R50="","",R50) -> -1.5276132e+11 | V50: =+IF(F50<>"",(_xlfn.XLOOKUP(C50,UVR[Fecha (dd/mm/aaaa)],UVR[Pesos colombianos por UVR],"",0,1)),"") -> 388.4691 | W50: =IF(C50="","",IF(CONCATENATE(DAY(C50),"/",MONTH(C50),"/",2000)-CONCATENATE(DAY(J50),"/",MONTH(J50),"/",2000)<0,K50%*ABS(S50),0)) -> 11062500000 | X50: =IF(S50<0,-W50,W50) -> -11062500000 | AB50: =IF(C50="","",ROUND(V50*(1+'Inflación observada '!$B$392%)^(("31-12-2025"-C50)/365),3)) -> 401.196 | AD50: =IF(C50="","",IF(G50="UVR",Q50*AB50-S50,0)) -> 0 | AE50: =IF(C50="","",P50/+(O50+P50)) -> 0.30134935 | AF50: =IF(C50="","",AE50*Q50*K50%) -> -3.3336772e+09 | AG50: =(Tabla6[[#This Row],[Fecha Vto]]-TODAY())/365 -> 0.70410959 | AJ50: =IF(C50="","",IF(G50="UVR",Q50*AI50-S50,0)) -> 0
A51: =IF(C51="","",YEAR(C51)) -> 2025 | B51: 623 | C51: 45785 | D51: Tesorería | E51: Títulos Entregados por la Nación | F51: TFIT05220829 | G51: =+_xlfn.XLOOKUP(F51,Emisiones[Mnemotécnico SEN],Emisiones[Moneda],"",0,1) -> COP | J51: =+_xlfn.XLOOKUP(F51,Emisiones[Mnemotécnico SEN],Emisiones[Fecha Vencim.],"",0,1) -> 47352 | K51: =+_xlfn.XLOOKUP(F51,Emisiones[Mnemotécnico SEN],Emisiones[Tasa de Interés],"",0,1) -> 11 | L51: 10.62 | M51: 108.948 | N51: =IF(C51="","",PRICE(C51,J51,K51%,L51%,100,1,3)) -> 101.1424 | O51: =IF(C51="","",M51-N51) -> 7.8055968 | P51: =IF(C51="","",100*K51%-O51) -> 3.1944032 | Q51: =IF(C51="","",IF(G51="UVR",S51/V51,S51)) -> 116000000000 | R51: =IF(C51="","",IF('Canjes desagregado'!$G51="UVR",'Canjes desagregado'!$V51*Q51*M51%,Q51*M51%)) -> 126379680000 | S51: 116000000000 | T51: =IFERROR(IF(RIGHT(F51,2)=RIGHT(YEAR(J51),2),1,0),"") -> 1 | U51: =+IF(R51="","",R51) -> 126379680000 | V51: =+IF(F51<>"",(_xlfn.XLOOKUP(C51,UVR[Fecha (dd/mm/aaaa)],UVR[Pesos colombianos por UVR],"",0,1)),"") -> 388.4691 | W51: =IF(C51="","",IF(CONCATENATE(DAY(C51),"/",MONTH(C51),"/",2000)-CONCATENATE(DAY(J51),"/",MONTH(J51),"/",2000)<0,K51%*ABS(S51),0)) -> 12760000000 | X51: =IF(S51<0,-W51,W51) -> 12760000000 | AB51: =IF(C51="","",ROUND(V51*(1+'Inflación observada '!$B$392%)^(("31-12-2025"-C51)/365),3)) -> 401.196 | AD51: =IF(C51="","",IF(G51="UVR",Q51*AB51-S51,0)) -> 0 | AE51: =IF(C51="","",P51/+(O51+P51)) -> 0.29040029 | AF51: =IF(C51="","",AE51*Q51*K51%) -> 3.7055077e+09 | AG51: =(Tabla6[[#This Row],[Fecha Vto]]-TODAY())/365 -> 3.6958904 | AJ51: =IF(C51="","",IF(G51="UVR",Q51*AI51-S51,0)) -> 0
A52: =IF(C52="","",YEAR(C52)) -> 2025 | B52: 623 | C52: 45785 | D52: Tesorería | E52: Títulos Entregados por la Nación | F52: TFIT10260331 | G52: =+_xlfn.XLOOKUP(F52,Emisiones[Mnemotécnico SEN],Emisiones[Moneda],"",0,1) -> COP | J52: =+_xlfn.XLOOKUP(F52,Emisiones[Mnemotécnico SEN],Emisiones[Fecha Vencim.],"",0,1) -> 47933 | K52: =+_xlfn.XLOOKUP(F52,Emisiones[Mnemotécnico SEN],Emisiones[Tasa de Interés],"",0,1) -> 7 | L52: 11.325 | M52: 82.914 | N52: =IF(C52="","",PRICE(C52,J52,K52%,L52%,100,1,3)) -> 82.089654 | O52: =IF(C52="","",M52-N52) -> 0.82434593 | P52: =IF(C52="","",100*K52%-O52) -> 6.1756541 | Q52: =IF(C52="","",IF(G52="UVR",S52/V52,S52)) -> 31500000000 | R52: =IF(C52="","",IF('Canjes desagregado'!$G52="UVR",'Canjes desagregado'!$V52*Q52*M52%,Q52*M52%)) -> 26117910000 | S52: 31500000000 | T52: =IFERROR(IF(RIGHT(F52,2)=RIGHT(YEAR(J52),2),1,0),"") -> 1 | U52: =+IF(R52="","",R52) -> 26117910000 | V52: =+IF(F52<>"",(_xlfn.XLOOKUP(C52,UVR[Fecha (dd/mm/aaaa)],UVR[Pesos colombianos por UVR],"",0,1)),"") -> 388.4691 | W52: =IF(C52="","",IF(CONCATENATE(DAY(C52),"/",MONTH(C52),"/",2000)-CONCATENATE(DAY(J52),"/",MONTH(J52),"/",2000)<0,K52%*ABS(S52),0)) -> 0 | X52: =IF(S52<0,-W52,W52) -> 0 | AB52: =IF(C52="","",ROUND(V52*(1+'Inflación observada '!$B$392%)^(("31-12-2025"-C52)/365),3)) -> 401.196 | AD52: =IF(C52="","",IF(G52="UVR",Q52*AB52-S52,0)) -> 0 | AE52: =IF(C52="","",P52/+(O52+P52)) -> 0.8822363 | AF52: =IF(C52="","",AE52*Q52*K52%) -> 1.945331e+09 | AG52: =(Tabla6[[#This Row],[Fecha Vto]]-TODAY())/365 -> 5.2876712 | AJ52: =IF(C52="","",IF(G52="UVR",Q52*AI52-S52,0)) -> 0
A53: =IF(C53="","",YEAR(C53)) -> 2025 | B53: 624 | C53: 45786 | D53: Tesorería | E53: Títulos Recogidos por la Nación | F53: TFIT15260826 | G53: =+_xlfn.XLOOKUP(F53,Emisiones[Mnemotécnico SEN],Emisiones[Moneda],"",0,1) -> COP | J53: =+_xlfn.XLOOKUP(F53,Emisiones[Mnemotécnico SEN],Emisiones[Fecha Vencim.],"",0,1) -> 46260 | K53: =+_xlfn.XLOOKUP(F53,Emisiones[Mnemotécnico SEN],Emisiones[Tasa de Interés],"",0,1) -> 7.5 | L53: 9.013 | M53: 103.413 | N53: =IF(C53="","",PRICE(C53,J53,K53%,L53%,100,1,3)) -> 98.152153 | O53: =IF(C53="","",M53-N53) -> 5.2608472 | P53: =IF(C53="","",100*K53%-O53) -> 2.2391528 | Q53: =IF(C53="","",IF(G53="UVR",S53/V53,S53)) -> -21500000000 | R53: =IF(C53="","",IF('Canjes desagregado'!$G53="UVR",'Canjes desagregado'!$V53*Q53*M53%,Q53*M53%)) -> -22233795000 | S53: -21500000000 | T53: =IFERROR(IF(RIGHT(F53,2)=RIGHT(YEAR(J53),2),1,0),"") -> 1 | U53: =+IF(R53="","",R53) -> -22233795000 | V53: =+IF(F53<>"",(_xlfn.XLOOKUP(C53,UVR[Fecha (dd/mm/aaaa)],UVR[Pesos colombianos por UVR],"",0,1)),"") -> 388.5363 | W53: =IF(C53="","",IF(CONCATENATE(DAY(C53),"/",MONTH(C53),"/",2000)-CONCATENATE(DAY(J53),"/",MONTH(J53),"/",2000)<0,K53%*ABS(S53),0)) -> 1612500000 | X53: =IF(S53<0,-W53,W53) -> -1612500000 | AB53: =IF(C53="","",ROUND(V53*(1+'Inflación observada '!$B$390%)^(("31-12-2025"-C53)/365),3)) -> 401.532 | AD53: =IF(C53="","",IF(G53="UVR",Q53*AB53-S53,0)) -> 0 | AE53: =IF(C53="","",P53/+(O53+P53)) -> 0.29855371 | AF53: =IF(C53="","",AE53*Q53*K53%) -> -4.8141786e+08 | AG53: =(Tabla6[[#This Row],[Fecha Vto]]-TODAY())/365 -> 0.70410959 | AJ53: =IF(C53="","",IF(G53="UVR",Q53*AI53-S53,0)) -> 0
A54: =IF(C54="","",YEAR(C54)) -> 2025 | B54: 624 | C54: 45786 | D54: Tesorería | E54: Títulos Entregados por la Nación | F54: TFIT05220829 | G54: =+_xlfn.XLOOKUP(F54,Emisiones[Mnemotécnico SEN],Emisiones[Moneda],"",0,1) -> COP | J54: =+_xlfn.XLOOKUP(F54,Emisiones[Mnemotécnico SEN],Emisiones[Fecha Vencim.],"",0,1) -> 47352 | K54: =+_xlfn.XLOOKUP(F54,Emisiones[Mnemotécnico SEN],Emisiones[Tasa de Interés],"",0,1) -> 11 | L54: 10.67 | M54: 108.811 | N54: =IF(C54="","",PRICE(C54,J54,K54%,L54%,100,1,3)) -> 100.97526 | O54: =IF(C54="","",M54-N54) -> 7.8357379 | P54: =IF(C54="","",100*K54%-O54) -> 3.1642621 | Q54: =IF(C54="","",IF(G54="UVR",S54/V54,S54)) -> 15000000000 | R54: =IF(C54="","",IF('Canjes desagregado'!$G54="UVR",'Canjes desagregado'!$V54*Q54*M54%,Q54*M54%)) -> 1.632165e+10 | S54: 15000000000 | T54: =IFERROR(IF(RIGHT(F54,2)=RIGHT(YEAR(J54),2),1,0),"") -> 1 | U54: =+IF(R54="","",R54) -> 1.632165e+10 | V54: =+IF(F54<>"",(_xlfn.XLOOKUP(C54,UVR[Fecha (dd/mm/aaaa)],UVR[Pesos colombianos por UVR],"",0,1)),"") -> 388.5363 | W54: =IF(C54="","",IF(CONCATENATE(DAY(C54),"/",MONTH(C54),"/",2000)-CONCATENATE(DAY(J54),"/",MONTH(J54),"/",2000)<0,K54%*ABS(S54),0)) -> 1650000000 | X54: =IF(S54<0,-W54,W54) -> 1650000000 | AB54: =IF(C54="","",ROUND(V54*(1+'Inflación observada '!$B$390%)^(("31-12-2025"-C54)/365),3)) -> 401.532 | AD54: =IF(C54="","",IF(G54="UVR",Q54*AB54-S54,0)) -> 0 | AE54: =IF(C54="","",P54/+(O54+P54)) -> 0.28766019 | AF54: =IF(C54="","",AE54*Q54*K54%) -> 4.7463931e+08 | AG54: =(Tabla6[[#This Row],[Fecha Vto]]-TODAY())/365 -> 3.6958904 | AJ54: =IF(C54="","",IF(G54="UVR",Q54*AI54-S54,0)) -> 0
A55: =IF(C55="","",YEAR(C55)) -> 2025 | B55: 624 | C55: 45786 | D55: Tesorería | E55: Títulos Entregados por la Nación | F55: TFIT10260331 | G55: =+_xlfn.XLOOKUP(F55,Emisiones[Mnemotécnico SEN],Emisiones[Moneda],"",0,1) -> COP | J55: =+_xlfn.XLOOKUP(F55,Emisiones[Mnemotécnico SEN],Emisiones[Fecha Vencim.],"",0,1) -> 47933 | K55: =+_xlfn.XLOOKUP(F55,Emisiones[Mnemotécnico SEN],Emisiones[Tasa de Interés],"",0,1) -> 7 | L55: 11.392 | M55: 82.696 | N55: =IF(C55="","",PRICE(C55,J55,K55%,L55%,100,1,3)) -> 81.852119 | O55: =IF(C55="","",M55-N55) -> 0.84388109 | P55: =IF(C55="","",100*K55%-O55) -> 6.1561189 | Q55: =IF(C55="","",IF(G55="UVR",S55/V55,S55)) -> 6500000000 | R55: =IF(C55="","",IF('Canjes desagregado'!$G55="UVR",'Canjes desagregado'!$V55*Q55*M55%,Q55*M55%)) -> 5375240000 | S55: 6500000000 | T55: =IFERROR(IF(RIGHT(F55,2)=RIGHT(YEAR(J55),2),1,0),"") -> 1 | U55: =+IF(R55="","",R55) -> 5375240000 | V55: =+IF(F55<>"",(_xlfn.XLOOKUP(C55,UVR[Fecha (dd/mm/aaaa)],UVR[Pesos colombianos por UVR],"",0,1)),"") -> 388.5363 | W55: =IF(C55="","",IF(CONCATENATE(DAY(C55),"/",MONTH(C55),"/",2000)-CONCATENATE(DAY(J55),"/",MONTH(J55),"/",2000)<0,K55%*ABS(S55),0)) -> 0 | X55: =IF(S55<0,-W55,W55) -> 0 | AB55: =IF(C55="","",ROUND(V55*(1+'Inflación observada '!$B$390%)^(("31-12-2025"-C55)/365),3)) -> 401.532 | AD55: =IF(C55="","",IF(G55="UVR",Q55*AB55-S55,0)) -> 0 | AE55: =IF(C55="","",P55/+(O55+P55)) -> 0.87944556 | AF55: =IF(C55="","",AE55*Q55*K55%) -> 4.0014773e+08 | AG55: =(Tabla6[[#This Row],[Fecha Vto]]-TODAY())/365 -> 5.2876712 | AJ55: =IF(C55="","",IF(G55="UVR",Q55*AI55-S55,0)) -> 0
A56: =IF(C56="","",YEAR(C56)) -> 2025 | B56: 625 | C56: 45797 | D56: Tesorería | E56: Títulos Recogidos por la Nación | F56: TFIT15260826 | G56: =+_xlfn.XLOOKUP(F56,Emisiones[Mnemotécnico SEN],Emisiones[Moneda],"",0,1) -> COP | J56: =+_xlfn.XLOOKUP(F56,Emisiones[Mnemotécnico SEN],Emisiones[Fecha Vencim.],"",0,1) -> 46260 | K56: =+_xlfn.XLOOKUP(F56,Emisiones[Mnemotécnico SEN],Emisiones[Tasa de Interés],"",0,1) -> 7.5 | L56: 8.871 | M56: 103.844 | N56: =IF(C56="","",PRICE(C56,J56,K56%,L56%,100,1,3)) -> 98.357432 | O56: =IF(C56="","",M56-N56) -> 5.4865678 | P56: =IF(C56="","",100*K56%-O56) -> 2.0134322 | Q56: =IF(C56="","",IF(G56="UVR",S56/V56,S56)) -> -394363800000 | R56: =IF(C56="","",IF('Canjes desagregado'!$G56="UVR",'Canjes desagregado'!$V56*Q56*M56%,Q56*M56%)) -> -409523144472 | S56: -394363800000 | T56: =IFERROR(IF(RIGHT(F56,2)=RIGHT(YEAR(J56),2),1,0),"") -> 1 | U56: =+IF(R56="","",R56) -> -409523144472 | V56: =+IF(F56<>"",(_xlfn.XLOOKUP(C56,UVR[Fecha (dd/mm/aaaa)],UVR[Pesos colombianos por UVR],"",0,1)),"") -> 389.3524 | W56: =IF(C56="","",IF(CONCATENATE(DAY(C56),"/",MONTH(C56),"/",2000)-CONCATENATE(DAY(J56),"/",MONTH(J56),"/",2000)<0,K56%*ABS(S56),0)) -> 29577285000 | X56: =IF(S56<0,-W56,W56) -> -29577285000 | AB56: =IF(C56="","",ROUND(V56*(1+'Inflación observada '!$B$390%)^(("31-12-2025"-C56)/365),3)) -> 401.759 | AD56: =IF(C56="","",IF(G56="UVR",Q56*AB56-S56,0)) -> 0 | AE56: =IF(C56="","",P56/+(O56+P56)) -> 0.26845763 | AF56: =IF(C56="","",AE56*Q56*K56%) -> -7.9402478e+09 | AG56: =(Tabla6[[#This Row],[Fecha Vto]]-TODAY())/365 -> 0.70410959 | AJ56: =IF(C56="","",IF(G56="UVR",Q56*AI56-S56,0)) -> 0
A57: =IF(C57="","",YEAR(C57)) -> 2025 | B57: 625 | C57: 45797 | D57: Tesorería | E57: Títulos Entregados por la Nación | F57: TFIT05220829 | G57: =+_xlfn.XLOOKUP(F57,Emisiones[Mnemotécnico SEN],Emisiones[Moneda],"",0,1) -> COP | J57: =+_xlfn.XLOOKUP(F57,Emisiones[Mnemotécnico SEN],Emisiones[Fecha Vencim.],"",0,1) -> 47352 | K57: =+_xlfn.XLOOKUP(F57,Emisiones[Mnemotécnico SEN],Emisiones[Tasa de Interés],"",0,1) -> 11 | L57: 11.1 | M57: 107.73 | N57: =IF(C57="","",PRICE(C57,J57,K57%,L57%,100,1,3)) -> 99.562983 | O57: =IF(C57="","",M57-N57) -> 8.1670174 | P57: =IF(C57="","",100*K57%-O57) -> 2.8329826 | Q57: =IF(C57="","",IF(G57="UVR",S57/V57,S57)) -> 380138400000 | R57: =IF(C57="","",IF('Canjes desagregado'!$G57="UVR",'Canjes desagregado'!$V57*Q57*M57%,Q57*M57%)) -> 4.095231e+11 | S57: 380138400000 | T57: =IFERROR(IF(RIGHT(F57,2)=RIGHT(YEAR(J57),2),1,0),"") -> 1 | U57: =+IF(R57="","",R57) -> 4.095231e+11 | V57: =+IF(F57<>"",(_xlfn.XLOOKUP(C57,UVR[Fecha (dd/mm/aaaa)],UVR[Pesos colombianos por UVR],"",0,1)),"") -> 389.3524 | W57: =IF(C57="","",IF(CONCATENATE(DAY(C57),"/",MONTH(C57),"/",2000)-CONCATENATE(DAY(J57),"/",MONTH(J57),"/",2000)<0,K57%*ABS(S57),0)) -> 41815224000 | X57: =IF(S57<0,-W57,W57) -> 41815224000 | AB57: =IF(C57="","",ROUND(V57*(1+'Inflación observada '!$B$390%)^(("31-12-2025"-C57)/365),3)) -> 401.759 | AD57: =IF(C57="","",IF(G57="UVR",Q57*AB57-S57,0)) -> 0 | AE57: =IF(C57="","",P57/+(O57+P57)) -> 0.25754387 | AF57: =IF(C57="","",AE57*Q57*K57%) -> 1.0769255e+10 | AG57: =(Tabla6[[#This Row],[Fecha Vto]]-TODAY())/365 -> 3.6958904 | AJ57: =IF(C57="","",IF(G57="UVR",Q57*AI57-S57,0)) -> 0
A58: 2025 | B58: 626 | C58: 45797 | D58: Mercado | E58: Títulos Recogidos por la Nación | F58: TFIT08261125 | G58: =+_xlfn.XLOOKUP(F58,Emisiones[Mnemotécnico SEN],Emisiones[Moneda],"",0,1) -> COP | J58: =+_xlfn.XLOOKUP(F58,Emisiones[Mnemotécnico SEN],Emisiones[Fecha Vencim.],"",0,1) -> 45987 | K58: =+_xlfn.XLOOKUP(F58,Emisiones[Mnemotécnico SEN],Emisiones[Tasa de Interés],"",0,1) -> 6.25 | L58: 8.875 | M58: 101.697 | N58: =IF(C58="","",PRICE(C58,J58,K58%,L58%,100,1,3)) -> 98.561577 | O58: =IF(C58="","",M58-N58) -> 3.1354229 | P58: =IF(C58="","",100*K58%-O58) -> 3.1145771 | Q58: =IF(C58="","",IF(G58="UVR",S58/V58,S58)) -> -873412400000 | R58: =IF(C58="","",IF('Canjes desagregado'!$G58="UVR",'Canjes desagregado'!$V58*Q58*M58%,Q58*M58%)) -> -8.8823421e+11 | S58: -873412400000 | T58: =IFERROR(IF(RIGHT(F58,2)=RIGHT(YEAR(J58),2),1,0),"") -> 1 | U58: =+IF(R58="","",R58) -> -8.8823421e+11 | V58: =+IF(F58<>"",(_xlfn.XLOOKUP(C58,UVR[Fecha (dd/mm/aaaa)],UVR[Pesos colombianos por UVR],"",0,1)),"") -> 389.3524 | W58: =IF(C58="","",IF(CONCATENATE(DAY(C58),"/",MONTH(C58),"/",2000)-CONCATENATE(DAY(J58),"/",MONTH(J58),"/",2000)<0,K58%*ABS(S58),0)) -> 54588275000 | X58: =IF(S58<0,-W58,W58) -> -54588275000 | AB58: =IF(C58="","",ROUND(V58*(1+'Inflación observada '!$B$390%)^(("31-12-2025"-C58)/365),3)) -> 401.759 | AD58: =IF(C58="","",IF(G58="UVR",Q58*AB58-S58,0)) -> 0 | AE58: =IF(C58="","",P58/+(O58+P58)) -> 0.49833234 | AF58: =IF(C58="","",AE58*Q58*K58%) -> -2.7203103e+10 | AG58: =(Tabla6[[#This Row],[Fecha Vto]]-TODAY())/365 -> -0.043835616 | AJ58: =IF(C58="","",IF(G58="UVR",Q58*AI58-S58,0)) -> 0
A59: 2025 | B59: 626 | C59: 45797 | D59: Mercado | E59: Títulos Recogidos por la Nación | F59: TFIT15260826 | G59: =+_xlfn.XLOOKUP(F59,Emisiones[Mnemotécnico SEN],Emisiones[Moneda],"",0,1) -> COP | J59: =+_xlfn.XLOOKUP(F59,Emisiones[Mnemotécnico SEN],Emisiones[Fecha Vencim.],"",0,1) -> 46260 | K59: =+_xlfn.XLOOKUP(F59,Emisiones[Mnemotécnico SEN],Emisiones[Tasa de Interés],"",0,1) -> 7.5 | L59: 8.787 | M59: 103.988 | N59: =IF(C59="","",PRICE(C59,J59,K59%,L59%,100,1,3)) -> 98.453493 | O59: =IF(C59="","",M59-N59) -> 5.5345072 | P59: =IF(C59="","",100*K59%-O59) -> 1.9654928 | Q59: =IF(C59="","",IF(G59="UVR",S59/V59,S59)) -> -1928000000000 | R59: =IF(C59="","",IF('Canjes desagregado'!$G59="UVR",'Canjes desagregado'!$V59*Q59*M59%,Q59*M59%)) -> -2.0048886e+12 | S59: -1928000000000 | T59: =IFERROR(IF(RIGHT(F59,2)=RIGHT(YEAR(J59),2),1,0),"") -> 1 | U59: =+IF(R59="","",R59) -> -2.0048886e+12 | V59: =+IF(F59<>"",(_xlfn.XLOOKUP(C59,UVR[Fecha (dd/mm/aaaa)],UVR[Pesos colombianos por UVR],"",0,1)),"") -> 389.3524 | W59: =IF(C59="","",IF(CONCATENATE(DAY(C59),"/",MONTH(C59),"/",2000)-CONCATENATE(DAY(J59),"/",MONTH(J59),"/",2000)<0,K59%*ABS(S59),0)) -> 144600000000 | X59: =IF(S59<0,-W59,W59) -> -144600000000 | AB59: =IF(C59="","",ROUND(V59*(1+'Inflación observada '!$B$390%)^(("31-12-2025"-C59)/365),3)) -> 401.759 | AD59: =IF(C59="","",IF(G59="UVR",Q59*AB59-S59,0)) -> 0 | AE59: =IF(C59="","",P59/+(O59+P59)) -> 0.2620657 | AF59: =IF(C59="","",AE59*Q59*K59%) -> -3.7894701e+10 | AG59: =(Tabla6[[#This Row],[Fecha Vto]]-TODAY())/365 -> 0.70410959 | AJ59: =IF(C59="","",IF(G59="UVR",Q59*AI59-S59,0)) -> 0
A60: 2025 | B60: 626 | C60: 45797 | D60: Mercado | E60: Títulos Entregados por la Nación | F60: TFIT05220829 | G60: =+_xlfn.XLOOKUP(F60,Emisiones[Mnemotécnico SEN],Emisiones[Moneda],"",0,1) -> COP | J60: =+_xlfn.XLOOKUP(F60,Emisiones[Mnemotécnico SEN],Emisiones[Fecha Vencim.],"",0,1) -> 47352 | K60: =+_xlfn.XLOOKUP(F60,Emisiones[Mnemotécnico SEN],Emisiones[Tasa de Interés],"",0,1) -> 11 | L60: 11.033 | M60: 108.01 | N60: =IF(C60="","",PRICE(C60,J60,K60%,L60%,100,1,3)) -> 99.781483 | O60: =IF(C60="","",M60-N60) -> 8.228517 | P60: =IF(C60="","",100*K60%-O60) -> 2.771483 | Q60: =IF(C60="","",IF(G60="UVR",S60/V60,S60)) -> 2678565900000 | R60: =IF(C60="","",IF('Canjes desagregado'!$G60="UVR",'Canjes desagregado'!$V60*Q60*M60%,Q60*M60%)) -> 2.893119e+12 | S60: 2678565900000 | T60: =IFERROR(IF(RIGHT(F60,2)=RIGHT(YEAR(J60),2),1,0),"") -> 1 | U60: =+IF(R60="","",R60) -> 2.893119e+12 | V60: =+IF(F60<>"",(_xlfn.XLOOKUP(C60,UVR[Fecha (dd/mm/aaaa)],UVR[Pesos colombianos por UVR],"",0,1)),"") -> 389.3524 | W60: =IF(C60="","",IF(CONCATENATE(DAY(C60),"/",MONTH(C60),"/",2000)-CONCATENATE(DAY(J60),"/",MONTH(J60),"/",2000)<0,K60%*ABS(S60),0)) -> 294642249000 | X60: =IF(S60<0,-W60,W60) -> 294642249000 | AB60: =IF(C60="","",ROUND(V60*(1+'Inflación observada '!$B$390%)^(("31-12-2025"-C60)/365),3)) -> 401.759 | AD60: =IF(C60="","",IF(G60="UVR",Q60*AB60-S60,0)) -> 0 | AE60: =IF(C60="","",P60/+(O60+P60)) -> 0.251953 | AF60: =IF(C60="","",AE60*Q60*K60%) -> 7.4235999e+10 | AG60: =(Tabla6[[#This Row],[Fecha Vto]]-TODAY())/365 -> 3.6958904 | AJ60: =IF(C60="","",IF(G60="UVR",Q60*AI60-S60,0)) -> 0
A61: =IF(C61="","",YEAR(C61)) -> 2025 | B61: 627 | C61: 45811 | D61: Mercado | E61: Títulos Recogidos por la Nación | F61: TFIT15260826 | G61: =+_xlfn.XLOOKUP(F61,Emisiones[Mnemotécnico SEN],Emisiones[Moneda],"",0,1) -> COP | J61: =+_xlfn.XLOOKUP(F61,Emisiones[Mnemotécnico SEN],Emisiones[Fecha Vencim.],"",0,1) -> 46260 | K61: =+_xlfn.XLOOKUP(F61,Emisiones[Mnemotécnico SEN],Emisiones[Tasa de Interés],"",0,1) -> 7.5 | L61: 8.715 | M61: 104.404 | N61: =IF(C61="","",PRICE(C61,J61,K61%,L61%,100,1,3)) -> 98.582221 | O61: =IF(C61="","",M61-N61) -> 5.8217789 | P61: =IF(C61="","",100*K61%-O61) -> 1.6782211 | Q61: =IF(C61="","",IF(G61="UVR",S61/V61,S61)) -> -3840025500000 | R61: =IF(C61="","",IF('Canjes desagregado'!$G61="UVR",'Canjes desagregado'!$V61*Q61*M61%,Q61*M61%)) -> -4.0091402e+12 | S61: -3840025500000 | T61: =IFERROR(IF(RIGHT(F61,2)=RIGHT(YEAR(J61),2),1,0),"") -> 1 | U61: =+IF(R61="","",R61) -> -4.0091402e+12 | V61: =+IF(F61<>"",(_xlfn.XLOOKUP(C61,UVR[Fecha (dd/mm/aaaa)],UVR[Pesos colombianos por UVR],"",0,1)),"") -> 390.5108 | W61: =IF(C61="","",IF(CONCATENATE(DAY(C61),"/",MONTH(C61),"/",2000)-CONCATENATE(DAY(J61),"/",MONTH(J61),"/",2000)<0,K61%*ABS(S61),0)) -> 288001912500 | X61: =IF(S61<0,-W61,W61) -> -288001912500 | AB61: =IF(C61="","",ROUND(V61*(1+'Inflación observada '!$B$390%)^(("31-12-2025"-C61)/365),3)) -> 402.168 | AD61: =IF(C61="","",IF(G61="UVR",Q61*AB61-S61,0)) -> 0 | AE61: =IF(C61="","",P61/+(O61+P61)) -> 0.22376281 | AF61: =IF(C61="","",AE61*Q61*K61%) -> -6.4444118e+10 | AG61: =(Tabla6[[#This Row],[Fecha Vto]]-TODAY())/365 -> 0.70410959 | AJ61: =IF(C61="","",IF(G61="UVR",Q61*AI61-S61,0)) -> 0
A62: =IF(C62="","",YEAR(C62)) -> 2025 | B62: 627 | C62: 45811 | D62: Mercado | E62: Títulos Entregados por la Nación | F62: TFIT05220829 | G62: =+_xlfn.XLOOKUP(F62,Emisiones[Mnemotécnico SEN],Emisiones[Moneda],"",0,1) -> COP | J62: =+_xlfn.XLOOKUP(F62,Emisiones[Mnemotécnico SEN],Emisiones[Fecha Vencim.],"",0,1) -> 47352 | K62: =+_xlfn.XLOOKUP(F62,Emisiones[Mnemotécnico SEN],Emisiones[Tasa de Interés],"",0,1) -> 11 | L62: 10.96 | M62: 108.682 | N62: =IF(C62="","",PRICE(C62,J62,K62%,L62%,100,1,3)) -> 100.0308 | O62: =IF(C62="","",M62-N62) -> 8.651199 | P62: =IF(C62="","",100*K62%-O62) -> 2.348801 | Q62: =IF(C62="","",IF(G62="UVR",S62/V62,S62)) -> 2869443700000 | R62: =IF(C62="","",IF('Canjes desagregado'!$G62="UVR",'Canjes desagregado'!$V62*Q62*M62%,Q62*M62%)) -> 3.1185688e+12 | S62: 2869443700000 | T62: =IFERROR(IF(RIGHT(F62,2)=RIGHT(YEAR(J62),2),1,0),"") -> 1 | U62: =+IF(R62="","",R62) -> 3.1185688e+12 | V62: =+IF(F62<>"",(_xlfn.XLOOKUP(C62,UVR[Fecha (dd/mm/aaaa)],UVR[Pesos colombianos por UVR],"",0,1)),"") -> 390.5108 | W62: =IF(C62="","",IF(CONCATENATE(DAY(C62),"/",MONTH(C62),"/",2000)-CONCATENATE(DAY(J62),"/",MONTH(J62),"/",2000)<0,K62%*ABS(S62),0)) -> 315638807000 | X62: =IF(S62<0,-W62,W62) -> 315638807000 | AB62: =IF(C62="","",ROUND(V62*(1+'Inflación observada '!$B$390%)^(("31-12-2025"-C62)/365),3)) -> 402.168 | AD62: =IF(C62="","",IF(G62="UVR",Q62*AB62-S62,0)) -> 0 | AE62: =IF(C62="","",P62/+(O62+P62)) -> 0.21352736 | AF62: =IF(C62="","",AE62*Q62*K62%) -> 6.7397523e+10 | AG62: =(Tabla6[[#This Row],[Fecha Vto]]-TODAY())/365 -> 3.6958904 | AJ62: =IF(C62="","",IF(G62="UVR",Q62*AI62-S62,0)) -> 0
A63: =IF(C63="","",YEAR(C63)) -> 2025 | B63: 627 | C63: 45811 | D63: Mercado | E63: Títulos Entregados por la Nación | F63: TFIT11090233 | G63: =+_xlfn.XLOOKUP(F63,Emisiones[Mnemotécnico SEN],Emisiones[Moneda],"",0,1) -> COP | J63: =+_xlfn.XLOOKUP(F63,Emisiones[Mnemotécnico SEN],Emisiones[Fecha Vencim.],"",0,1) -> 48619 | K63: =+_xlfn.XLOOKUP(F63,Emisiones[Mnemotécnico SEN],Emisiones[Tasa de Interés],"",0,1) -> 13.25 | L63: 12.059 | M63: 109.807 | N63: =IF(C63="","",PRICE(C63,J63,K63%,L63%,100,1,3)) -> 105.59967 | O63: =IF(C63="","",M63-N63) -> 4.2073252 | P63: =IF(C63="","",100*K63%-O63) -> 9.0426748 | Q63: =IF(C63="","",IF(G63="UVR",S63/V63,S63)) -> 645589000000 | R63: =IF(C63="","",IF('Canjes desagregado'!$G63="UVR",'Canjes desagregado'!$V63*Q63*M63%,Q63*M63%)) -> 7.0890191e+11 | S63: 645589000000 | T63: =IFERROR(IF(RIGHT(F63,2)=RIGHT(YEAR(J63),2),1,0),"") -> 1 | U63: =+IF(R63="","",R63) -> 7.0890191e+11 | V63: =+IF(F63<>"",(_xlfn.XLOOKUP(C63,UVR[Fecha (dd/mm/aaaa)],UVR[Pesos colombianos por UVR],"",0,1)),"") -> 390.5108 | W63: =IF(C63="","",IF(CONCATENATE(DAY(C63),"/",MONTH(C63),"/",2000)-CONCATENATE(DAY(J63),"/",MONTH(J63),"/",2000)<0,K63%*ABS(S63),0)) -> 0 | X63: =IF(S63<0,-W63,W63) -> 0 | AB63: =IF(C63="","",ROUND(V63*(1+'Inflación observada '!$B$390%)^(("31-12-2025"-C63)/365),3)) -> 402.168 | AD63: =IF(C63="","",IF(G63="UVR",Q63*AB63-S63,0)) -> 0 | AE63: =IF(C63="","",P63/+(O63+P63)) -> 0.68246602 | AF63: =IF(C63="","",AE63*Q63*K63%) -> 5.8378514e+10 | AG63: =(Tabla6[[#This Row],[Fecha Vto]]-TODAY())/365 -> 7.1671233 | AJ63: =IF(C63="","",IF(G63="UVR",Q63*AI63-S63,0)) -> 0
A64: =IF(C64="","",YEAR(C64)) -> 2025 | B64: 627 | C64: 45811 | D64: Mercado | E64: Títulos Entregados por la Nación | F64: TFIT16281140 | G64: =+_xlfn.XLOOKUP(F64,Emisiones[Mnemotécnico SEN],Emisiones[Moneda],"",0,1) -> COP | J64: =+_xlfn.XLOOKUP(F64,Emisiones[Mnemotécnico SEN],Emisiones[Fecha Vencim.],"",0,1) -> 51468 | K64: =+_xlfn.XLOOKUP(F64,Emisiones[Mnemotécnico SEN],Emisiones[Tasa de Interés],"",0,1) -> 12.75 | L64: 12.89 | M64: 105.489 | N64: =IF(C64="","",PRICE(C64,J64,K64%,L64%,100,1,3)) -> 98.886833 | O64: =IF(C64="","",M64-N64) -> 6.602167 | P64: =IF(C64="","",100*K64%-O64) -> 6.147833 | Q64: =IF(C64="","",IF(G64="UVR",S64/V64,S64)) -> 55918400000 | R64: =IF(C64="","",IF('Canjes desagregado'!$G64="UVR",'Canjes desagregado'!$V64*Q64*M64%,Q64*M64%)) -> 5.8987761e+10 | S64: 55918400000 | T64: =IFERROR(IF(RIGHT(F64,2)=RIGHT(YEAR(J64),2),1,0),"") -> 1 | U64: =+IF(R64="","",R64) -> 5.8987761e+10 | V64: =+IF(F64<>"",(_xlfn.XLOOKUP(C64,UVR[Fecha (dd/mm/aaaa)],UVR[Pesos colombianos por UVR],"",0,1)),"") -> 390.5108 | W64: =IF(C64="","",IF(CONCATENATE(DAY(C64),"/",MONTH(C64),"/",2000)-CONCATENATE(DAY(J64),"/",MONTH(J64),"/",2000)<0,K64%*ABS(S64),0)) -> 7129596000 | X64: =IF(S64<0,-W64,W64) -> 7129596000 | AB64: =IF(C64="","",ROUND(V64*(1+'Inflación observada '!$B$390%)^(("31-12-2025"-C64)/365),3)) -> 402.168 | AD64: =IF(C64="","",IF(G64="UVR",Q64*AB64-S64,0)) -> 0 | AE64: =IF(C64="","",P64/+(O64+P64)) -> 0.48218298 | AF64: =IF(C64="","",AE64*Q64*K64%) -> 3.4377698e+09 | AG64: =(Tabla6[[#This Row],[Fecha Vto]]-TODAY())/365 -> 14.972603 | AJ64: =IF(C64="","",IF(G64="UVR",Q64*AI64-S64,0)) -> 0
A65: =IF(C65="","",YEAR(C65)) -> 2025 | B65: 627 | C65: 45811 | D65: Mercado | E65: Títulos Entregados por la Nación | F65: TFIT23250746 | G65: =+_xlfn.XLOOKUP(F65,Emisiones[Mnemotécnico SEN],Emisiones[Moneda],"",0,1) -> COP | J65: =+_xlfn.XLOOKUP(F65,Emisiones[Mnemotécnico SEN],Emisiones[Fecha Vencim.],"",0,1) -> 53533 | K65: =+_xlfn.XLOOKUP(F65,Emisiones[Mnemotécnico SEN],Emisiones[Tasa de Interés],"",0,1) -> 11.5 | L65: 12.87 | M65: 100.02 | N65: =IF(C65="","",PRICE(C65,J65,K65%,L65%,100,1,3)) -> 90.092024 | O65: =IF(C65="","",M65-N65) -> 9.9279763 | P65: =IF(C65="","",100*K65%-O65) -> 1.5720237 | Q65: =IF(C65="","",IF(G65="UVR",S65/V65,S65)) -> 80000000000 | R65: =IF(C65="","",IF('Canjes desagregado'!$G65="UVR",'Canjes desagregado'!$V65*Q65*M65%,Q65*M65%)) -> 80016000000 | S65: 80000000000 | T65: =IFERROR(IF(RIGHT(F65,2)=RIGHT(YEAR(J65),2),1,0),"") -> 1 | U65: =+IF(R65="","",R65) -> 80016000000 | V65: =+IF(F65<>"",(_xlfn.XLOOKUP(C65,UVR[Fecha (dd/mm/aaaa)],UVR[Pesos colombianos por UVR],"",0,1)),"") -> 390.5108 | W65: =IF(C65="","",IF(CONCATENATE(DAY(C65),"/",MONTH(C65),"/",2000)-CONCATENATE(DAY(J65),"/",MONTH(J65),"/",2000)<0,K65%*ABS(S65),0)) -> 9200000000 | X65: =IF(S65<0,-W65,W65) -> 9200000000 | AB65: =IF(C65="","",ROUND(V65*(1+'Inflación observada '!$B$390%)^(("31-12-2025"-C65)/365),3)) -> 402.168 | AD65: =IF(C65="","",IF(G65="UVR",Q65*AB65-S65,0)) -> 0 | AE65: =IF(C65="","",P65/+(O65+P65)) -> 0.13669771 | AF65: =IF(C65="","",AE65*Q65*K65%) -> 1.2576189e+09 | AG65: =(Tabla6[[#This Row],[Fecha Vto]]-TODAY())/365 -> 20.630137 | AJ65: =IF(C65="","",IF(G65="UVR",Q65*AI65-S65,0)) -> 0
A66: =IF(C66="","",YEAR(C66)) -> 2025 | B66: 627 | C66: 45811 | D66: Mercado | E66: Títulos Entregados por la Nación | F66: TFIT31261050 | G66: =+_xlfn.XLOOKUP(F66,Emisiones[Mnemotécnico SEN],Emisiones[Moneda],"",0,1) -> COP | J66: =+_xlfn.XLOOKUP(F66,Emisiones[Mnemotécnico SEN],Emisiones[Fecha Vencim.],"",0,1) -> 55087 | K66: =+_xlfn.XLOOKUP(F66,Emisiones[Mnemotécnico SEN],Emisiones[Tasa de Interés],"",0,1) -> 7.25 | L66: 12.75 | M66: 63.217 | N66: =IF(C66="","",PRICE(C66,J66,K66%,L66%,100,1,3)) -> 58.805738 | O66: =IF(C66="","",M66-N66) -> 4.4112618 | P66: =IF(C66="","",100*K66%-O66) -> 2.8387382 | Q66: =IF(C66="","",IF(G66="UVR",S66/V66,S66)) -> 37500000000 | R66: =IF(C66="","",IF('Canjes desagregado'!$G66="UVR",'Canjes desagregado'!$V66*Q66*M66%,Q66*M66%)) -> 2.3706375e+10 | S66: 37500000000 | T66: =IFERROR(IF(RIGHT(F66,2)=RIGHT(YEAR(J66),2),1,0),"") -> 1 | U66: =+IF(R66="","",R66) -> 2.3706375e+10 | V66: =+IF(F66<>"",(_xlfn.XLOOKUP(C66,UVR[Fecha (dd/mm/aaaa)],UVR[Pesos colombianos por UVR],"",0,1)),"") -> 390.5108 | W66: =IF(C66="","",IF(CONCATENATE(DAY(C66),"/",MONTH(C66),"/",2000)-CONCATENATE(DAY(J66),"/",MONTH(J66),"/",2000)<0,K66%*ABS(S66),0)) -> 2718750000 | X66: =IF(S66<0,-W66,W66) -> 2718750000 | AB66: =IF(C66="","",ROUND(V66*(1+'Inflación observada '!$B$390%)^(("31-12-2025"-C66)/365),3)) -> 402.168 | AD66: =IF(C66="","",IF(G66="UVR",Q66*AB66-S66,0)) -> 0 | AE66: =IF(C66="","",P66/+(O66+P66)) -> 0.39155009 | AF66: =IF(C66="","",AE66*Q66*K66%) -> 1.0645268e+09 | AG66: =(Tabla6[[#This Row],[Fecha Vto]]-TODAY())/365 -> 24.887671 | AJ66: =IF(C66="","",IF(G66="UVR",Q66*AI66-S66,0)) -> 0
A67: =IF(C67="","",YEAR(C67)) -> 2025 | B67: 628 | C67: 45821 | D67: Tesorería | E67: Títulos Recogidos por la Nación | F67: TFIT08261125 | G67: =+_xlfn.XLOOKUP(F67,Emisiones[Mnemotécnico SEN],Emisiones[Moneda],"",0,1) -> COP | J67: =+_xlfn.XLOOKUP(F67,Emisiones[Mnemotécnico SEN],Emisiones[Fecha Vencim.],"",0,1) -> 45987 | K67: =+_xlfn.XLOOKUP(F67,Emisiones[Mnemotécnico SEN],Emisiones[Tasa de Interés],"",0,1) -> 6.25 | L67: 8.802 | M67: 102.251 | N67: =IF(C67="","",PRICE(C67,J67,K67%,L67%,100,1,3)) -> 98.752881 | O67: =IF(C67="","",M67-N67) -> 3.4981192 | P67: =IF(C67="","",100*K67%-O67) -> 2.7518808 | Q67: =IF(C67="","",IF(G67="UVR",S67/V67,S67)) -> -241140800000 | R67: =IF(C67="","",IF('Canjes desagregado'!$G67="UVR",'Canjes desagregado'!$V67*Q67*M67%,Q67*M67%)) -> -246568879408 | S67: -241140800000 | T67: =IFERROR(IF(RIGHT(F67,2)=RIGHT(YEAR(J67),2),1,0),"") -> 1 | U67: =+IF(R67="","",R67) -> -246568879408 | V67: =+IF(F67<>"",(_xlfn.XLOOKUP(C67,UVR[Fecha (dd/mm/aaaa)],UVR[Pesos colombianos por UVR],"",0,1)),"") -> 391.3404 | W67: =IF(C67="","",IF(CONCATENATE(DAY(C67),"/",MONTH(C67),"/",2000)-CONCATENATE(DAY(J67),"/",MONTH(J67),"/",2000)<0,K67%*ABS(S67),0)) -> 15071300000 | X67: =IF(S67<0,-W67,W67) -> -15071300000 | AB67: =IF(C67="","",ROUND(V67*(1+'Inflación observada '!$B$390%)^(("31-12-2025"-C67)/365),3)) -> 402.461 | AD67: =IF(C67="","",IF(G67="UVR",Q67*AB67-S67,0)) -> 0 | AE67: =IF(C67="","",P67/+(O67+P67)) -> 0.44030092 | AF67: =IF(C67="","",AE67*Q67*K67%) -> -6.6359073e+09 | AG67: =(Tabla6[[#This Row],[Fecha Vto]]-TODAY())/365 -> -0.043835616 | AJ67: =IF(C67="","",IF(G67="UVR",Q67*AI67-S67,0)) -> 0
A68: =IF(C68="","",YEAR(C68)) -> 2025 | B68: 628 | C68: 45821 | D68: Tesorería | E68: Títulos Recogidos por la Nación | F68: TFIT15260826 | G68: =+_xlfn.XLOOKUP(F68,Emisiones[Mnemotécnico SEN],Emisiones[Moneda],"",0,1) -> COP | J68: =+_xlfn.XLOOKUP(F68,Emisiones[Mnemotécnico SEN],Emisiones[Fecha Vencim.],"",0,1) -> 46260 | K68: =+_xlfn.XLOOKUP(F68,Emisiones[Mnemotécnico SEN],Emisiones[Tasa de Interés],"",0,1) -> 7.5 | L68: 9.101 | M68: 104.177 | N68: =IF(C68="","",PRICE(C68,J68,K68%,L68%,100,1,3)) -> 98.197064 | O68: =IF(C68="","",M68-N68) -> 5.979936 | P68: =IF(C68="","",100*K68%-O68) -> 1.520064 | Q68: =IF(C68="","",IF(G68="UVR",S68/V68,S68)) -> -1865500000000 | R68: =IF(C68="","",IF('Canjes desagregado'!$G68="UVR",'Canjes desagregado'!$V68*Q68*M68%,Q68*M68%)) -> -1.9434219e+12 | S68: -1865500000000 | T68: =IFERROR(IF(RIGHT(F68,2)=RIGHT(YEAR(J68),2),1,0),"") -> 1 | U68: =+IF(R68="","",R68) -> -1.9434219e+12 | V68: =+IF(F68<>"",(_xlfn.XLOOKUP(C68,UVR[Fecha (dd/mm/aaaa)],UVR[Pesos colombianos por UVR],"",0,1)),"") -> 391.3404 | W68: =IF(C68="","",IF(CONCATENATE(DAY(C68),"/",MONTH(C68),"/",2000)-CONCATENATE(DAY(J68),"/",MONTH(J68),"/",2000)<0,K68%*ABS(S68),0)) -> 139912500000 | X68: =IF(S68<0,-W68,W68) -> -139912500000 | AB68: =IF(C68="","",ROUND(V68*(1+'Inflación observada '!$B$390%)^(("31-12-2025"-C68)/365),3)) -> 402.461 | AD68: =IF(C68="","",IF(G68="UVR",Q68*AB68-S68,0)) -> 0 | AE68: =IF(C68="","",P68/+(O68+P68)) -> 0.2026752 | AF68: =IF(C68="","",AE68*Q68*K68%) -> -2.8356793e+10 | AG68: =(Tabla6[[#This Row],[Fecha Vto]]-TODAY())/365 -> 0.70410959 | AJ68: =IF(C68="","",IF(G68="UVR",Q68*AI68-S68,0)) -> 0
A69: =IF(C69="","",YEAR(C69)) -> 2025 | B69: 628 | C69: 45821 | D69: Tesorería | E69: Títulos Entregados por la Nación | F69: TFIT16280428 | G69: =+_xlfn.XLOOKUP(F69,Emisiones[Mnemotécnico SEN],Emisiones[Moneda],"",0,1) -> COP | J69: =+_xlfn.XLOOKUP(F69,Emisiones[Mnemotécnico SEN],Emisiones[Fecha Vencim.],"",0,1) -> 46871 | K69: =+_xlfn.XLOOKUP(F69,Emisiones[Mnemotécnico SEN],Emisiones[Tasa de Interés],"",0,1) -> 6 | L69: 10.318 | M69: 90.434 | N69: =IF(C69="","",PRICE(C69,J69,K69%,L69%,100,1,3)) -> 89.67771 | O69: =IF(C69="","",M69-N69) -> 0.75629009 | P69: =IF(C69="","",100*K69%-O69) -> 5.2437099 | Q69: =IF(C69="","",IF(G69="UVR",S69/V69,S69)) -> 2106640800000 | R69: =IF(C69="","",IF('Canjes desagregado'!$G69="UVR",'Canjes desagregado'!$V69*Q69*M69%,Q69*M69%)) -> 1.9051195e+12 | S69: 2106640800000 | T69: =IFERROR(IF(RIGHT(F69,2)=RIGHT(YEAR(J69),2),1,0),"") -> 1 | U69: =+IF(R69="","",R69) -> 1.9051195e+12 | V69: =+IF(F69<>"",(_xlfn.XLOOKUP(C69,UVR[Fecha (dd/mm/aaaa)],UVR[Pesos colombianos por UVR],"",0,1)),"") -> 391.3404 | W69: =IF(C69="","",IF(CONCATENATE(DAY(C69),"/",MONTH(C69),"/",2000)-CONCATENATE(DAY(J69),"/",MONTH(J69),"/",2000)<0,K69%*ABS(S69),0)) -> 0 | X69: =IF(S69<0,-W69,W69) -> 0 | AB69: =IF(C69="","",ROUND(V69*(1+'Inflación observada '!$B$390%)^(("31-12-2025"-C69)/365),3)) -> 402.461 | AD69: =IF(C69="","",IF(G69="UVR",Q69*AB69-S69,0)) -> 0 | AE69: =IF(C69="","",P69/+(O69+P69)) -> 0.87395165 | AF69: =IF(C69="","",AE69*Q69*K69%) -> 1.1046613e+11 | AG69: =(Tabla6[[#This Row],[Fecha Vto]]-TODAY())/365 -> 2.3780822 | AJ69: =IF(C69="","",IF(G69="UVR",Q69*AI69-S69,0)) -> 0
A70: =IF(C70="","",YEAR(C70)) -> 2025 | B70: 629 | C70: 45860 | D70: Tesorería | E70: Títulos Recogidos por la Nación | F70: TFIT08261125 | G70: =+_xlfn.XLOOKUP(F70,Emisiones[Mnemotécnico SEN],Emisiones[Moneda],"",0,1) -> COP | J70: =+_xlfn.XLOOKUP(F70,Emisiones[Mnemotécnico SEN],Emisiones[Fecha Vencim.],"",0,1) -> 45987 | K70: =+_xlfn.XLOOKUP(F70,Emisiones[Mnemotécnico SEN],Emisiones[Tasa de Interés],"",0,1) -> 6.25 | L70: 9.184 | M70: 103.051 | N70: =IF(C70="","",PRICE(C70,J70,K70%,L70%,100,1,3)) -> 98.884545 | O70: =IF(C70="","",M70-N70) -> 4.1664553 | P70: =IF(C70="","",100*K70%-O70) -> 2.0835447 | Q70: =IF(C70="","",IF(G70="UVR",S70/V70,S70)) -> -373500000000 | R70: =IF(C70="","",IF('Canjes desagregado'!$G70="UVR",'Canjes desagregado'!$V70*Q70*M70%,Q70*M70%)) -> -384895485000 | S70: -373500000000 | T70: =IFERROR(IF(RIGHT(F70,2)=RIGHT(YEAR(J70),2),1,0),"") -> 1 | U70: =+IF(R70="","",R70) -> -384895485000 | V70: =+IF(F70<>"",(_xlfn.XLOOKUP(C70,UVR[Fecha (dd/mm/aaaa)],UVR[Pesos colombianos por UVR],"",0,1)),"") -> 392.848 | W70: =IF(C70="","",IF(CONCATENATE(DAY(C70),"/",MONTH(C70),"/",2000)-CONCATENATE(DAY(J70),"/",MONTH(J70),"/",2000)<0,K70%*ABS(S70),0)) -> 23343750000 | X70: =IF(S70<0,-W70,W70) -> -23343750000 | AB70: =IF(C70="","",ROUND(V70*(1+'Inflación observada '!$B$390%)^(("31-12-2025"-C70)/365),3)) -> 401.821 | AD70: =IF(C70="","",IF(G70="UVR",Q70*AB70-S70,0)) -> 0 | AE70: =IF(C70="","",P70/+(O70+P70)) -> 0.33336716 | AF70: =IF(C70="","",AE70*Q70*K70%) -> -7.7820395e+09 | AG70: =(Tabla6[[#This Row],[Fecha Vto]]-TODAY())/365 -> -0.043835616 | AJ70: =IF(C70="","",IF(G70="UVR",Q70*AI70-S70,0)) -> 0
A71: =IF(C71="","",YEAR(C71)) -> 2025 | B71: 629 | C71: 45860 | D71: Tesorería | E71: Títulos Recogidos por la Nación | F71: TFIT15260826 | G71: =+_xlfn.XLOOKUP(F71,Emisiones[Mnemotécnico SEN],Emisiones[Moneda],"",0,1) -> COP | J71: =+_xlfn.XLOOKUP(F71,Emisiones[Mnemotécnico SEN],Emisiones[Fecha Vencim.],"",0,1) -> 46260 | K71: =+_xlfn.XLOOKUP(F71,Emisiones[Mnemotécnico SEN],Emisiones[Tasa de Interés],"",0,1) -> 7.5 | L71: 8.907 | M71: 105.343 | N71: =IF(C71="","",PRICE(C71,J71,K71%,L71%,100,1,3)) -> 98.561826 | O71: =IF(C71="","",M71-N71) -> 6.7811742 | P71: =IF(C71="","",100*K71%-O71) -> 0.71882579 | Q71: =IF(C71="","",IF(G71="UVR",S71/V71,S71)) -> -246817300000 | R71: =IF(C71="","",IF('Canjes desagregado'!$G71="UVR",'Canjes desagregado'!$V71*Q71*M71%,Q71*M71%)) -> -2.6000475e+11 | S71: -246817300000 | T71: =IFERROR(IF(RIGHT(F71,2)=RIGHT(YEAR(J71),2),1,0),"") -> 1 | U71: =+IF(R71="","",R71) -> -2.6000475e+11 | V71: =+IF(F71<>"",(_xlfn.XLOOKUP(C71,UVR[Fecha (dd/mm/aaaa)],UVR[Pesos colombianos por UVR],"",0,1)),"") -> 392.848 | W71: =IF(C71="","",IF(CONCATENATE(DAY(C71),"/",MONTH(C71),"/",2000)-CONCATENATE(DAY(J71),"/",MONTH(J71),"/",2000)<0,K71%*ABS(S71),0)) -> 18511297500 | X71: =IF(S71<0,-W71,W71) -> -18511297500 | AB71: =IF(C71="","",ROUND(V71*(1+'Inflación observada '!$B$390%)^(("31-12-2025"-C71)/365),3)) -> 401.821 | AD71: =IF(C71="","",IF(G71="UVR",Q71*AB71-S71,0)) -> 0 | AE71: =IF(C71="","",P71/+(O71+P71)) -> 0.095843439 | AF71: =IF(C71="","",AE71*Q71*K71%) -> -1.7741864e+09 | AG71: =(Tabla6[[#This Row],[Fecha Vto]]-TODAY())/365 -> 0.70410959 | AJ71: =IF(C71="","",IF(G71="UVR",Q71*AI71-S71,0)) -> 0
A72: =IF(C72="","",YEAR(C72)) -> 2025 | B72: 629 | C72: 45860 | D72: Tesorería | E72: Títulos Recogidos por la Nación | F72: TFIT16300632 | G72: =+_xlfn.XLOOKUP(F72,Emisiones[Mnemotécnico SEN],Emisiones[Moneda],"",0,1) -> COP | J72: =+_xlfn.XLOOKUP(F72,Emisiones[Mnemotécnico SEN],Emisiones[Fecha Vencim.],"",0,1) -> 48395 | K72: =+_xlfn.XLOOKUP(F72,Emisiones[Mnemotécnico SEN],Emisiones[Tasa de Interés],"",0,1) -> 7 | L72: 11.447 | M72: 79.864 | N72: =IF(C72="","",PRICE(C72,J72,K72%,L72%,100,1,3)) -> 79.442166 | O72: =IF(C72="","",M72-N72) -> 0.42183443 | P72: =IF(C72="","",100*K72%-O72) -> 6.5781656 | Q72: =IF(C72="","",IF(G72="UVR",S72/V72,S72)) -> -271000000000 | R72: =IF(C72="","",IF('Canjes desagregado'!$G72="UVR",'Canjes desagregado'!$V72*Q72*M72%,Q72*M72%)) -> -216431440000 | S72: -271000000000 | T72: =IFERROR(IF(RIGHT(F72,2)=RIGHT(YEAR(J72),2),1,0),"") -> 1 | U72: =+IF(R72="","",R72) -> -216431440000 | V72: =+IF(F72<>"",(_xlfn.XLOOKUP(C72,UVR[Fecha (dd/mm/aaaa)],UVR[Pesos colombianos por UVR],"",0,1)),"") -> 392.848 | W72: =IF(C72="","",IF(CONCATENATE(DAY(C72),"/",MONTH(C72),"/",2000)-CONCATENATE(DAY(J72),"/",MONTH(J72),"/",2000)<0,K72%*ABS(S72),0)) -> 0 | X72: =IF(S72<0,-W72,W72) -> 0 | AB72: =IF(C72="","",ROUND(V72*(1+'Inflación observada '!$B$390%)^(("31-12-2025"-C72)/365),3)) -> 401.821 | AD72: =IF(C72="","",IF(G72="UVR",Q72*AB72-S72,0)) -> 0 | AE72: =IF(C72="","",P72/+(O72+P72)) -> 0.93973794 | AF72: =IF(C72="","",AE72*Q72*K72%) -> -1.7826829e+10 | AG72: =(Tabla6[[#This Row],[Fecha Vto]]-TODAY())/365 -> 6.5534247 | AJ72: =IF(C72="","",IF(G72="UVR",Q72*AI72-S72,0)) -> 0
... A78: =IF(C78="","",YEAR(C78)) -> 2025 | B78: 629 | C78: 45860 | D78: Tesorería | E78: Títulos Entregados por la Nación | F78: TFIT05220829 | G78: =+_xlfn.XLOOKUP(F78,Emisiones[Mnemotécnico SEN],Emisiones[Moneda],"",0,1) -> COP | J78: =+_xlfn.XLOOKUP(F78,Emisiones[Mnemotécnico SEN],Emisiones[Fecha Vencim.],"",0,1) -> 47352 | K78: =+_xlfn.XLOOKUP(F78,Emisiones[Mnemotécnico SEN],Emisiones[Tasa de Interés],"",0,1) -> 11 | L78: 10.654 | M78: 111.122 | N78: =IF(C78="","",PRICE(C78,J78,K78%,L78%,100,1,3)) -> 101.05609 | O78: =IF(C78="","",M78-N78) -> 10.065907 | P78: =IF(C78="","",100*K78%-O78) -> 0.93409289 | Q78: =IF(C78="","",IF(G78="UVR",S78/V78,S78)) -> 1100000000000 | R78: =IF(C78="","",IF('Canjes desagregado'!$G78="UVR",'Canjes desagregado'!$V78*Q78*M78%,Q78*M78%)) -> 1222342000000 | S78: 1100000000000 | T78: =IFERROR(IF(RIGHT(F78,2)=RIGHT(YEAR(J78),2),1,0),"") -> 1 | U78: =+IF(R78="","",R78) -> 1222342000000 | V78: =+IF(F78<>"",(_xlfn.XLOOKUP(C78,UVR[Fecha (dd/mm/aaaa)],UVR[Pesos colombianos por UVR],"",0,1)),"") -> 392.848 | W78: =IF(C78="","",IF(CONCATENATE(DAY(C78),"/",MONTH(C78),"/",2000)-CONCATENATE(DAY(J78),"/",MONTH(J78),"/",2000)<0,K78%*ABS(S78),0)) -> 121000000000 | X78: =IF(S78<0,-W78,W78) -> 121000000000 | AB78: =IF(C78="","",ROUND(V78*(1+'Inflación observada '!$B$390%)^(("31-12-2025"-C78)/365),3)) -> 401.821 | AD78: =IF(C78="","",IF(G78="UVR",Q78*AB78-S78,0)) -> 0 | AE78: =IF(C78="","",P78/+(O78+P78)) -> 0.084917535 | AF78: =IF(C78="","",AE78*Q78*K78%) -> 1.0275022e+10 | AG78: =(Tabla6[[#This Row],[Fecha Vto]]-TODAY())/365 -> 3.6958904 | AJ78: =IF(C78="","",IF(G78="UVR",Q78*AI78-S78,0)) -> 0
A79: 2025 | B79: 629 | C79: 45860 | D79: Tesorería | E79: Títulos Entregados por la Nación | F79: TFIT11090233 | G79: =+_xlfn.XLOOKUP(F79,Emisiones[Mnemotécnico SEN],Emisiones[Moneda],"",0,1) -> COP | J79: =+_xlfn.XLOOKUP(F79,Emisiones[Mnemotécnico SEN],Emisiones[Fecha Vencim.],"",0,1) -> 48619 | K79: =+_xlfn.XLOOKUP(F79,Emisiones[Mnemotécnico SEN],Emisiones[Tasa de Interés],"",0,1) -> 13.25 | L79: 11.58 | M79: 113.856 | N79: =IF(C79="","",PRICE(C79,J79,K79%,L79%,100,1,3)) -> 107.9391 | O79: =IF(C79="","",M79-N79) -> 5.9168952 | P79: =IF(C79="","",100*K79%-O79) -> 7.3331048 | Q79: =IF(C79="","",IF(G79="UVR",S79/V79,S79)) -> 14595781300000 | R79: =IF(C79="","",IF('Canjes desagregado'!$G79="UVR",'Canjes desagregado'!$V79*Q79*M79%,Q79*M79%)) -> 16618172756928 | S79: 14595781300000 | T79: =IFERROR(IF(RIGHT(F79,2)=RIGHT(YEAR(J79),2),1,0),"") -> 1 | U79: =+IF(R79="","",R79) -> 16618172756928 | V79: =+IF(F79<>"",(_xlfn.XLOOKUP(C79,UVR[Fecha (dd/mm/aaaa)],UVR[Pesos colombianos por UVR],"",0,1)),"") -> 392.848 | W79: =IF(C79="","",IF(CONCATENATE(DAY(C79),"/",MONTH(C79),"/",2000)-CONCATENATE(DAY(J79),"/",MONTH(J79),"/",2000)<0,K79%*ABS(S79),0)) -> 0 | X79: =IF(S79<0,-W79,W79) -> 0 | AB79: =IF(C79="","",ROUND(V79*(1+'Inflación observada '!$B$390%)^(("31-12-2025"-C79)/365),3)) -> 401.821 | AD79: =IF(C79="","",IF(G79="UVR",Q79*AB79-S79,0)) -> 0 | AE79: =IF(C79="","",P79/+(O79+P79)) -> 0.55344187 | AF79: =IF(C79="","",AE79*Q79*K79%) -> 1.0703239e+12 | AG79: =(Tabla6[[#This Row],[Fecha Vto]]-TODAY())/365 -> 7.1671233 | AJ79: =IF(C79="","",IF(G79="UVR",Q79*AI79-S79,0)) -> 0
A80: =IF(C80="","",YEAR(C80)) -> 2025 | B80: 630 | C80: 45863 | D80: Mercado | E80: Títulos Recogidos por la Nación | F80: TUVT11170327 | G80: =+_xlfn.XLOOKUP(F80,Emisiones[Mnemotécnico SEN],Emisiones[Moneda],"",0,1) -> UVR | J80: =+_xlfn.XLOOKUP(F80,Emisiones[Mnemotécnico SEN],Emisiones[Fecha Vencim.],"",0,1) -> 46463 | K80: =+_xlfn.XLOOKUP(F80,Emisiones[Mnemotécnico SEN],Emisiones[Tasa de Interés],"",0,1) -> 3.3 | L80: 5.302 | M80: 98.082 | N80: =IF(C80="","",PRICE(C80,J80,K80%,L80%,100,1,3)) -> 96.906209 | O80: =IF(C80="","",M80-N80) -> 1.175791 | P80: =IF(C80="","",100*K80%-O80) -> 2.124209 | Q80: =IF(C80="","",IF(G80="UVR",S80/V80,S80)) -> -3503500000 | R80: =IF(C80="","",IF('Canjes desagregado'!$G80="UVR",'Canjes desagregado'!$V80*Q80*M80%,Q80*M80%)) -> -1.3500753e+12 | S80: -1376476101000 | T80: =IFERROR(IF(RIGHT(F80,2)=RIGHT(YEAR(J80),2),1,0),"") -> 1 | U80: =+IF(R80="","",R80) -> -1.3500753e+12 | V80: =+IF(F80<>"",(_xlfn.XLOOKUP(C80,UVR[Fecha (dd/mm/aaaa)],UVR[Pesos colombianos por UVR],"",0,1)),"") -> 392.886 | W80: =IF(C80="","",IF(CONCATENATE(DAY(C80),"/",MONTH(C80),"/",2000)-CONCATENATE(DAY(J80),"/",MONTH(J80),"/",2000)<0,K80%*ABS(S80),0)) -> 0 | X80: =IF(S80<0,-W80,W80) -> 0 | AB80: =IF(C80="","",ROUND(V80*(1+'Inflación observada '!$B$390%)^(("31-12-2025"-C80)/365),3)) -> 401.692 | AD80: =IF(C80="","",IF(G80="UVR",Q80*AB80-S80,0)) -> -30851821000 | AE80: =IF(C80="","",P80/+(O80+P80)) -> 0.6436997 | AF80: =IF(C80="","",AE80*Q80*K80%) -> -74421663 | AG80: =(Tabla6[[#This Row],[Fecha Vto]]-TODAY())/365 -> 1.260274 | AJ80: =IF(C80="","",IF(G80="UVR",Q80*AI80-S80,0)) -> 1376476101000
A81: =IF(C81="","",YEAR(C81)) -> 2025 | B81: 630 | C81: 45863 | D81: Mercado | E81: Títulos Recogidos por la Nación | F81: TUVT10180429 | G81: =+_xlfn.XLOOKUP(F81,Emisiones[Mnemotécnico SEN],Emisiones[Moneda],"",0,1) -> UVR | J81: =+_xlfn.XLOOKUP(F81,Emisiones[Mnemotécnico SEN],Emisiones[Fecha Vencim.],"",0,1) -> 47226 | K81: =+_xlfn.XLOOKUP(F81,Emisiones[Mnemotécnico SEN],Emisiones[Tasa de Interés],"",0,1) -> 2.25 | L81: 5.869 | M81: 88.771 | N81: =IF(C81="","",PRICE(C81,J81,K81%,L81%,100,1,3)) -> 88.166942 | O81: =IF(C81="","",M81-N81) -> 0.60405845 | P81: =IF(C81="","",100*K81%-O81) -> 1.6459415 | Q81: =IF(C81="","",IF(G81="UVR",S81/V81,S81)) -> -8761512000 | R81: =IF(C81="","",IF('Canjes desagregado'!$G81="UVR",'Canjes desagregado'!$V81*Q81*M81%,Q81*M81%)) -> -3.0557423e+12 | S81: -3442275403632 | T81: =IFERROR(IF(RIGHT(F81,2)=RIGHT(YEAR(J81),2),1,0),"") -> 1 | U81: =+IF(R81="","",R81) -> -3.0557423e+12 | V81: =+IF(F81<>"",(_xlfn.XLOOKUP(C81,UVR[Fecha (dd/mm/aaaa)],UVR[Pesos colombianos por UVR],"",0,1)),"") -> 392.886 | W81: =IF(C81="","",IF(CONCATENATE(DAY(C81),"/",MONTH(C81),"/",2000)-CONCATENATE(DAY(J81),"/",MONTH(J81),"/",2000)<0,K81%*ABS(S81),0)) -> 0 | X81: =IF(S81<0,-W81,W81) -> 0 | AB81: =IF(C81="","",ROUND(V81*(1+'Inflación observada '!$B$390%)^(("31-12-2025"-C81)/365),3)) -> 401.692 | AD81: =IF(C81="","",IF(G81="UVR",Q81*AB81-S81,0)) -> -77153874672 | AE81: =IF(C81="","",P81/+(O81+P81)) -> 0.73152958 | AF81: =IF(C81="","",AE81*Q81*K81%) -> -1.4420937e+08 | AG81: =(Tabla6[[#This Row],[Fecha Vto]]-TODAY())/365 -> 3.3506849 | AJ81: =IF(C81="","",IF(G81="UVR",Q81*AI81-S81,0)) -> 3442275403632
A82: =IF(C82="","",YEAR(C82)) -> 2025 | B82: 630 | C82: 45863 | D82: Mercado | E82: Títulos Entregados por la Nación | F82: TUVT07220131 | G82: =+_xlfn.XLOOKUP(F82,Emisiones[Mnemotécnico SEN],Emisiones[Moneda],"",0,1) -> UVR | J82: =+_xlfn.XLOOKUP(F82,Emisiones[Mnemotécnico SEN],Emisiones[Fecha Vencim.],"",0,1) -> 47870 | K82: =+_xlfn.XLOOKUP(F82,Emisiones[Mnemotécnico SEN],Emisiones[Tasa de Interés],"",0,1) -> 6.5 | L82: 6.47 | M82: 103.361 | N82: =IF(C82="","",PRICE(C82,J82,K82%,L82%,100,1,3)) -> 100.08421 | O82: =IF(C82="","",M82-N82) -> 3.2767893 | P82: =IF(C82="","",100*K82%-O82) -> 3.2232107 | Q82: =IF(C82="","",IF(G82="UVR",S82/V82,S82)) -> 6344532000 | R82: =IF(C82="","",IF('Canjes desagregado'!$G82="UVR",'Canjes desagregado'!$V82*Q82*M82%,Q82*M82%)) -> 2.5764567e+12 | S82: 2492677799352 | T82: =IFERROR(IF(RIGHT(F82,2)=RIGHT(YEAR(J82),2),1,0),"") -> 1 | U82: =+IF(R82="","",R82) -> 2.5764567e+12 | V82: =+IF(F82<>"",(_xlfn.XLOOKUP(C82,UVR[Fecha (dd/mm/aaaa)],UVR[Pesos colombianos por UVR],"",0,1)),"") -> 392.886 | W82: =IF(C82="","",IF(CONCATENATE(DAY(C82),"/",MONTH(C82),"/",2000)-CONCATENATE(DAY(J82),"/",MONTH(J82),"/",2000)<0,K82%*ABS(S82),0)) -> 0 | X82: =IF(S82<0,-W82,W82) -> 0 | AB82: =IF(C82="","",ROUND(V82*(1+'Inflación observada '!$B$390%)^(("31-12-2025"-C82)/365),3)) -> 401.692 | AD82: =IF(C82="","",IF(G82="UVR",Q82*AB82-S82,0)) -> 55869948792 | AE82: =IF(C82="","",P82/+(O82+P82)) -> 0.49587856 | AF82: =IF(C82="","",AE82*Q82*K82%) -> 2.0449763e+08 | AG82: =(Tabla6[[#This Row],[Fecha Vto]]-TODAY())/365 -> 5.1150685 | AJ82: =IF(C82="","",IF(G82="UVR",Q82*AI82-S82,0)) -> -2492677799352
A83: =IF(C83="","",YEAR(C83)) -> 2025 | B83: 630 | C83: 45863 | D83: Mercado | E83: Títulos Entregados por la Nación | F83: TUVT38010262 | G83: =+_xlfn.XLOOKUP(F83,Emisiones[Mnemotécnico SEN],Emisiones[Moneda],"",0,1) -> UVR | J83: =+_xlfn.XLOOKUP(F83,Emisiones[Mnemotécnico SEN],Emisiones[Fecha Vencim.],"",0,1) -> 59203 | K83: =+_xlfn.XLOOKUP(F83,Emisiones[Mnemotécnico SEN],Emisiones[Tasa de Interés],"",0,1) -> 6.5 | L83: 6.528 | M83: 102.661 | N83: =IF(C83="","",PRICE(C83,J83,K83%,L83%,100,1,3)) -> 99.562429 | O83: =IF(C83="","",M83-N83) -> 3.098571 | P83: =IF(C83="","",100*K83%-O83) -> 3.401429 | Q83: =IF(C83="","",IF(G83="UVR",S83/V83,S83)) -> 4535451000 | R83: =IF(C83="","",IF('Canjes desagregado'!$G83="UVR",'Canjes desagregado'!$V83*Q83*M83%,Q83*M83%)) -> 1.829332e+12 | S83: 1781915201586 | T83: =IFERROR(IF(RIGHT(F83,2)=RIGHT(YEAR(J83),2),1,0),"") -> 1 | U83: =+IF(R83="","",R83) -> 1.829332e+12 | V83: =+IF(F83<>"",(_xlfn.XLOOKUP(C83,UVR[Fecha (dd/mm/aaaa)],UVR[Pesos colombianos por UVR],"",0,1)),"") -> 392.886 | W83: =IF(C83="","",IF(CONCATENATE(DAY(C83),"/",MONTH(C83),"/",2000)-CONCATENATE(DAY(J83),"/",MONTH(J83),"/",2000)<0,K83%*ABS(S83),0)) -> 0 | X83: =IF(S83<0,-W83,W83) -> 0 | AB83: =IF(C83="","",ROUND(V83*(1+'Inflación observada '!$B$390%)^(("31-12-2025"-C83)/365),3)) -> 401.692 | AD83: =IF(C83="","",IF(G83="UVR",Q83*AB83-S83,0)) -> 39939181506 | AE83: =IF(C83="","",P83/+(O83+P83)) -> 0.52329677 | AF83: =IF(C83="","",AE83*Q83*K83%) -> 1.5427015e+08 | AG83: =(Tabla6[[#This Row],[Fecha Vto]]-TODAY())/365 -> 36.164384 | AJ83: =IF(C83="","",IF(G83="UVR",Q83*AI83-S83,0)) -> -1781915201586
A84: =IF(C84="","",YEAR(C84)) -> 2025 | B84: 631 | C84: 45869 | D84: Tesorería | E84: Títulos Recogidos por la Nación | F84: TFIT08261125 | G84: =+_xlfn.XLOOKUP(F84,Emisiones[Mnemotécnico SEN],Emisiones[Moneda],"",0,1) -> COP | J84: =+_xlfn.XLOOKUP(F84,Emisiones[Mnemotécnico SEN],Emisiones[Fecha Vencim.],"",0,1) -> 45987 | K84: =+_xlfn.XLOOKUP(F84,Emisiones[Mnemotécnico SEN],Emisiones[Tasa de Interés],"",0,1) -> 6.25 | L84: 8.977 | M84: 103.338 | N84: =IF(C84="","",PRICE(C84,J84,K84%,L84%,100,1,3)) -> 99.023975 | O84: =IF(C84="","",M84-N84) -> 4.3140249 | P84: =IF(C84="","",100*K84%-O84) -> 1.9359751 | Q84: -240000000000 | R84: =IF(C84="","",IF('Canjes desagregado'!$G84="UVR",'Canjes desagregado'!$V84*Q84*M84%,Q84*M84%)) -> -248011200000 | S84: -240000000000 | T84: =IFERROR(IF(RIGHT(F84,2)=RIGHT(YEAR(J84),2),1,0),"") -> 1 | U84: =+IF(R84="","",R84) -> -248011200000 | V84: =+IF(F84<>"",(_xlfn.XLOOKUP(C84,UVR[Fecha (dd/mm/aaaa)],UVR[Pesos colombianos por UVR],"",0,1)),"") -> 392.962 | W84: =IF(C84="","",IF(CONCATENATE(DAY(C84),"/",MONTH(C84),"/",2000)-CONCATENATE(DAY(J84),"/",MONTH(J84),"/",2000)<0,K84%*ABS(S84),0)) -> 15000000000 | X84: =IF(S84<0,-W84,W84) -> -15000000000 | AB84: =IF(C84="","",ROUND(V84*(1+'Inflación observada '!$B$390%)^(("31-12-2025"-C84)/365),3)) -> 401.434 | AD84: =IF(C84="","",IF(G84="UVR",Q84*AB84-S84,0)) -> 0 | AE84: =IF(C84="","",P84/+(O84+P84)) -> 0.30975601 | AF84: =IF(C84="","",AE84*Q84*K84%) -> -4.6463402e+09 | AG84: =(Tabla6[[#This Row],[Fecha Vto]]-TODAY())/365 -> -0.043835616 | AJ84: =IF(C84="","",IF(G84="UVR",Q84*AI84-S84,0)) -> 0
A85: =IF(C85="","",YEAR(C85)) -> 2025 | B85: 631 | C85: 45869 | D85: Tesorería | E85: Títulos Recogidos por la Nación | F85: TFIT15260826 | G85: =+_xlfn.XLOOKUP(F85,Emisiones[Mnemotécnico SEN],Emisiones[Moneda],"",0,1) -> COP | J85: =+_xlfn.XLOOKUP(F85,Emisiones[Mnemotécnico SEN],Emisiones[Fecha Vencim.],"",0,1) -> 46260 | K85: =+_xlfn.XLOOKUP(F85,Emisiones[Mnemotécnico SEN],Emisiones[Tasa de Interés],"",0,1) -> 7.5 | L85: 8.525 | M85: 105.936 | N85: =IF(C85="","",PRICE(C85,J85,K85%,L85%,100,1,3)) -> 98.970608 | O85: =IF(C85="","",M85-N85) -> 6.9653921 | P85: =IF(C85="","",100*K85%-O85) -> 0.53460789 | Q85: -1026012700000 | R85: =IF(C85="","",IF('Canjes desagregado'!$G85="UVR",'Canjes desagregado'!$V85*Q85*M85%,Q85*M85%)) -> -1.0869168e+12 | S85: -1026012700000 | T85: =IFERROR(IF(RIGHT(F85,2)=RIGHT(YEAR(J85),2),1,0),"") -> 1 | U85: =+IF(R85="","",R85) -> -1.0869168e+12 | V85: =+IF(F85<>"",(_xlfn.XLOOKUP(C85,UVR[Fecha (dd/mm/aaaa)],UVR[Pesos colombianos por UVR],"",0,1)),"") -> 392.962 | W85: =IF(C85="","",IF(CONCATENATE(DAY(C85),"/",MONTH(C85),"/",2000)-CONCATENATE(DAY(J85),"/",MONTH(J85),"/",2000)<0,K85%*ABS(S85),0)) -> 76950952500 | X85: =IF(S85<0,-W85,W85) -> -76950952500 | AB85: =IF(C85="","",ROUND(V85*(1+'Inflación observada '!$B$390%)^(("31-12-2025"-C85)/365),3)) -> 401.434 | AD85: =IF(C85="","",IF(G85="UVR",Q85*AB85-S85,0)) -> 0 | AE85: =IF(C85="","",P85/+(O85+P85)) -> 0.071281052 | AF85: =IF(C85="","",AE85*Q85*K85%) -> -5.4851448e+09 | AG85: =(Tabla6[[#This Row],[Fecha Vto]]-TODAY())/365 -> 0.70410959 | AJ85: =IF(C85="","",IF(G85="UVR",Q85*AI85-S85,0)) -> 0
A86: =IF(C86="","",YEAR(C86)) -> 2025 | B86: 631 | C86: 45869 | D86: Tesorería | E86: Títulos Entregados por la Nación | F86: TFIT05220829 | G86: =+_xlfn.XLOOKUP(F86,Emisiones[Mnemotécnico SEN],Emisiones[Moneda],"",0,1) -> COP | J86: =+_xlfn.XLOOKUP(F86,Emisiones[Mnemotécnico SEN],Emisiones[Fecha Vencim.],"",0,1) -> 47352 | K86: =+_xlfn.XLOOKUP(F86,Emisiones[Mnemotécnico SEN],Emisiones[Tasa de Interés],"",0,1) -> 11 | L86: 10.703 | M86: 111.244 | N86: =IF(C86="","",PRICE(C86,J86,K86%,L86%,100,1,3)) -> 100.90644 | O86: =IF(C86="","",M86-N86) -> 10.337558 | P86: =IF(C86="","",100*K86%-O86) -> 0.66244219 | Q86: =IF(C86="","",IF(G86="UVR",S86/V86,S86)) -> 1200000000000 | R86: =IF(C86="","",IF('Canjes desagregado'!$G86="UVR",'Canjes desagregado'!$V86*Q86*M86%,Q86*M86%)) -> 1334928000000 | S86: 1200000000000 | T86: =IFERROR(IF(RIGHT(F86,2)=RIGHT(YEAR(J86),2),1,0),"") -> 1 | U86: =+IF(R86="","",R86) -> 1334928000000 | V86: =+IF(F86<>"",(_xlfn.XLOOKUP(C86,UVR[Fecha (dd/mm/aaaa)],UVR[Pesos colombianos por UVR],"",0,1)),"") -> 392.962 | W86: =IF(C86="","",IF(CONCATENATE(DAY(C86),"/",MONTH(C86),"/",2000)-CONCATENATE(DAY(J86),"/",MONTH(J86),"/",2000)<0,K86%*ABS(S86),0)) -> 132000000000 | X86: =IF(S86<0,-W86,W86) -> 132000000000 | AB86: =IF(C86="","",ROUND(V86*(1+'Inflación observada '!$B$390%)^(("31-12-2025"-C86)/365),3)) -> 401.434 | AD86: =IF(C86="","",IF(G86="UVR",Q86*AB86-S86,0)) -> 0 | AE86: =IF(C86="","",P86/+(O86+P86)) -> 0.060222018 | AF86: =IF(C86="","",AE86*Q86*K86%) -> 7.9493063e+09 | AG86: =(Tabla6[[#This Row],[Fecha Vto]]-TODAY())/365 -> 3.6958904 | AJ86: =IF(C86="","",IF(G86="UVR",Q86*AI86-S86,0)) -> 0
A87: =IF(C87="","",YEAR(C87)) -> 2025 | B87: 632 | C87: 45881 | D87: Tesorería | E87: Títulos Recogidos por la Nación | F87: TFIT15260826 | G87: =+_xlfn.XLOOKUP(F87,Emisiones[Mnemotécnico SEN],Emisiones[Moneda],"",0,1) -> COP | J87: =+_xlfn.XLOOKUP(F87,Emisiones[Mnemotécnico SEN],Emisiones[Fecha Vencim.],"",0,1) -> 46260 | K87: =+_xlfn.XLOOKUP(F87,Emisiones[Mnemotécnico SEN],Emisiones[Tasa de Interés],"",0,1) -> 7.5 | L87: 8.996 | M87: 105.778 | N87: =IF(C87="","",PRICE(C87,J87,K87%,L87%,100,1,3)) -> 98.565073 | O87: =IF(C87="","",M87-N87) -> 7.2129268 | P87: =IF(C87="","",100*K87%-O87) -> 0.28707321 | Q87: =IF(C87="","",IF(G87="UVR",S87/V87,S87)) -> -117052300000 | R87: =IF(C87="","",IF('Canjes desagregado'!$G87="UVR",'Canjes desagregado'!$V87*Q87*M87%,Q87*M87%)) -> -1.2381558e+11 | S87: -117052300000 | T87: =IFERROR(IF(RIGHT(F87,2)=RIGHT(YEAR(J87),2),1,0),"") -> 1 | U87: =+IF(R87="","",R87) -> -1.2381558e+11 | V87: =+IF(F87<>"",(_xlfn.XLOOKUP(C87,UVR[Fecha (dd/mm/aaaa)],UVR[Pesos colombianos por UVR],"",0,1)),"") -> 393.114 | W87: =IF(C87="","",IF(CONCATENATE(DAY(C87),"/",MONTH(C87),"/",2000)-CONCATENATE(DAY(J87),"/",MONTH(J87),"/",2000)<0,K87%*ABS(S87),0)) -> 8778922500 | X87: =IF(S87<0,-W87,W87) -> -8778922500 | AB87: =IF(C87="","",ROUND(V87*(1+'Inflación observada '!$B$390%)^(("31-12-2025"-C87)/365),3)) -> 400.918 | AD87: =IF(C87="","",IF(G87="UVR",Q87*AB87-S87,0)) -> 0 | AE87: =IF(C87="","",P87/+(O87+P87)) -> 0.038276428 | AF87: =IF(C87="","",AE87*Q87*K87%) -> -3.3602579e+08 | AG87: =(Tabla6[[#This Row],[Fecha Vto]]-TODAY())/365 -> 0.70410959 | AJ87: =IF(C87="","",IF(G87="UVR",Q87*AI87-S87,0)) -> 0
A88: =IF(C88="","",YEAR(C88)) -> 2025 | B88: 632 | C88: 45881 | D88: Tesorería | E88: Títulos Recogidos por la Nación | F88: TFIT16180930 | G88: =+_xlfn.XLOOKUP(F88,Emisiones[Mnemotécnico SEN],Emisiones[Moneda],"",0,1) -> COP | J88: =+_xlfn.XLOOKUP(F88,Emisiones[Mnemotécnico SEN],Emisiones[Fecha Vencim.],"",0,1) -> 47744 | K88: =+_xlfn.XLOOKUP(F88,Emisiones[Mnemotécnico SEN],Emisiones[Tasa de Interés],"",0,1) -> 7.75 | L88: 10.85 | M88: 95.25 | N88: =IF(C88="","",PRICE(C88,J88,K88%,L88%,100,1,3)) -> 88.285177 | O88: =IF(C88="","",M88-N88) -> 6.9648235 | P88: =IF(C88="","",100*K88%-O88) -> 0.78517651 | Q88: =IF(C88="","",IF(G88="UVR",S88/V88,S88)) -> -1256822800000 | R88: =IF(C88="","",IF('Canjes desagregado'!$G88="UVR",'Canjes desagregado'!$V88*Q88*M88%,Q88*M88%)) -> -1197123717000 | S88: -1256822800000 | T88: =IFERROR(IF(RIGHT(F88,2)=RIGHT(YEAR(J88),2),1,0),"") -> 1 | U88: =+IF(R88="","",R88) -> -1197123717000 | V88: =+IF(F88<>"",(_xlfn.XLOOKUP(C88,UVR[Fecha (dd/mm/aaaa)],UVR[Pesos colombianos por UVR],"",0,1)),"") -> 393.114 | W88: =IF(C88="","",IF(CONCATENATE(DAY(C88),"/",MONTH(C88),"/",2000)-CONCATENATE(DAY(J88),"/",MONTH(J88),"/",2000)<0,K88%*ABS(S88),0)) -> 97403767000 | X88: =IF(S88<0,-W88,W88) -> -97403767000 | AB88: =IF(C88="","",ROUND(V88*(1+'Inflación observada '!$B$390%)^(("31-12-2025"-C88)/365),3)) -> 400.918 | AD88: =IF(C88="","",IF(G88="UVR",Q88*AB88-S88,0)) -> 0 | AE88: =IF(C88="","",P88/+(O88+P88)) -> 0.1013131 | AF88: =IF(C88="","",AE88*Q88*K88%) -> -9.8682774e+09 | AG88: =(Tabla6[[#This Row],[Fecha Vto]]-TODAY())/365 -> 4.769863 | AJ88: =IF(C88="","",IF(G88="UVR",Q88*AI88-S88,0)) -> 0
A89: =IF(C89="","",YEAR(C89)) -> 2025 | B89: 632 | C89: 45881 | D89: Tesorería | E89: Títulos Recogidos por la Nación | F89: TFIT16090736 | G89: =+_xlfn.XLOOKUP(F89,Emisiones[Mnemotécnico SEN],Emisiones[Moneda],"",0,1) -> COP | J89: =+_xlfn.XLOOKUP(F89,Emisiones[Mnemotécnico SEN],Emisiones[Fecha Vencim.],"",0,1) -> 49865 | K89: =+_xlfn.XLOOKUP(F89,Emisiones[Mnemotécnico SEN],Emisiones[Tasa de Interés],"",0,1) -> 6.25 | L89: 11.68 | M89: 67.998 | N89: =IF(C89="","",PRICE(C89,J89,K89%,L89%,100,1,3)) -> 67.416215 | O89: =IF(C89="","",M89-N89) -> 0.58178496 | P89: =IF(C89="","",100*K89%-O89) -> 5.668215 | Q89: =IF(C89="","",IF(G89="UVR",S89/V89,S89)) -> -580000000000 | R89: =IF(C89="","",IF('Canjes desagregado'!$G89="UVR",'Canjes desagregado'!$V89*Q89*M89%,Q89*M89%)) -> -394388400000 | S89: -580000000000 | T89: =IFERROR(IF(RIGHT(F89,2)=RIGHT(YEAR(J89),2),1,0),"") -> 1 | U89: =+IF(R89="","",R89) -> -394388400000 | V89: =+IF(F89<>"",(_xlfn.XLOOKUP(C89,UVR[Fecha (dd/mm/aaaa)],UVR[Pesos colombianos por UVR],"",0,1)),"") -> 393.114 | W89: =IF(C89="","",IF(CONCATENATE(DAY(C89),"/",MONTH(C89),"/",2000)-CONCATENATE(DAY(J89),"/",MONTH(J89),"/",2000)<0,K89%*ABS(S89),0)) -> 0 | X89: =IF(S89<0,-W89,W89) -> 0 | AB89: =IF(C89="","",ROUND(V89*(1+'Inflación observada '!$B$390%)^(("31-12-2025"-C89)/365),3)) -> 400.918 | AD89: =IF(C89="","",IF(G89="UVR",Q89*AB89-S89,0)) -> 0 | AE89: =IF(C89="","",P89/+(O89+P89)) -> 0.90691441 | AF89: =IF(C89="","",AE89*Q89*K89%) -> -3.2875647e+10 | AG89: =(Tabla6[[#This Row],[Fecha Vto]]-TODAY())/365 -> 10.580822 | AJ89: =IF(C89="","",IF(G89="UVR",Q89*AI89-S89,0)) -> 0
A90: =IF(C90="","",YEAR(C90)) -> 2025 | B90: 632 | C90: 45881 | D90: Tesorería | E90: Títulos Entregados por la Nación | F90: TFIT05220829 | G90: =+_xlfn.XLOOKUP(F90,Emisiones[Mnemotécnico SEN],Emisiones[Moneda],"",0,1) -> COP | J90: =+_xlfn.XLOOKUP(F90,Emisiones[Mnemotécnico SEN],Emisiones[Fecha Vencim.],"",0,1) -> 47352 | K90: =+_xlfn.XLOOKUP(F90,Emisiones[Mnemotécnico SEN],Emisiones[Tasa de Interés],"",0,1) -> 11 | L90: 10.74 | M90: 111.499 | N90: =IF(C90="","",PRICE(C90,J90,K90%,L90%,100,1,3)) -> 100.80044 | O90: =IF(C90="","",M90-N90) -> 10.698564 | P90: =IF(C90="","",100*K90%-O90) -> 0.30143614 | Q90: =IF(C90="","",IF(G90="UVR",S90/V90,S90)) -> 800000000000 | R90: =IF(C90="","",IF('Canjes desagregado'!$G90="UVR",'Canjes desagregado'!$V90*Q90*M90%,Q90*M90%)) -> 891992000000 | S90: 800000000000 | T90: =IFERROR(IF(RIGHT(F90,2)=RIGHT(YEAR(J90),2),1,0),"") -> 1 | U90: =+IF(R90="","",R90) -> 891992000000 | V90: =+IF(F90<>"",(_xlfn.XLOOKUP(C90,UVR[Fecha (dd/mm/aaaa)],UVR[Pesos colombianos por UVR],"",0,1)),"") -> 393.114 | W90: =IF(C90="","",IF(CONCATENATE(DAY(C90),"/",MONTH(C90),"/",2000)-CONCATENATE(DAY(J90),"/",MONTH(J90),"/",2000)<0,K90%*ABS(S90),0)) -> 88000000000 | X90: =IF(S90<0,-W90,W90) -> 88000000000 | AB90: =IF(C90="","",ROUND(V90*(1+'Inflación observada '!$B$390%)^(("31-12-2025"-C90)/365),3)) -> 400.918 | AD90: =IF(C90="","",IF(G90="UVR",Q90*AB90-S90,0)) -> 0 | AE90: =IF(C90="","",P90/+(O90+P90)) -> 0.027403285 | AF90: =IF(C90="","",AE90*Q90*K90%) -> 2.4114891e+09 | AG90: =(Tabla6[[#This Row],[Fecha Vto]]-TODAY())/365 -> 3.6958904 | AJ90: =IF(C90="","",IF(G90="UVR",Q90*AI90-S90,0)) -> 0
A91: =IF(C91="","",YEAR(C91)) -> 2025 | B91: 632 | C91: 45881 | D91: Tesorería | E91: Títulos Entregados por la Nación | F91: TFIT11090233 | G91: =+_xlfn.XLOOKUP(F91,Emisiones[Mnemotécnico SEN],Emisiones[Moneda],"",0,1) -> COP | J91: =+_xlfn.XLOOKUP(F91,Emisiones[Mnemotécnico SEN],Emisiones[Fecha Vencim.],"",0,1) -> 48619 | K91: =+_xlfn.XLOOKUP(F91,Emisiones[Mnemotécnico SEN],Emisiones[Tasa de Interés],"",0,1) -> 13.25 | L91: 11.793 | M91: 113.493 | N91: =IF(C91="","",PRICE(C91,J91,K91%,L91%,100,1,3)) -> 106.81315 | O91: =IF(C91="","",M91-N91) -> 6.6798548 | P91: =IF(C91="","",100*K91%-O91) -> 6.5701452 | Q91: =IF(C91="","",IF(G91="UVR",S91/V91,S91)) -> 725450600000 | R91: =IF(C91="","",IF('Canjes desagregado'!$G91="UVR",'Canjes desagregado'!$V91*Q91*M91%,Q91*M91%)) -> 823335649458 | S91: 725450600000 | T91: =IFERROR(IF(RIGHT(F91,2)=RIGHT(YEAR(J91),2),1,0),"") -> 1 | U91: =+IF(R91="","",R91) -> 823335649458 | V91: =+IF(F91<>"",(_xlfn.XLOOKUP(C91,UVR[Fecha (dd/mm/aaaa)],UVR[Pesos colombianos por UVR],"",0,1)),"") -> 393.114 | W91: =IF(C91="","",IF(CONCATENATE(DAY(C91),"/",MONTH(C91),"/",2000)-CONCATENATE(DAY(J91),"/",MONTH(J91),"/",2000)<0,K91%*ABS(S91),0)) -> 0 | X91: =IF(S91<0,-W91,W91) -> 0 | AB91: =IF(C91="","",ROUND(V91*(1+'Inflación observada '!$B$390%)^(("31-12-2025"-C91)/365),3)) -> 400.918 | AD91: =IF(C91="","",IF(G91="UVR",Q91*AB91-S91,0)) -> 0 | AE91: =IF(C91="","",P91/+(O91+P91)) -> 0.49586002 | AF91: =IF(C91="","",AE91*Q91*K91%) -> 4.7663158e+10 | AG91: =(Tabla6[[#This Row],[Fecha Vto]]-TODAY())/365 -> 7.1671233 | AJ91: =IF(C91="","",IF(G91="UVR",Q91*AI91-S91,0)) -> 0
A92: =IF(C92="","",YEAR(C92)) -> 2025 | B92: 633 | C92: 45904 | D92: Tesorería | E92: Títulos Recogidos por la Nación | F92: TFIT11090233 | G92: =+_xlfn.XLOOKUP(F92,Emisiones[Mnemotécnico SEN],Emisiones[Moneda],"",0,1) -> COP | J92: =+_xlfn.XLOOKUP(F92,Emisiones[Mnemotécnico SEN],Emisiones[Fecha Vencim.],"",0,1) -> 48619 | K92: =+_xlfn.XLOOKUP(F92,Emisiones[Mnemotécnico SEN],Emisiones[Tasa de Interés],"",0,1) -> 13.25 | L92: 11.851 | M92: 114.002 | N92: =IF(C92="","",PRICE(C92,J92,K92%,L92%,100,1,3)) -> 106.48749 | O92: =IF(C92="","",M92-N92) -> 7.5145106 | P92: =IF(C92="","",100*K92%-O92) -> 5.7354894 | Q92: =IF(C92="","",IF(G92="UVR",S92/V92,S92)) -> -546000000000 | R92: =IF(C92="","",IF('Canjes desagregado'!$G92="UVR",'Canjes desagregado'!$V92*Q92*M92%,Q92*M92%)) -> -622450920000 | S92: -546000000000 | T92: =IFERROR(IF(RIGHT(F92,2)=RIGHT(YEAR(J92),2),1,0),"") -> 1 | U92: =+IF(R92="","",R92) -> -622450920000 | V92: =+IF(F92<>"",(_xlfn.XLOOKUP(C92,UVR[Fecha (dd/mm/aaaa)],UVR[Pesos colombianos por UVR],"",0,1)),"") -> 393.862 | W92: =IF(C92="","",IF(CONCATENATE(DAY(C92),"/",MONTH(C92),"/",2000)-CONCATENATE(DAY(J92),"/",MONTH(J92),"/",2000)<0,K92%*ABS(S92),0)) -> 0 | X92: =IF(S92<0,-W92,W92) -> 0 | AB92: =IF(C92="","",ROUND(V92*(1+'Inflación observada '!$B$390%)^(("31-12-2025"-C92)/365),3)) -> 400.395 | AD92: =IF(C92="","",IF(G92="UVR",Q92*AB92-S92,0)) -> 0 | AE92: =IF(C92="","",P92/+(O92+P92)) -> 0.43286712 | AF92: =IF(C92="","",AE92*Q92*K92%) -> -3.1315772e+10 | AG92: =(Tabla6[[#This Row],[Fecha Vto]]-TODAY())/365 -> 7.1671233 | AJ92: =IF(C92="","",IF(G92="UVR",Q92*AI92-S92,0)) -> 0
A93: =IF(C93="","",YEAR(C93)) -> 2025 | B93: 633 | C93: 45904 | D93: Tesorería | E93: Títulos Entregados por la Nación | F93: TFIT16281140 | G93: =+_xlfn.XLOOKUP(F93,Emisiones[Mnemotécnico SEN],Emisiones[Moneda],"",0,1) -> COP | J93: =+_xlfn.XLOOKUP(F93,Emisiones[Mnemotécnico SEN],Emisiones[Fecha Vencim.],"",0,1) -> 51468 | K93: =+_xlfn.XLOOKUP(F93,Emisiones[Mnemotécnico SEN],Emisiones[Tasa de Interés],"",0,1) -> 12.75 | L93: 12.65 | M93: 110.306 | N93: =IF(C93="","",PRICE(C93,J93,K93%,L93%,100,1,3)) -> 100.52465 | O93: =IF(C93="","",M93-N93) -> 9.7813457 | P93: =IF(C93="","",100*K93%-O93) -> 2.9686543 | Q93: =IF(C93="","",IF(G93="UVR",S93/V93,S93)) -> 546000000000 | R93: =IF(C93="","",IF('Canjes desagregado'!$G93="UVR",'Canjes desagregado'!$V93*Q93*M93%,Q93*M93%)) -> 602270760000 | S93: 546000000000 | T93: =IFERROR(IF(RIGHT(F93,2)=RIGHT(YEAR(J93),2),1,0),"") -> 1 | U93: =+IF(R93="","",R93) -> 602270760000 | V93: =+IF(F93<>"",(_xlfn.XLOOKUP(C93,UVR[Fecha (dd/mm/aaaa)],UVR[Pesos colombianos por UVR],"",0,1)),"") -> 393.862 | W93: =IF(C93="","",IF(CONCATENATE(DAY(C93),"/",MONTH(C93),"/",2000)-CONCATENATE(DAY(J93),"/",MONTH(J93),"/",2000)<0,K93%*ABS(S93),0)) -> 69615000000 | X93: =IF(S93<0,-W93,W93) -> 69615000000 | AB93: =IF(C93="","",ROUND(V93*(1+'Inflación observada '!$B$390%)^(("31-12-2025"-C93)/365),3)) -> 400.395 | AD93: =IF(C93="","",IF(G93="UVR",Q93*AB93-S93,0)) -> 0 | AE93: =IF(C93="","",P93/+(O93+P93)) -> 0.23283563 | AF93: =IF(C93="","",AE93*Q93*K93%) -> 1.6208853e+10 | AG93: =(Tabla6[[#This Row],[Fecha Vto]]-TODAY())/365 -> 14.972603 | AJ93: =IF(C93="","",IF(G93="UVR",Q93*AI93-S93,0)) -> 0
A94: =IF(C94="","",YEAR(C94)) -> 2025 | B94: 634 | C94: 45905 | D94: Tesorería | E94: Títulos Recogidos por la Nación | F94: TFIT11090233 | G94: =+_xlfn.XLOOKUP(F94,Emisiones[Mnemotécnico SEN],Emisiones[Moneda],"",0,1) -> COP | J94: =+_xlfn.XLOOKUP(F94,Emisiones[Mnemotécnico SEN],Emisiones[Fecha Vencim.],"",0,1) -> 48619 | K94: =+_xlfn.XLOOKUP(F94,Emisiones[Mnemotécnico SEN],Emisiones[Tasa de Interés],"",0,1) -> 13.25 | L94: 11.771 | M94: 114.438 | N94: =IF(C94="","",PRICE(C94,J94,K94%,L94%,100,1,3)) -> 106.88744 | O94: =IF(C94="","",M94-N94) -> 7.5505593 | P94: =IF(C94="","",100*K94%-O94) -> 5.6994407 | Q94: =IF(C94="","",IF(G94="UVR",S94/V94,S94)) -> -1304000000000 | R94: =IF(C94="","",IF('Canjes desagregado'!$G94="UVR",'Canjes desagregado'!$V94*Q94*M94%,Q94*M94%)) -> -1492271520000 | S94: -1304000000000 | T94: =IFERROR(IF(RIGHT(F94,2)=RIGHT(YEAR(J94),2),1,0),"") -> 1 | U94: =+IF(R94="","",R94) -> -1492271520000 | V94: =+IF(F94<>"",(_xlfn.XLOOKUP(C94,UVR[Fecha (dd/mm/aaaa)],UVR[Pesos colombianos por UVR],"",0,1)),"") -> 393.8975 | W94: =IF(C94="","",IF(CONCATENATE(DAY(C94),"/",MONTH(C94),"/",2000)-CONCATENATE(DAY(J94),"/",MONTH(J94),"/",2000)<0,K94%*ABS(S94),0)) -> 0 | X94: =IF(S94<0,-W94,W94) -> 0 | AB94: =IF(C94="","",ROUND(V94*(1+'Inflación observada '!$B$390%)^(("31-12-2025"-C94)/365),3)) -> 400.375 | AD94: =IF(C94="","",IF(G94="UVR",Q94*AB94-S94,0)) -> 0 | AE94: =IF(C94="","",P94/+(O94+P94)) -> 0.43014647 | AF94: =IF(C94="","",AE94*Q94*K94%) -> -7.4320707e+10 | AG94: =(Tabla6[[#This Row],[Fecha Vto]]-TODAY())/365 -> 7.1671233 | AJ94: =IF(C94="","",IF(G94="UVR",Q94*AI94-S94,0)) -> 0
A95: =IF(C95="","",YEAR(C95)) -> 2025 | B95: 634 | C95: 45905 | D95: Tesorería | E95: Títulos Entregados por la Nación | F95: TFIT16281140 | G95: =+_xlfn.XLOOKUP(F95,Emisiones[Mnemotécnico SEN],Emisiones[Moneda],"",0,1) -> COP | J95: =+_xlfn.XLOOKUP(F95,Emisiones[Mnemotécnico SEN],Emisiones[Fecha Vencim.],"",0,1) -> 51468 | K95: =+_xlfn.XLOOKUP(F95,Emisiones[Mnemotécnico SEN],Emisiones[Tasa de Interés],"",0,1) -> 12.75 | L95: 12.705 | M95: 109.976 | N95: =IF(C95="","",PRICE(C95,J95,K95%,L95%,100,1,3)) -> 100.16038 | O95: =IF(C95="","",M95-N95) -> 9.815621 | P95: =IF(C95="","",100*K95%-O95) -> 2.934379 | Q95: =IF(C95="","",IF(G95="UVR",S95/V95,S95)) -> 1304000000000 | R95: =IF(C95="","",IF('Canjes desagregado'!$G95="UVR",'Canjes desagregado'!$V95*Q95*M95%,Q95*M95%)) -> 1434087040000 | S95: 1304000000000 | T95: =IFERROR(IF(RIGHT(F95,2)=RIGHT(YEAR(J95),2),1,0),"") -> 1 | U95: =+IF(R95="","",R95) -> 1434087040000 | V95: =+IF(F95<>"",(_xlfn.XLOOKUP(C95,UVR[Fecha (dd/mm/aaaa)],UVR[Pesos colombianos por UVR],"",0,1)),"") -> 393.8975 | W95: =IF(C95="","",IF(CONCATENATE(DAY(C95),"/",MONTH(C95),"/",2000)-CONCATENATE(DAY(J95),"/",MONTH(J95),"/",2000)<0,K95%*ABS(S95),0)) -> 166260000000 | X95: =IF(S95<0,-W95,W95) -> 166260000000 | AB95: =IF(C95="","",ROUND(V95*(1+'Inflación observada '!$B$390%)^(("31-12-2025"-C95)/365),3)) -> 400.375 | AD95: =IF(C95="","",IF(G95="UVR",Q95*AB95-S95,0)) -> 0 | AE95: =IF(C95="","",P95/+(O95+P95)) -> 0.23014737 | AF95: =IF(C95="","",AE95*Q95*K95%) -> 3.8264302e+10 | AG95: =(Tabla6[[#This Row],[Fecha Vto]]-TODAY())/365 -> 14.972603 | AJ95: =IF(C95="","",IF(G95="UVR",Q95*AI95-S95,0)) -> 0
A96: =IF(C96="","",YEAR(C96)) -> 2025 | B96: 635 | C96: 45908 | D96: Tesorería | E96: Títulos Recogidos por la Nación | F96: TFIT11090233 | G96: =+_xlfn.XLOOKUP(F96,Emisiones[Mnemotécnico SEN],Emisiones[Moneda],"",0,1) -> COP | J96: =+_xlfn.XLOOKUP(F96,Emisiones[Mnemotécnico SEN],Emisiones[Fecha Vencim.],"",0,1) -> 48619 | K96: =+_xlfn.XLOOKUP(F96,Emisiones[Mnemotécnico SEN],Emisiones[Tasa de Interés],"",0,1) -> 13.25 | L96: 12.722 | M96: 109.91 | N96: =IF(C96="","",PRICE(C96,J96,K96%,L96%,100,1,3)) -> 102.24986 | O96: =IF(C96="","",M96-N96) -> 7.6601363 | P96: =IF(C96="","",100*K96%-O96) -> 5.5898637 | Q96: =IF(C96="","",IF(G96="UVR",S96/V96,S96)) -> -494000000000 | R96: =IF(C96="","",IF('Canjes desagregado'!$G96="UVR",'Canjes desagregado'!$V96*Q96*M96%,Q96*M96%)) -> -542955400000 | S96: -494000000000 | T96: =IFERROR(IF(RIGHT(F96,2)=RIGHT(YEAR(J96),2),1,0),"") -> 1 | U96: =+IF(R96="","",R96) -> -542955400000 | V96: =+IF(F96<>"",(_xlfn.XLOOKUP(C96,UVR[Fecha (dd/mm/aaaa)],UVR[Pesos colombianos por UVR],"",0,1)),"") -> 394.0041 | W96: =IF(C96="","",IF(CONCATENATE(DAY(C96),"/",MONTH(C96),"/",2000)-CONCATENATE(DAY(J96),"/",MONTH(J96),"/",2000)<0,K96%*ABS(S96),0)) -> 0 | X96: =IF(S96<0,-W96,W96) -> 0 | AB96: =IF(C96="","",ROUND(V96*(1+'Inflación observada '!$B$390%)^(("31-12-2025"-C96)/365),3)) -> 400.316 | AD96: =IF(C96="","",IF(G96="UVR",Q96*AB96-S96,0)) -> 0 | AE96: =IF(C96="","",P96/+(O96+P96)) -> 0.4218765 | AF96: =IF(C96="","",AE96*Q96*K96%) -> -2.7613927e+10 | AG96: =(Tabla6[[#This Row],[Fecha Vto]]-TODAY())/365 -> 7.1671233 | AJ96: =IF(C96="","",IF(G96="UVR",Q96*AI96-S96,0)) -> 0
A97: =IF(C97="","",YEAR(C97)) -> 2025 | B97: 635 | C97: 45908 | D97: Tesorería | E97: Títulos Entregados por la Nación | F97: TFIT16090736 | G97: =+_xlfn.XLOOKUP(F97,Emisiones[Mnemotécnico SEN],Emisiones[Moneda],"",0,1) -> COP | J97: =+_xlfn.XLOOKUP(F97,Emisiones[Mnemotécnico SEN],Emisiones[Fecha Vencim.],"",0,1) -> 49865 | K97: =+_xlfn.XLOOKUP(F97,Emisiones[Mnemotécnico SEN],Emisiones[Tasa de Interés],"",0,1) -> 6.25 | L97: 11.593 | M97: 68.955 | N97: =IF(C97="","",PRICE(C97,J97,K97%,L97%,100,1,3)) -> 67.910442 | O97: =IF(C97="","",M97-N97) -> 1.0445584 | P97: =IF(C97="","",100*K97%-O97) -> 5.2054416 | Q97: =IF(C97="","",IF(G97="UVR",S97/V97,S97)) -> 55000000000 | R97: =IF(C97="","",IF('Canjes desagregado'!$G97="UVR",'Canjes desagregado'!$V97*Q97*M97%,Q97*M97%)) -> 37925250000 | S97: 55000000000 | T97: =IFERROR(IF(RIGHT(F97,2)=RIGHT(YEAR(J97),2),1,0),"") -> 1 | U97: =+IF(R97="","",R97) -> 37925250000 | V97: =+IF(F97<>"",(_xlfn.XLOOKUP(C97,UVR[Fecha (dd/mm/aaaa)],UVR[Pesos colombianos por UVR],"",0,1)),"") -> 394.0041 | W97: =IF(C97="","",IF(CONCATENATE(DAY(C97),"/",MONTH(C97),"/",2000)-CONCATENATE(DAY(J97),"/",MONTH(J97),"/",2000)<0,K97%*ABS(S97),0)) -> 0 | X97: =IF(S97<0,-W97,W97) -> 0 | AB97: =IF(C97="","",ROUND(V97*(1+'Inflación observada '!$B$390%)^(("31-12-2025"-C97)/365),3)) -> 400.316 | AD97: =IF(C97="","",IF(G97="UVR",Q97*AB97-S97,0)) -> 0 | AE97: =IF(C97="","",P97/+(O97+P97)) -> 0.83287065 | AF97: =IF(C97="","",AE97*Q97*K97%) -> 2.8629929e+09 | AG97: =(Tabla6[[#This Row],[Fecha Vto]]-TODAY())/365 -> 10.580822 | AJ97: =IF(C97="","",IF(G97="UVR",Q97*AI97-S97,0)) -> 0
... A101: =IF(C101="","",YEAR(C101)) -> 2025 | B101: 635 | C101: 45908 | D101: Tesorería | E101: Títulos Entregados por la Nación | F101: TFIT31261050 | G101: =+_xlfn.XLOOKUP(F101,Emisiones[Mnemotécnico SEN],Emisiones[Moneda],"",0,1) -> COP | J101: =+_xlfn.XLOOKUP(F101,Emisiones[Mnemotécnico SEN],Emisiones[Fecha Vencim.],"",0,1) -> 55087 | K101: =+_xlfn.XLOOKUP(F101,Emisiones[Mnemotécnico SEN],Emisiones[Tasa de Interés],"",0,1) -> 7.25 | L101: 11.999 | M101: 68.965 | N101: =IF(C101="","",PRICE(C101,J101,K101%,L101%,100,1,3)) -> 62.668339 | O101: =IF(C101="","",M101-N101) -> 6.296661 | P101: =IF(C101="","",100*K101%-O101) -> 0.95333903 | Q101: =IF(C101="","",IF(G101="UVR",S101/V101,S101)) -> 159000000000 | R101: =IF(C101="","",IF('Canjes desagregado'!$G101="UVR",'Canjes desagregado'!$V101*Q101*M101%,Q101*M101%)) -> 109654350000 | S101: 159000000000 | T101: =IFERROR(IF(RIGHT(F101,2)=RIGHT(YEAR(J101),2),1,0),"") -> 1 | U101: =+IF(R101="","",R101) -> 109654350000 | V101: =+IF(F101<>"",(_xlfn.XLOOKUP(C101,UVR[Fecha (dd/mm/aaaa)],UVR[Pesos colombianos por UVR],"",0,1)),"") -> 394.0041 | W101: =IF(C101="","",IF(CONCATENATE(DAY(C101),"/",MONTH(C101),"/",2000)-CONCATENATE(DAY(J101),"/",MONTH(J101),"/",2000)<0,K101%*ABS(S101),0)) -> 11527500000 | X101: =IF(S101<0,-W101,W101) -> 11527500000 | AB101: =IF(C101="","",ROUND(V101*(1+'Inflación observada '!$B$390%)^(("31-12-2025"-C101)/365),3)) -> 400.316 | AD101: =IF(C101="","",IF(G101="UVR",Q101*AB101-S101,0)) -> 0 | AE101: =IF(C101="","",P101/+(O101+P101)) -> 0.13149504 | AF101: =IF(C101="","",AE101*Q101*K101%) -> 1.5158091e+09 | AG101: =(Tabla6[[#This Row],[Fecha Vto]]-TODAY())/365 -> 24.887671 | AJ101: =IF(C101="","",IF(G101="UVR",Q101*AI101-S101,0)) -> 0
A102: 2025 | B102: 636 | C102: 45951 | D102: Tesorería | E102: Títulos Recogidos por la Nación | G102: COP | J102: 46084 | L102: 9.119 | M102: 96.87 | N102: =IF(C102="","",PRICE(C102,J102,K102%,L102%,100,1,3)) -> 96.784046 | O102: =IF(C102="","",M102-N102) -> 0.085953553 | P102: =IF(C102="","",100*K102%-O102) -> -0.085953553 | Q102: =IF(C102="","",IF(G102="UVR",S102/V102,S102)) -> -313318900000 | R102: =IF(C102="","",IF('Canjes desagregado'!$G102="UVR",'Canjes desagregado'!$V102*Q102*M102%,Q102*M102%)) -> -303512018430 | S102: -313318900000 | T102: =IFERROR(IF(RIGHT(F102,2)=RIGHT(YEAR(J102),2),1,0),"") -> 0 | U102: =+IF(R102="","",R102) -> -303512018430 | V102: =+IF(F102<>"",(_xlfn.XLOOKUP(C102,UVR[Fecha (dd/mm/aaaa)],UVR[Pesos colombianos por UVR],"",0,1)),"") | W102: =IF(C102="","",IF(CONCATENATE(DAY(C102),"/",MONTH(C102),"/",2000)-CONCATENATE(DAY(J102),"/",MONTH(J102),"/",2000)<0,K102%*ABS(S102),0)) -> 0 | X102: =IF(S102<0,-W102,W102) -> 0 | AB102: =IF(C102="","",ROUND(V102*(1+'Inflación observada '!$B$390%)^(("31-12-2025"-C102)/365),3)) -> #VALUE! | AD102: =IF(C102="","",IF(G102="UVR",Q102*AB102-S102,0)) -> 0 | AE102: =IF(C102="","",P102/+(O102+P102)) -> #DIV/0! | AF102: =IF(C102="","",AE102*Q102*K102%) -> #DIV/0! | AG102: =(Tabla6[[#This Row],[Fecha Vto]]-TODAY())/365 -> 0.22191781 | AJ102: =IF(C102="","",IF(G102="UVR",Q102*AI102-S102,0)) -> 0
A103: 2025 | B103: 636 | C103: 45951 | D103: Tesorería | E103: Títulos Entregados por la Nación | F103: TFIT16281140 | G103: COP | J103: =+_xlfn.XLOOKUP(F103,Emisiones[Mnemotécnico SEN],Emisiones[Fecha Vencim.],"",0,1) -> 51468 | K103: =+_xlfn.XLOOKUP(F103,Emisiones[Mnemotécnico SEN],Emisiones[Tasa de Interés],"",0,1) -> 12.75 | L103: 11.998 | M103: 116.49 | N103: =IF(C103="","",PRICE(C103,J103,K103%,L103%,100,1,3)) -> 105.06737 | O103: =IF(C103="","",M103-N103) -> 11.422626 | P103: =IF(C103="","",100*K103%-O103) -> 1.3273744 | Q103: =IF(C103="","",IF(G103="UVR",S103/V103,S103)) -> 15000000000 | R103: =IF(C103="","",IF('Canjes desagregado'!$G103="UVR",'Canjes desagregado'!$V103*Q103*M103%,Q103*M103%)) -> 17473500000 | S103: 15000000000 | T103: =IFERROR(IF(RIGHT(F103,2)=RIGHT(YEAR(J103),2),1,0),"") -> 1 | U103: =+IF(R103="","",R103) -> 17473500000 | V103: =+IF(F103<>"",(_xlfn.XLOOKUP(C103,UVR[Fecha (dd/mm/aaaa)],UVR[Pesos colombianos por UVR],"",0,1)),"") -> 395.2463 | W103: =IF(C103="","",IF(CONCATENATE(DAY(C103),"/",MONTH(C103),"/",2000)-CONCATENATE(DAY(J103),"/",MONTH(J103),"/",2000)<0,K103%*ABS(S103),0)) -> 1912500000 | X103: =IF(S103<0,-W103,W103) -> 1912500000 | AB103: =IF(C103="","",ROUND(V103*(1+'Inflación observada '!$B$390%)^(("31-12-2025"-C103)/365),3)) -> 399.178 | AD103: =IF(C103="","",IF(G103="UVR",Q103*AB103-S103,0)) -> 0 | AE103: =IF(C103="","",P103/+(O103+P103)) -> 0.1041078 | AF103: =IF(C103="","",AE103*Q103*K103%) -> 1.9910616e+08 | AG103: =(Tabla6[[#This Row],[Fecha Vto]]-TODAY())/365 -> 14.972603 | AJ103: =IF(C103="","",IF(G103="UVR",Q103*AI103-S103,0)) -> 0
A104: 2025 | B104: 636 | C104: 45951 | D104: Tesorería | E104: Títulos Entregados por la Nación | F104: TFIT23250746 | G104: COP | J104: =+_xlfn.XLOOKUP(F104,Emisiones[Mnemotécnico SEN],Emisiones[Fecha Vencim.],"",0,1) -> 53533 | K104: =+_xlfn.XLOOKUP(F104,Emisiones[Mnemotécnico SEN],Emisiones[Tasa de Interés],"",0,1) -> 11.5 | L104: 12.081 | M104: 98.295 | N104: =IF(C104="","",PRICE(C104,J104,K104%,L104%,100,1,3)) -> 95.522664 | O104: =IF(C104="","",M104-N104) -> 2.7723363 | P104: =IF(C104="","",100*K104%-O104) -> 8.7276637 | Q104: =IF(C104="","",IF(G104="UVR",S104/V104,S104)) -> 291000000000 | R104: =IF(C104="","",IF('Canjes desagregado'!$G104="UVR",'Canjes desagregado'!$V104*Q104*M104%,Q104*M104%)) -> 286038450000 | S104: 291000000000 | T104: =IFERROR(IF(RIGHT(F104,2)=RIGHT(YEAR(J104),2),1,0),"") -> 1 | U104: =+IF(R104="","",R104) -> 286038450000 | V104: =+IF(F104<>"",(_xlfn.XLOOKUP(C104,UVR[Fecha (dd/mm/aaaa)],UVR[Pesos colombianos por UVR],"",0,1)),"") -> 395.2463 | W104: =IF(C104="","",IF(CONCATENATE(DAY(C104),"/",MONTH(C104),"/",2000)-CONCATENATE(DAY(J104),"/",MONTH(J104),"/",2000)<0,K104%*ABS(S104),0)) -> 0 | X104: =IF(S104<0,-W104,W104) -> 0 | AB104: =IF(C104="","",ROUND(V104*(1+'Inflación observada '!$B$390%)^(("31-12-2025"-C104)/365),3)) -> 399.178 | AD104: =IF(C104="","",IF(G104="UVR",Q104*AB104-S104,0)) -> 0 | AE104: =IF(C104="","",P104/+(O104+P104)) -> 0.75892727 | AF104: =IF(C104="","",AE104*Q104*K104%) -> 2.5397501e+10 | AG104: =(Tabla6[[#This Row],[Fecha Vto]]-TODAY())/365 -> 20.630137 | AJ104: =IF(C104="","",IF(G104="UVR",Q104*AI104-S104,0)) -> 0
A105: 2025 | B105: 637 | C105: 45952 | D105: Tesorería | E105: Títulos Recogidos por la Nación | G105: COP | J105: 46175 | K105: 0 | L105: 9.1 | M105: 94.818 | N105: =IF(C105="","",PRICE(C105,J105,K105%,L105%,100,1,3)) -> 94.733099 | O105: =IF(C105="","",M105-N105) -> 0.084900774 | P105: =IF(C105="","",100*K105%-O105) -> -0.084900774 | Q105: =IF(C105="","",IF(G105="UVR",S105/V105,S105)) -> -397613400000 | R105: =IF(C105="","",IF('Canjes desagregado'!$G105="UVR",'Canjes desagregado'!$V105*Q105*M105%,Q105*M105%)) -> -377009073612 | S105: -397613400000 | T105: =IFERROR(IF(RIGHT(F105,2)=RIGHT(YEAR(J105),2),1,0),"") -> 0 | U105: =+IF(R105="","",R105) -> -377009073612 | V105: =+IF(F105<>"",(_xlfn.XLOOKUP(C105,UVR[Fecha (dd/mm/aaaa)],UVR[Pesos colombianos por UVR],"",0,1)),"") | W105: =IF(C105="","",IF(CONCATENATE(DAY(C105),"/",MONTH(C105),"/",2000)-CONCATENATE(DAY(J105),"/",MONTH(J105),"/",2000)<0,K105%*ABS(S105),0)) -> 0 | X105: =IF(S105<0,-W105,W105) -> 0 | AB105: =IF(C105="","",ROUND(V105*(1+'Inflación observada '!$B$390%)^(("31-12-2025"-C105)/365),3)) -> #VALUE! | AD105: =IF(C105="","",IF(G105="UVR",Q105*AB105-S105,0)) -> 0 | AE105: =IF(C105="","",P105/+(O105+P105)) -> #DIV/0! | AF105: =IF(C105="","",AE105*Q105*K105%) -> #DIV/0! | AG105: =(Tabla6[[#This Row],[Fecha Vto]]-TODAY())/365 -> 0.47123288 | AJ105: =IF(C105="","",IF(G105="UVR",Q105*AI105-S105,0)) -> 0
A106: 2025 | B106: 637 | C106: 45952 | D106: Tesorería | E106: Títulos Entregados por la Nación | F106: COL17CT04084 | G106: =+_xlfn.XLOOKUP(F106,Emisiones[Mnemotécnico SEN],Emisiones[Moneda],"",0,1) -> COP | J106: =+_xlfn.XLOOKUP(F106,Emisiones[Mnemotécnico SEN],Emisiones[Fecha Vencim.],"",0,1) -> 49313 | K106: =+_xlfn.XLOOKUP(F106,Emisiones[Mnemotécnico SEN],Emisiones[Tasa de Interés],"",0,1) -> 11.75 | L106: 11.93 | M106: 107.619 | N106: =IF(C106="","",PRICE(C106,J106,K106%,L106%,100,1,3)) -> 98.917796 | O106: =IF(C106="","",M106-N106) -> 8.7012042 | P106: =IF(C106="","",100*K106%-O106) -> 3.0487958 | Q106: =IF(C106="","",IF(G106="UVR",S106/V106,S106)) -> 197000000000 | R106: =IF(C106="","",IF('Canjes desagregado'!$G106="UVR",'Canjes desagregado'!$V106*Q106*M106%,Q106*M106%)) -> 212009430000 | S106: 197000000000 | T106: {=SIERROR(IF(RIGHT(F106,2)=RIGHT(YEAR(J106),2),1,0),"")} -> #NAME? | U106: =+IF(R106="","",R106) -> 212009430000 | V106: =+IF(F106<>"",(_xlfn.XLOOKUP(C106,UVR[Fecha (dd/mm/aaaa)],UVR[Pesos colombianos por UVR],"",0,1)),"") -> 395.2871 | W106: =IF(C106="","",IF(CONCATENATE(DAY(C106),"/",MONTH(C106),"/",2000)-CONCATENATE(DAY(J106),"/",MONTH(J106),"/",2000)<0,K106%*ABS(S106),0)) -> 0 | X106: =IF(S106<0,-W106,W106) -> 0 | AB106: =IF(C106="","",ROUND(V106*(1+'Inflación observada '!$B$390%)^(("31-12-2025"-C106)/365),3)) -> 399.163 | AD106: =IF(C106="","",IF(G106="UVR",Q106*AB106-S106,0)) -> 0 | AE106: =IF(C106="","",P106/+(O106+P106)) -> 0.25947199 | AF106: =IF(C106="","",AE106*Q106*K106%) -> 6.0061278e+09 | AG106: =(Tabla6[[#This Row],[Fecha Vto]]-TODAY())/365 -> 9.0684932 | AJ106: =IF(C106="","",IF(G106="UVR",Q106*AI106-S106,0)) -> 0
A107: 2025 | B107: 637 | C107: 45952 | D107: Tesorería | E107: Títulos Entregados por la Nación | F107: TFIT16281140 | G107: =+_xlfn.XLOOKUP(F107,Emisiones[Mnemotécnico SEN],Emisiones[Moneda],"",0,1) -> COP | J107: =+_xlfn.XLOOKUP(F107,Emisiones[Mnemotécnico SEN],Emisiones[Fecha Vencim.],"",0,1) -> 51468 | K107: =+_xlfn.XLOOKUP(F107,Emisiones[Mnemotécnico SEN],Emisiones[Tasa de Interés],"",0,1) -> 12.75 | L107: 12.12 | M107: 115.664 | N107: =IF(C107="","",PRICE(C107,J107,K107%,L107%,100,1,3)) -> 104.20683 | O107: =IF(C107="","",M107-N107) -> 11.457169 | P107: =IF(C107="","",100*K107%-O107) -> 1.2928306 | Q107: =IF(C107="","",IF(G107="UVR",S107/V107,S107)) -> 35000000000 | R107: =IF(C107="","",IF('Canjes desagregado'!$G107="UVR",'Canjes desagregado'!$V107*Q107*M107%,Q107*M107%)) -> 4.04824e+10 | S107: 35000000000 | T107: =IFERROR(IF(RIGHT(F107,2)=RIGHT(YEAR(J107),2),1,0),"") -> 1 | U107: =+IF(R107="","",R107) -> 4.04824e+10 | V107: =+IF(F107<>"",(_xlfn.XLOOKUP(C107,UVR[Fecha (dd/mm/aaaa)],UVR[Pesos colombianos por UVR],"",0,1)),"") -> 395.2871 | W107: =IF(C107="","",IF(CONCATENATE(DAY(C107),"/",MONTH(C107),"/",2000)-CONCATENATE(DAY(J107),"/",MONTH(J107),"/",2000)<0,K107%*ABS(S107),0)) -> 4462500000 | X107: =IF(S107<0,-W107,W107) -> 4462500000 | AB107: =IF(C107="","",ROUND(V107*(1+'Inflación observada '!$B$390%)^(("31-12-2025"-C107)/365),3)) -> 399.163 | AD107: =IF(C107="","",IF(G107="UVR",Q107*AB107-S107,0)) -> 0 | AE107: =IF(C107="","",P107/+(O107+P107)) -> 0.10139848 | AF107: =IF(C107="","",AE107*Q107*K107%) -> 4.524907e+08 | AG107: =(Tabla6[[#This Row],[Fecha Vto]]-TODAY())/365 -> 14.972603 | AJ107: =IF(C107="","",IF(G107="UVR",Q107*AI107-S107,0)) -> 0
A108: 2025 | B108: 637 | C108: 45952 | D108: Tesorería | E108: Títulos Entregados por la Nación | F108: TFIT23250746 | G108: =+_xlfn.XLOOKUP(F108,Emisiones[Mnemotécnico SEN],Emisiones[Moneda],"",0,1) -> COP | J108: =+_xlfn.XLOOKUP(F108,Emisiones[Mnemotécnico SEN],Emisiones[Fecha Vencim.],"",0,1) -> 53533 | K108: =+_xlfn.XLOOKUP(F108,Emisiones[Mnemotécnico SEN],Emisiones[Tasa de Interés],"",0,1) -> 11.5 | L108: 12.12 | M108: 98.045 | N108: =IF(C108="","",PRICE(C108,J108,K108%,L108%,100,1,3)) -> 95.240469 | O108: =IF(C108="","",M108-N108) -> 2.8045306 | P108: =IF(C108="","",100*K108%-O108) -> 8.6954694 | Q108: =IF(C108="","",IF(G108="UVR",S108/V108,S108)) -> 127000000000 | R108: =IF(C108="","",IF('Canjes desagregado'!$G108="UVR",'Canjes desagregado'!$V108*Q108*M108%,Q108*M108%)) -> 124517150000 | S108: 127000000000 | T108: =IFERROR(IF(RIGHT(F108,2)=RIGHT(YEAR(J108),2),1,0),"") -> 1 | U108: =+IF(R108="","",R108) -> 124517150000 | V108: =+IF(F108<>"",(_xlfn.XLOOKUP(C108,UVR[Fecha (dd/mm/aaaa)],UVR[Pesos colombianos por UVR],"",0,1)),"") -> 395.2871 | W108: =IF(C108="","",IF(CONCATENATE(DAY(C108),"/",MONTH(C108),"/",2000)-CONCATENATE(DAY(J108),"/",MONTH(J108),"/",2000)<0,K108%*ABS(S108),0)) -> 0 | X108: =IF(S108<0,-W108,W108) -> 0 | AB108: =IF(C108="","",ROUND(V108*(1+'Inflación observada '!$B$390%)^(("31-12-2025"-C108)/365),3)) -> 399.163 | AD108: =IF(C108="","",IF(G108="UVR",Q108*AB108-S108,0)) -> 0 | AE108: =IF(C108="","",P108/+(O108+P108)) -> 0.75612777 | AF108: =IF(C108="","",AE108*Q108*K108%) -> 1.1043246e+10 | AG108: =(Tabla6[[#This Row],[Fecha Vto]]-TODAY())/365 -> 20.630137 | AJ108: =IF(C108="","",IF(G108="UVR",Q108*AI108-S108,0)) -> 0
A109: 2025 | B109: 638 | C109: 45953 | D109: Tesorería | E109: Títulos Recogidos por la Nación | G109: COP | J109: 46084 | L109: 9.107 | M109: 96.92 | N109: =IF(C109="","",PRICE(C109,J109,K109%,L109%,100,1,3)) -> 96.834912 | O109: =IF(C109="","",M109-N109) -> 0.085087581 | P109: =IF(C109="","",100*K109%-O109) -> -0.085087581 | Q109: =IF(C109="","",IF(G109="UVR",S109/V109,S109)) -> -120077500000 | R109: =IF(C109="","",IF('Canjes desagregado'!$G109="UVR",'Canjes desagregado'!$V109*Q109*M109%,Q109*M109%)) -> -116379113000 | S109: -120077500000 | T109: =IFERROR(IF(RIGHT(F109,2)=RIGHT(YEAR(J109),2),1,0),"") -> 0 | U109: =+IF(R109="","",R109) -> -116379113000 | V109: =+IF(F109<>"",(_xlfn.XLOOKUP(C109,UVR[Fecha (dd/mm/aaaa)],UVR[Pesos colombianos por UVR],"",0,1)),"") | W109: =IF(C109="","",IF(CONCATENATE(DAY(C109),"/",MONTH(C109),"/",2000)-CONCATENATE(DAY(J109),"/",MONTH(J109),"/",2000)<0,K109%*ABS(S109),0)) -> 0 | X109: =IF(S109<0,-W109,W109) -> 0 | AB109: =IF(C109="","",ROUND(V109*(1+'Inflación observada '!$B$390%)^(("31-12-2025"-C109)/365),3)) -> #VALUE! | AD109: =IF(C109="","",IF(G109="UVR",Q109*AB109-S109,0)) -> 0 | AE109: =IF(C109="","",P109/+(O109+P109)) -> #DIV/0! | AF109: =IF(C109="","",AE109*Q109*K109%) -> #DIV/0! | AG109: =(Tabla6[[#This Row],[Fecha Vto]]-TODAY())/365 -> 0.22191781 | AJ109: =IF(C109="","",IF(G109="UVR",Q109*AI109-S109,0)) -> 0
A110: 2025 | B110: 638 | C110: 45953 | D110: Tesorería | E110: Títulos Recogidos por la Nación | G110: COP | J110: 46175 | L110: 9.1 | M110: 94.841 | N110: =IF(C110="","",PRICE(C110,J110,K110%,L110%,100,1,3)) -> 94.755479 | O110: =IF(C110="","",M110-N110) -> 0.085521056 | P110: =IF(C110="","",100*K110%-O110) -> -0.085521056 | Q110: =IF(C110="","",IF(G110="UVR",S110/V110,S110)) -> -105250000000 | R110: =IF(C110="","",IF('Canjes desagregado'!$G110="UVR",'Canjes desagregado'!$V110*Q110*M110%,Q110*M110%)) -> -99820152500 | S110: -105250000000 | T110: =IFERROR(IF(RIGHT(F110,2)=RIGHT(YEAR(J110),2),1,0),"") -> 0 | U110: =+IF(R110="","",R110) -> -99820152500 | V110: =+IF(F110<>"",(_xlfn.XLOOKUP(C110,UVR[Fecha (dd/mm/aaaa)],UVR[Pesos colombianos por UVR],"",0,1)),"") | W110: =IF(C110="","",IF(CONCATENATE(DAY(C110),"/",MONTH(C110),"/",2000)-CONCATENATE(DAY(J110),"/",MONTH(J110),"/",2000)<0,K110%*ABS(S110),0)) -> 0 | X110: =IF(S110<0,-W110,W110) -> 0 | AB110: =IF(C110="","",ROUND(V110*(1+'Inflación observada '!$B$390%)^(("31-12-2025"-C110)/365),3)) -> #VALUE! | AD110: =IF(C110="","",IF(G110="UVR",Q110*AB110-S110,0)) -> 0 | AE110: =IF(C110="","",P110/+(O110+P110)) -> #DIV/0! | AF110: =IF(C110="","",AE110*Q110*K110%) -> #DIV/0! | AG110: =(Tabla6[[#This Row],[Fecha Vto]]-TODAY())/365 -> 0.47123288 | AJ110: =IF(C110="","",IF(G110="UVR",Q110*AI110-S110,0)) -> 0
A111: 2025 | B111: 638 | C111: 45953 | D111: Tesorería | E111: Títulos Entregados por la Nación | F111: COL17CT04084 | G111: =+_xlfn.XLOOKUP(F111,Emisiones[Mnemotécnico SEN],Emisiones[Moneda],"",0,1) -> COP | J111: =+_xlfn.XLOOKUP(F111,Emisiones[Mnemotécnico SEN],Emisiones[Fecha Vencim.],"",0,1) -> 49313 | K111: =+_xlfn.XLOOKUP(F111,Emisiones[Mnemotécnico SEN],Emisiones[Tasa de Interés],"",0,1) -> 11.75 | L111: 11.973 | M111: 107.421 | N111: =IF(C111="","",PRICE(C111,J111,K111%,L111%,100,1,3)) -> 98.688041 | O111: =IF(C111="","",M111-N111) -> 8.7329592 | P111: =IF(C111="","",100*K111%-O111) -> 3.0170408 | Q111: =IF(C111="","",IF(G111="UVR",S111/V111,S111)) -> 107500000000 | R111: =IF(C111="","",IF('Canjes desagregado'!$G111="UVR",'Canjes desagregado'!$V111*Q111*M111%,Q111*M111%)) -> 1.1547758e+11 | S111: 107500000000 | T111: =IFERROR(IF(RIGHT(F111,2)=RIGHT(YEAR(J111),2),1,0),"") -> 0 | U111: =+IF(R111="","",R111) -> 1.1547758e+11 | V111: =+IF(F111<>"",(_xlfn.XLOOKUP(C111,UVR[Fecha (dd/mm/aaaa)],UVR[Pesos colombianos por UVR],"",0,1)),"") -> 395.3278 | W111: =IF(C111="","",IF(CONCATENATE(DAY(C111),"/",MONTH(C111),"/",2000)-CONCATENATE(DAY(J111),"/",MONTH(J111),"/",2000)<0,K111%*ABS(S111),0)) -> 0 | X111: =IF(S111<0,-W111,W111) -> 0 | AB111: =IF(C111="","",ROUND(V111*(1+'Inflación observada '!$B$390%)^(("31-12-2025"-C111)/365),3)) -> 399.149 | AD111: =IF(C111="","",IF(G111="UVR",Q111*AB111-S111,0)) -> 0 | AE111: =IF(C111="","",P111/+(O111+P111)) -> 0.25676943 | AF111: =IF(C111="","",AE111*Q111*K111%) -> 3.2433188e+09 | AG111: =(Tabla6[[#This Row],[Fecha Vto]]-TODAY())/365 -> 9.0684932 | AJ111: =IF(C111="","",IF(G111="UVR",Q111*AI111-S111,0)) -> 0
A112: 2025 | B112: 638 | C112: 45953 | D112: Tesorería | E112: Títulos Entregados por la Nación | F112: TFIT23250746 | G112: =+_xlfn.XLOOKUP(F112,Emisiones[Mnemotécnico SEN],Emisiones[Moneda],"",0,1) -> COP | J112: =+_xlfn.XLOOKUP(F112,Emisiones[Mnemotécnico SEN],Emisiones[Fecha Vencim.],"",0,1) -> 53533 | K112: =+_xlfn.XLOOKUP(F112,Emisiones[Mnemotécnico SEN],Emisiones[Tasa de Interés],"",0,1) -> 11.5 | L112: 12.16 | M112: 97.788 | N112: =IF(C112="","",PRICE(C112,J112,K112%,L112%,100,1,3)) -> 94.952532 | O112: =IF(C112="","",M112-N112) -> 2.8354677 | P112: =IF(C112="","",100*K112%-O112) -> 8.6645323 | Q112: =IF(C112="","",IF(G112="UVR",S112/V112,S112)) -> 103000000000 | R112: =IF(C112="","",IF('Canjes desagregado'!$G112="UVR",'Canjes desagregado'!$V112*Q112*M112%,Q112*M112%)) -> 100721640000 | S112: 103000000000 | T112: =IFERROR(IF(RIGHT(F112,2)=RIGHT(YEAR(J112),2),1,0),"") -> 1 | U112: =+IF(R112="","",R112) -> 100721640000 | V112: =+IF(F112<>"",(_xlfn.XLOOKUP(C112,UVR[Fecha (dd/mm/aaaa)],UVR[Pesos colombianos por UVR],"",0,1)),"") -> 395.3278 | W112: =IF(C112="","",IF(CONCATENATE(DAY(C112),"/",MONTH(C112),"/",2000)-CONCATENATE(DAY(J112),"/",MONTH(J112),"/",2000)<0,K112%*ABS(S112),0)) -> 0 | X112: =IF(S112<0,-W112,W112) -> 0 | AB112: =IF(C112="","",ROUND(V112*(1+'Inflación observada '!$B$390%)^(("31-12-2025"-C112)/365),3)) -> 399.149 | AD112: =IF(C112="","",IF(G112="UVR",Q112*AB112-S112,0)) -> 0 | AE112: =IF(C112="","",P112/+(O112+P112)) -> 0.75343759 | AF112: =IF(C112="","",AE112*Q112*K112%) -> 8.9244683e+09 | AG112: =(Tabla6[[#This Row],[Fecha Vto]]-TODAY())/365 -> 20.630137 | AJ112: =IF(C112="","",IF(G112="UVR",Q112*AI112-S112,0)) -> 0
A113: =IF(C113="","",YEAR(C113)) -> 2025 | B113: 639 | C113: 45957 | D113: Tesorería | E113: Títulos Recogidos por la Nación | F113: COL17CT03987 | G113: =+_xlfn.XLOOKUP(F113,Emisiones[Mnemotécnico SEN],Emisiones[Moneda],"",0,1) -> COP | J113: =+_xlfn.XLOOKUP(F113,Emisiones[Mnemotécnico SEN],Emisiones[Fecha Vencim.],"",0,1) -> 46084 | K113: =+_xlfn.XLOOKUP(F113,Emisiones[Mnemotécnico SEN],Emisiones[Tasa de Interés],"",0,1) -> 0 | L113: 9.06 | M113: 97.027 | N113: =IF(C113="","",PRICE(C113,J113,K113%,L113%,100,1,3)) -> 96.943955 | O113: =IF(C113="","",M113-N113) -> 0.083045292 | P113: =IF(C113="","",100*K113%-O113) -> -0.083045292 | Q113: =IF(C113="","",IF(G113="UVR",S113/V113,S113)) -> -396635400000 | R113: =IF(C113="","",IF('Canjes desagregado'!$G113="UVR",'Canjes desagregado'!$V113*Q113*M113%,Q113*M113%)) -> -384843429558 | S113: -396635400000 | T113: =IFERROR(IF(RIGHT(F113,2)=RIGHT(YEAR(J113),2),1,0),"") -> 0 | U113: =+IF(R113="","",R113) -> -384843429558 | V113: =+IF(F113<>"",(_xlfn.XLOOKUP(C113,UVR[Fecha (dd/mm/aaaa)],UVR[Pesos colombianos por UVR],"",0,1)),"") -> 395.4908 | W113: =IF(C113="","",IF(CONCATENATE(DAY(C113),"/",MONTH(C113),"/",2000)-CONCATENATE(DAY(J113),"/",MONTH(J113),"/",2000)<0,K113%*ABS(S113),0)) -> 0 | X113: =IF(S113<0,-W113,W113) -> 0 | AB113: =IF(C113="","",ROUND(V113*(1+'Inflación observada '!$B$390%)^(("31-12-2025"-C113)/365),3)) -> 399.091 | AD113: =IF(C113="","",IF(G113="UVR",Q113*AB113-S113,0)) -> 0 | AE113: =IF(C113="","",P113/+(O113+P113)) -> #DIV/0! | AF113: =IF(C113="","",AE113*Q113*K113%) -> #DIV/0! | AG113: =(Tabla6[[#This Row],[Fecha Vto]]-TODAY())/365 -> 0.22191781 | AJ113: =IF(C113="","",IF(G113="UVR",Q113*AI113-S113,0)) -> 0
A114: =IF(C114="","",YEAR(C114)) -> 2025 | B114: 639 | C114: 45957 | D114: Tesorería | E114: Títulos Recogidos por la Nación | F114: COL17CT04027 | G114: =+_xlfn.XLOOKUP(F114,Emisiones[Mnemotécnico SEN],Emisiones[Moneda],"",0,1) -> COP | J114: =+_xlfn.XLOOKUP(F114,Emisiones[Mnemotécnico SEN],Emisiones[Fecha Vencim.],"",0,1) -> 46175 | K114: =+_xlfn.XLOOKUP(F114,Emisiones[Mnemotécnico SEN],Emisiones[Tasa de Interés],"",0,1) -> 0 | L114: 9.075 | M114: 94.944 | N114: =IF(C114="","",PRICE(C114,J114,K114%,L114%,100,1,3)) -> 94.858537 | O114: =IF(C114="","",M114-N114) -> 0.085462667 | P114: =IF(C114="","",100*K114%-O114) -> -0.085462667 | Q114: =IF(C114="","",IF(G114="UVR",S114/V114,S114)) -> -92300000000 | R114: =IF(C114="","",IF('Canjes desagregado'!$G114="UVR",'Canjes desagregado'!$V114*Q114*M114%,Q114*M114%)) -> -87633312000 | S114: -92300000000 | T114: =IFERROR(IF(RIGHT(F114,2)=RIGHT(YEAR(J114),2),1,0),"") -> 0 | U114: =+IF(R114="","",R114) -> -87633312000 | V114: =+IF(F114<>"",(_xlfn.XLOOKUP(C114,UVR[Fecha (dd/mm/aaaa)],UVR[Pesos colombianos por UVR],"",0,1)),"") -> 395.4908 | W114: =IF(C114="","",IF(CONCATENATE(DAY(C114),"/",MONTH(C114),"/",2000)-CONCATENATE(DAY(J114),"/",MONTH(J114),"/",2000)<0,K114%*ABS(S114),0)) -> 0 | X114: =IF(S114<0,-W114,W114) -> 0 | AB114: =IF(C114="","",ROUND(V114*(1+'Inflación observada '!$B$390%)^(("31-12-2025"-C114)/365),3)) -> 399.091 | AD114: =IF(C114="","",IF(G114="UVR",Q114*AB114-S114,0)) -> 0 | AE114: =IF(C114="","",P114/+(O114+P114)) -> #DIV/0! | AF114: =IF(C114="","",AE114*Q114*K114%) -> #DIV/0! | AG114: =(Tabla6[[#This Row],[Fecha Vto]]-TODAY())/365 -> 0.47123288 | AJ114: =IF(C114="","",IF(G114="UVR",Q114*AI114-S114,0)) -> 0
A115: =IF(C115="","",YEAR(C115)) -> 2025 | B115: 639 | C115: 45957 | D115: Tesorería | E115: Títulos Entregados por la Nación | F115: TFIT23250746 | G115: =+_xlfn.XLOOKUP(F115,Emisiones[Mnemotécnico SEN],Emisiones[Moneda],"",0,1) -> COP | J115: =+_xlfn.XLOOKUP(F115,Emisiones[Mnemotécnico SEN],Emisiones[Fecha Vencim.],"",0,1) -> 53533 | K115: =+_xlfn.XLOOKUP(F115,Emisiones[Mnemotécnico SEN],Emisiones[Tasa de Interés],"",0,1) -> 11.5 | L115: 12.13 | M115: 98.126 | N115: =IF(C115="","",PRICE(C115,J115,K115%,L115%,100,1,3)) -> 95.16478 | O115: =IF(C115="","",M115-N115) -> 2.96122 | P115: =IF(C115="","",100*K115%-O115) -> 8.53878 | Q115: =IF(C115="","",IF(G115="UVR",S115/V115,S115)) -> 481500000000 | R115: =IF(C115="","",IF('Canjes desagregado'!$G115="UVR",'Canjes desagregado'!$V115*Q115*M115%,Q115*M115%)) -> 472476690000 | S115: 481500000000 | T115: =IFERROR(IF(RIGHT(F115,2)=RIGHT(YEAR(J115),2),1,0),"") -> 1 | U115: =+IF(R115="","",R115) -> 472476690000 | V115: =+IF(F115<>"",(_xlfn.XLOOKUP(C115,UVR[Fecha (dd/mm/aaaa)],UVR[Pesos colombianos por UVR],"",0,1)),"") -> 395.4908 | W115: =IF(C115="","",IF(CONCATENATE(DAY(C115),"/",MONTH(C115),"/",2000)-CONCATENATE(DAY(J115),"/",MONTH(J115),"/",2000)<0,K115%*ABS(S115),0)) -> 0 | X115: =IF(S115<0,-W115,W115) -> 0 | AB115: =IF(C115="","",ROUND(V115*(1+'Inflación observada '!$B$390%)^(("31-12-2025"-C115)/365),3)) -> 399.091 | AD115: =IF(C115="","",IF(G115="UVR",Q115*AB115-S115,0)) -> 0 | AE115: =IF(C115="","",P115/+(O115+P115)) -> 0.7425026 | AF115: =IF(C115="","",AE115*Q115*K115%) -> 4.1114225e+10 | AG115: =(Tabla6[[#This Row],[Fecha Vto]]-TODAY())/365 -> 20.630137 | AJ115: =IF(C115="","",IF(G115="UVR",Q115*AI115-S115,0)) -> 0
A116: =IF(C116="","",YEAR(C116)) -> 2025 | B116: 640 | C116: 45958 | D116: Tesorería | E116: Títulos Recogidos por la Nación | F116: COL17CT04027 | G116: =+_xlfn.XLOOKUP(F116,Emisiones[Mnemotécnico SEN],Emisiones[Moneda],"",0,1) -> COP | J116: =+_xlfn.XLOOKUP(F116,Emisiones[Mnemotécnico SEN],Emisiones[Fecha Vencim.],"",0,1) -> 46175 | K116: =+_xlfn.XLOOKUP(F116,Emisiones[Mnemotécnico SEN],Emisiones[Tasa de Interés],"",0,1) -> 0 | L116: 9.1 | M116: 94.954 | N116: =IF(C116="","",PRICE(C116,J116,K116%,L116%,100,1,3)) -> 94.867536 | O116: =IF(C116="","",M116-N116) -> 0.086463671 | P116: =IF(C116="","",100*K116%-O116) -> -0.086463671 | Q116: =IF(C116="","",IF(G116="UVR",S116/V116,S116)) -> -517245200000 | R116: =IF(C116="","",IF('Canjes desagregado'!$G116="UVR",'Canjes desagregado'!$V116*Q116*M116%,Q116*M116%)) -> -4.9114501e+11 | S116: -517245200000 | T116: =IFERROR(IF(RIGHT(F116,2)=RIGHT(YEAR(J116),2),1,0),"") -> 0 | U116: =+IF(R116="","",R116) -> -4.9114501e+11 | V116: =+IF(F116<>"",(_xlfn.XLOOKUP(C116,UVR[Fecha (dd/mm/aaaa)],UVR[Pesos colombianos por UVR],"",0,1)),"") -> 395.5316 | W116: =IF(C116="","",IF(CONCATENATE(DAY(C116),"/",MONTH(C116),"/",2000)-CONCATENATE(DAY(J116),"/",MONTH(J116),"/",2000)<0,K116%*ABS(S116),0)) -> 0 | X116: =IF(S116<0,-W116,W116) -> 0 | AB116: =IF(C116="","",ROUND(V116*(1+'Inflación observada '!$B$390%)^(("31-12-2025"-C116)/365),3)) -> 399.076 | AD116: =IF(C116="","",IF(G116="UVR",Q116*AB116-S116,0)) -> 0 | AE116: =IF(C116="","",P116/+(O116+P116)) -> #DIV/0! | AF116: =IF(C116="","",AE116*Q116*K116%) -> #DIV/0! | AG116: =(Tabla6[[#This Row],[Fecha Vto]]-TODAY())/365 -> 0.47123288 | AJ116: =IF(C116="","",IF(G116="UVR",Q116*AI116-S116,0)) -> 0
A117: =IF(C117="","",YEAR(C117)) -> 2025 | B117: 640 | C117: 45958 | D117: Tesorería | E117: Títulos Entregados por la Nación | F117: TFIT23250746 | G117: =+_xlfn.XLOOKUP(F117,Emisiones[Mnemotécnico SEN],Emisiones[Moneda],"",0,1) -> COP | J117: =+_xlfn.XLOOKUP(F117,Emisiones[Mnemotécnico SEN],Emisiones[Fecha Vencim.],"",0,1) -> 53533 | K117: =+_xlfn.XLOOKUP(F117,Emisiones[Mnemotécnico SEN],Emisiones[Tasa de Interés],"",0,1) -> 11.5 | L117: 12.12 | M117: 98.229 | N117: =IF(C117="","",PRICE(C117,J117,K117%,L117%,100,1,3)) -> 95.235979 | O117: =IF(C117="","",M117-N117) -> 2.9930215 | P117: =IF(C117="","",100*K117%-O117) -> 8.5069785 | Q117: =IF(C117="","",IF(G117="UVR",S117/V117,S117)) -> 500000000000 | R117: =IF(C117="","",IF('Canjes desagregado'!$G117="UVR",'Canjes desagregado'!$V117*Q117*M117%,Q117*M117%)) -> 491145000000 | S117: 500000000000 | T117: =IFERROR(IF(RIGHT(F117,2)=RIGHT(YEAR(J117),2),1,0),"") -> 1 | U117: =+IF(R117="","",R117) -> 491145000000 | V117: =+IF(F117<>"",(_xlfn.XLOOKUP(C117,UVR[Fecha (dd/mm/aaaa)],UVR[Pesos colombianos por UVR],"",0,1)),"") -> 395.5316 | W117: =IF(C117="","",IF(CONCATENATE(DAY(C117),"/",MONTH(C117),"/",2000)-CONCATENATE(DAY(J117),"/",MONTH(J117),"/",2000)<0,K117%*ABS(S117),0)) -> 0 | X117: =IF(S117<0,-W117,W117) -> 0 | AB117: =IF(C117="","",ROUND(V117*(1+'Inflación observada '!$B$390%)^(("31-12-2025"-C117)/365),3)) -> 399.076 | AD117: =IF(C117="","",IF(G117="UVR",Q117*AB117-S117,0)) -> 0 | AE117: =IF(C117="","",P117/+(O117+P117)) -> 0.73973726 | AF117: =IF(C117="","",AE117*Q117*K117%) -> 4.2534893e+10 | AG117: =(Tabla6[[#This Row],[Fecha Vto]]-TODAY())/365 -> 20.630137 | AJ117: =IF(C117="","",IF(G117="UVR",Q117*AI117-S117,0)) -> 0
A118: =IF(C118="","",YEAR(C118)) | B118: 641 | G118: =+_xlfn.XLOOKUP(F118,Emisiones[Mnemotécnico SEN],Emisiones[Moneda],"",0,1) -> 0 | J118: =+_xlfn.XLOOKUP(F118,Emisiones[Mnemotécnico SEN],Emisiones[Fecha Vencim.],"",0,1) -> 0 | K118: =+_xlfn.XLOOKUP(F118,Emisiones[Mnemotécnico SEN],Emisiones[Tasa de Interés],"",0,1) -> 0 | N118: =IF(C118="","",PRICE(C118,J118,K118%,L118%,100,1,3)) | O118: =IF(C118="","",M118-N118) | P118: =IF(C118="","",100*K118%-O118) | Q118: =IF(C118="","",IF(G118="UVR",S118/V118,S118)) | R118: =IF(C118="","",IF('Canjes desagregado'!$G118="UVR",'Canjes desagregado'!$V118*Q118*M118%,Q118*M118%)) | T118: =IFERROR(IF(RIGHT(F118,2)=RIGHT(YEAR(J118),2),1,0),"") -> 0 | U118: =+IF(R118="","",R118) | V118: =+IF(F118<>"",(_xlfn.XLOOKUP(C118,UVR[Fecha (dd/mm/aaaa)],UVR[Pesos colombianos por UVR],"",0,1)),"") | W118: =IF(C118="","",IF(CONCATENATE(DAY(C118),"/",MONTH(C118),"/",2000)-CONCATENATE(DAY(J118),"/",MONTH(J118),"/",2000)<0,K118%*ABS(S118),0)) | X118: =IF(S118<0,-W118,W118) | AB118: =IF(C118="","",ROUND(V118*(1+'Inflación observada '!$B$390%)^(("31-12-2025"-C118)/365),3)) | AD118: =IF(C118="","",IF(G118="UVR",Q118*AB118-S118,0)) | AE118: =IF(C118="","",P118/+(O118+P118)) | AF118: =IF(C118="","",AE118*Q118*K118%) | AG118: =(Tabla6[[#This Row],[Fecha Vto]]-TODAY())/365 -> -126.03562 | AJ118: =IF(C118="","",IF(G118="UVR",Q118*AI118-S118,0))
A119: =IF(C119="","",YEAR(C119)) -> 2025 | B119: 642 | C119: 45966 | D119: Tesorería | E119: Títulos Recogidos por la Nación | F119: COL17CT03987 | G119: =+_xlfn.XLOOKUP(F119,Emisiones[Mnemotécnico SEN],Emisiones[Moneda],"",0,1) -> COP | J119: =+_xlfn.XLOOKUP(F119,Emisiones[Mnemotécnico SEN],Emisiones[Fecha Vencim.],"",0,1) -> 46084 | K119: =+_xlfn.XLOOKUP(F119,Emisiones[Mnemotécnico SEN],Emisiones[Tasa de Interés],"",0,1) -> 0 | L119: 9.139 | M119: 97.212 | N119: =IF(C119="","",PRICE(C119,J119,K119%,L119%,100,1,3)) -> 97.130261 | O119: =IF(C119="","",M119-N119) -> 0.081738846 | P119: =IF(C119="","",100*K119%-O119) -> -0.081738846 | Q119: =IF(C119="","",IF(G119="UVR",S119/V119,S119)) -> -179000000000 | R119: =IF(C119="","",IF('Canjes desagregado'!$G119="UVR",'Canjes desagregado'!$V119*Q119*M119%,Q119*M119%)) -> -174009480000 | S119: -179000000000 | T119: =IFERROR(IF(RIGHT(F119,2)=RIGHT(YEAR(J119),2),1,0),"") -> 0 | U119: =+IF(R119="","",R119) -> -174009480000 | V119: =+IF(F119<>"",(_xlfn.XLOOKUP(C119,UVR[Fecha (dd/mm/aaaa)],UVR[Pesos colombianos por UVR],"",0,1)),"") -> 395.8578 | W119: =IF(C119="","",IF(CONCATENATE(DAY(C119),"/",MONTH(C119),"/",2000)-CONCATENATE(DAY(J119),"/",MONTH(J119),"/",2000)<0,K119%*ABS(S119),0)) -> 0 | X119: =IF(S119<0,-W119,W119) -> 0 | AB119: =IF(C119="","",ROUND(V119*(1+'Inflación observada '!$B$390%)^(("31-12-2025"-C119)/365),3)) -> 398.96 | AD119: =IF(C119="","",IF(G119="UVR",Q119*AB119-S119,0)) -> 0 | AE119: =IF(C119="","",P119/+(O119+P119)) -> #DIV/0! | AF119: =IF(C119="","",AE119*Q119*K119%) -> #DIV/0! | AG119: =(Tabla6[[#This Row],[Fecha Vto]]-TODAY())/365 -> 0.22191781 | AJ119: =IF(C119="","",IF(G119="UVR",Q119*AI119-S119,0)) -> 0
A120: =IF(C120="","",YEAR(C120)) -> 2025 | B120: 642 | C120: 45966 | D120: Tesorería | E120: Títulos Recogidos por la Nación | F120: TFIT15260826 | G120: =+_xlfn.XLOOKUP(F120,Emisiones[Mnemotécnico SEN],Emisiones[Moneda],"",0,1) -> COP | J120: =+_xlfn.XLOOKUP(F120,Emisiones[Mnemotécnico SEN],Emisiones[Fecha Vencim.],"",0,1) -> 46260 | K120: =+_xlfn.XLOOKUP(F120,Emisiones[Mnemotécnico SEN],Emisiones[Tasa de Interés],"",0,1) -> 7.5 | L120: 9.183 | M120: 100.156 | N120: =IF(C120="","",PRICE(C120,J120,K120%,L120%,100,1,3)) -> 98.637265 | O120: =IF(C120="","",M120-N120) -> 1.5187353 | P120: =IF(C120="","",100*K120%-O120) -> 5.9812647 | Q120: =IF(C120="","",IF(G120="UVR",S120/V120,S120)) -> -41273300000 | R120: =IF(C120="","",IF('Canjes desagregado'!$G120="UVR",'Canjes desagregado'!$V120*Q120*M120%,Q120*M120%)) -> -41337686348 | S120: -41273300000 | T120: =IFERROR(IF(RIGHT(F120,2)=RIGHT(YEAR(J120),2),1,0),"") -> 1 | U120: =+IF(R120="","",R120) -> -41337686348 | V120: =+IF(F120<>"",(_xlfn.XLOOKUP(C120,UVR[Fecha (dd/mm/aaaa)],UVR[Pesos colombianos por UVR],"",0,1)),"") -> 395.8578 | W120: =IF(C120="","",IF(CONCATENATE(DAY(C120),"/",MONTH(C120),"/",2000)-CONCATENATE(DAY(J120),"/",MONTH(J120),"/",2000)<0,K120%*ABS(S120),0)) -> 0 | X120: =IF(S120<0,-W120,W120) -> 0 | AB120: =IF(C120="","",ROUND(V120*(1+'Inflación observada '!$B$390%)^(("31-12-2025"-C120)/365),3)) -> 398.96 | AD120: =IF(C120="","",IF(G120="UVR",Q120*AB120-S120,0)) -> 0 | AE120: =IF(C120="","",P120/+(O120+P120)) -> 0.79750197 | AF120: =IF(C120="","",AE120*Q120*K120%) -> -2.4686653e+09 | AG120: =(Tabla6[[#This Row],[Fecha Vto]]-TODAY())/365 -> 0.70410959 | AJ120: =IF(C120="","",IF(G120="UVR",Q120*AI120-S120,0)) -> 0
A121: =IF(C121="","",YEAR(C121)) -> 2025 | B121: 642 | C121: 45966 | D121: Tesorería | E121: Títulos Entregados por la Nación | F121: TFIT23250746 | G121: =+_xlfn.XLOOKUP(F121,Emisiones[Mnemotécnico SEN],Emisiones[Moneda],"",0,1) -> COP | J121: =+_xlfn.XLOOKUP(F121,Emisiones[Mnemotécnico SEN],Emisiones[Fecha Vencim.],"",0,1) -> 53533 | K121: =+_xlfn.XLOOKUP(F121,Emisiones[Mnemotécnico SEN],Emisiones[Tasa de Interés],"",0,1) -> 11.5 | L121: 12.14 | M121: 98.332 | N121: =IF(C121="","",PRICE(C121,J121,K121%,L121%,100,1,3)) -> 95.086803 | O121: =IF(C121="","",M121-N121) -> 3.2451965 | P121: =IF(C121="","",100*K121%-O121) -> 8.2548035 | Q121: =IF(C121="","",IF(G121="UVR",S121/V121,S121)) -> 219000000000 | R121: =IF(C121="","",IF('Canjes desagregado'!$G121="UVR",'Canjes desagregado'!$V121*Q121*M121%,Q121*M121%)) -> 215347080000 | S121: 219000000000 | T121: =IFERROR(IF(RIGHT(F121,2)=RIGHT(YEAR(J121),2),1,0),"") -> 1 | U121: =+IF(R121="","",R121) -> 215347080000 | V121: =+IF(F121<>"",(_xlfn.XLOOKUP(C121,UVR[Fecha (dd/mm/aaaa)],UVR[Pesos colombianos por UVR],"",0,1)),"") -> 395.8578 | W121: =IF(C121="","",IF(CONCATENATE(DAY(C121),"/",MONTH(C121),"/",2000)-CONCATENATE(DAY(J121),"/",MONTH(J121),"/",2000)<0,K121%*ABS(S121),0)) -> 0 | X121: =IF(S121<0,-W121,W121) -> 0 | AB121: =IF(C121="","",ROUND(V121*(1+'Inflación observada '!$B$390%)^(("31-12-2025"-C121)/365),3)) -> 398.96 | AD121: =IF(C121="","",IF(G121="UVR",Q121*AB121-S121,0)) -> 0 | AE121: =IF(C121="","",P121/+(O121+P121)) -> 0.717809 | AF121: =IF(C121="","",AE121*Q121*K121%) -> 1.807802e+10 | AG121: =(Tabla6[[#This Row],[Fecha Vto]]-TODAY())/365 -> 20.630137 | AJ121: =IF(C121="","",IF(G121="UVR",Q121*AI121-S121,0)) -> 0
A122: =IF(C122="","",YEAR(C122)) -> 2025 | B122: 643 | C122: 45971 | D122: Tesorería | E122: Títulos Recogidos por la Nación | F122: COL17CT03987 | G122: =+_xlfn.XLOOKUP(F122,Emisiones[Mnemotécnico SEN],Emisiones[Moneda],"",0,1) -> COP | J122: =+_xlfn.XLOOKUP(F122,Emisiones[Mnemotécnico SEN],Emisiones[Fecha Vencim.],"",0,1) -> 46084 | K122: =+_xlfn.XLOOKUP(F122,Emisiones[Mnemotécnico SEN],Emisiones[Tasa de Interés],"",0,1) -> 0 | L122: 9.146 | M122: 97.327 | N122: =IF(C122="","",PRICE(C122,J122,K122%,L122%,100,1,3)) -> 97.246465 | O122: =IF(C122="","",M122-N122) -> 0.080534989 | P122: =IF(C122="","",100*K122%-O122) -> -0.080534989 | Q122: =IF(C122="","",IF(G122="UVR",S122/V122,S122)) -> -97500000000 | R122: =IF(C122="","",IF('Canjes desagregado'!$G122="UVR",'Canjes desagregado'!$V122*Q122*M122%,Q122*M122%)) -> -94893825000 | S122: -97500000000 | T122: =IFERROR(IF(RIGHT(F122,2)=RIGHT(YEAR(J122),2),1,0),"") -> 0 | U122: =+IF(R122="","",R122) -> -94893825000 | V122: =+IF(F122<>"",(_xlfn.XLOOKUP(C122,UVR[Fecha (dd/mm/aaaa)],UVR[Pesos colombianos por UVR],"",0,1)),"") -> 396.0619 | W122: =IF(C122="","",IF(CONCATENATE(DAY(C122),"/",MONTH(C122),"/",2000)-CONCATENATE(DAY(J122),"/",MONTH(J122),"/",2000)<0,K122%*ABS(S122),0)) -> 0 | X122: =IF(S122<0,-W122,W122) -> 0 | AB122: =IF(C122="","",ROUND(V122*(1+'Inflación observada '!$B$390%)^(("31-12-2025"-C122)/365),3)) -> 398.888 | AD122: =IF(C122="","",IF(G122="UVR",Q122*AB122-S122,0)) -> 0 | AE122: =IF(C122="","",P122/+(O122+P122)) -> #DIV/0! | AF122: =IF(C122="","",AE122*Q122*K122%) -> #DIV/0! | AG122: =(Tabla6[[#This Row],[Fecha Vto]]-TODAY())/365 -> 0.22191781 | AJ122: =IF(C122="","",IF(G122="UVR",Q122*AI122-S122,0)) -> 0
A123: =IF(C123="","",YEAR(C123)) -> 2025 | B123: 643 | C123: 45971 | D123: Tesorería | E123: Títulos Recogidos por la Nación | F123: TFIT15260826 | G123: =+_xlfn.XLOOKUP(F123,Emisiones[Mnemotécnico SEN],Emisiones[Moneda],"",0,1) -> COP | J123: =+_xlfn.XLOOKUP(F123,Emisiones[Mnemotécnico SEN],Emisiones[Fecha Vencim.],"",0,1) -> 46260 | K123: =+_xlfn.XLOOKUP(F123,Emisiones[Mnemotécnico SEN],Emisiones[Tasa de Interés],"",0,1) -> 7.5 | L123: 9.201 | M123: 100.263 | N123: =IF(C123="","",PRICE(C123,J123,K123%,L123%,100,1,3)) -> 98.638593 | O123: =IF(C123="","",M123-N123) -> 1.6244068 | P123: =IF(C123="","",100*K123%-O123) -> 5.8755932 | Q123: =IF(C123="","",IF(G123="UVR",S123/V123,S123)) -> -97500000000 | R123: =IF(C123="","",IF('Canjes desagregado'!$G123="UVR",'Canjes desagregado'!$V123*Q123*M123%,Q123*M123%)) -> -9.7756425e+10 | S123: -97500000000 | T123: =IFERROR(IF(RIGHT(F123,2)=RIGHT(YEAR(J123),2),1,0),"") -> 1 | U123: =+IF(R123="","",R123) -> -9.7756425e+10 | V123: =+IF(F123<>"",(_xlfn.XLOOKUP(C123,UVR[Fecha (dd/mm/aaaa)],UVR[Pesos colombianos por UVR],"",0,1)),"") -> 396.0619 | W123: =IF(C123="","",IF(CONCATENATE(DAY(C123),"/",MONTH(C123),"/",2000)-CONCATENATE(DAY(J123),"/",MONTH(J123),"/",2000)<0,K123%*ABS(S123),0)) -> 0 | X123: =IF(S123<0,-W123,W123) -> 0 | AB123: =IF(C123="","",ROUND(V123*(1+'Inflación observada '!$B$390%)^(("31-12-2025"-C123)/365),3)) -> 398.888 | AD123: =IF(C123="","",IF(G123="UVR",Q123*AB123-S123,0)) -> 0 | AE123: =IF(C123="","",P123/+(O123+P123)) -> 0.78341243 | AF123: =IF(C123="","",AE123*Q123*K123%) -> -5.7287034e+09 | AG123: =(Tabla6[[#This Row],[Fecha Vto]]-TODAY())/365 -> 0.70410959 | AJ123: =IF(C123="","",IF(G123="UVR",Q123*AI123-S123,0)) -> 0
A124: =IF(C124="","",YEAR(C124)) -> 2025 | B124: 643 | C124: 45971 | D124: Tesorería | E124: Títulos Entregados por la Nación | F124: COL17CT04084 | G124: =+_xlfn.XLOOKUP(F124,Emisiones[Mnemotécnico SEN],Emisiones[Moneda],"",0,1) -> COP | J124: =+_xlfn.XLOOKUP(F124,Emisiones[Mnemotécnico SEN],Emisiones[Fecha Vencim.],"",0,1) -> 49313 | K124: =+_xlfn.XLOOKUP(F124,Emisiones[Mnemotécnico SEN],Emisiones[Tasa de Interés],"",0,1) -> 11.75 | L124: 12.098 | M124: 107.354 | N124: =IF(C124="","",PRICE(C124,J124,K124%,L124%,100,1,3)) -> 98.048101 | O124: =IF(C124="","",M124-N124) -> 9.3058992 | P124: =IF(C124="","",100*K124%-O124) -> 2.4441008 | Q124: =IF(C124="","",IF(G124="UVR",S124/V124,S124)) -> 8000000000 | R124: =IF(C124="","",IF('Canjes desagregado'!$G124="UVR",'Canjes desagregado'!$V124*Q124*M124%,Q124*M124%)) -> 8.58832e+09 | S124: 8000000000 | T124: =IFERROR(IF(RIGHT(F124,2)=RIGHT(YEAR(J124),2),1,0),"") -> 0 | U124: =+IF(R124="","",R124) -> 8.58832e+09 | V124: =+IF(F124<>"",(_xlfn.XLOOKUP(C124,UVR[Fecha (dd/mm/aaaa)],UVR[Pesos colombianos por UVR],"",0,1)),"") -> 396.0619 | W124: =IF(C124="","",IF(CONCATENATE(DAY(C124),"/",MONTH(C124),"/",2000)-CONCATENATE(DAY(J124),"/",MONTH(J124),"/",2000)<0,K124%*ABS(S124),0)) -> 0 | X124: =IF(S124<0,-W124,W124) -> 0 | AB124: =IF(C124="","",ROUND(V124*(1+'Inflación observada '!$B$390%)^(("31-12-2025"-C124)/365),3)) -> 398.888 | AD124: =IF(C124="","",IF(G124="UVR",Q124*AB124-S124,0)) -> 0 | AE124: =IF(C124="","",P124/+(O124+P124)) -> 0.20800858 | AF124: =IF(C124="","",AE124*Q124*K124%) -> 1.9552806e+08 | AG124: =(Tabla6[[#This Row],[Fecha Vto]]-TODAY())/365 -> 9.0684932 | AJ124: =IF(C124="","",IF(G124="UVR",Q124*AI124-S124,0)) -> 0
A125: =IF(C125="","",YEAR(C125)) -> 2025 | B125: 643 | C125: 45971 | D125: Tesorería | E125: Títulos Entregados por la Nación | F125: TFIT23250746 | G125: =+_xlfn.XLOOKUP(F125,Emisiones[Mnemotécnico SEN],Emisiones[Moneda],"",0,1) -> COP | J125: =+_xlfn.XLOOKUP(F125,Emisiones[Mnemotécnico SEN],Emisiones[Fecha Vencim.],"",0,1) -> 53533 | K125: =+_xlfn.XLOOKUP(F125,Emisiones[Mnemotécnico SEN],Emisiones[Tasa de Interés],"",0,1) -> 11.5 | L125: 12.15 | M125: 98.415 | N125: =IF(C125="","",PRICE(C125,J125,K125%,L125%,100,1,3)) -> 95.012009 | O125: =IF(C125="","",M125-N125) -> 3.4029906 | P125: =IF(C125="","",100*K125%-O125) -> 8.0970094 | Q125: =IF(C125="","",IF(G125="UVR",S125/V125,S125)) -> 187000000000 | R125: =IF(C125="","",IF('Canjes desagregado'!$G125="UVR",'Canjes desagregado'!$V125*Q125*M125%,Q125*M125%)) -> 184036050000 | S125: 187000000000 | T125: =IFERROR(IF(RIGHT(F125,2)=RIGHT(YEAR(J125),2),1,0),"") -> 1 | U125: =+IF(R125="","",R125) -> 184036050000 | V125: =+IF(F125<>"",(_xlfn.XLOOKUP(C125,UVR[Fecha (dd/mm/aaaa)],UVR[Pesos colombianos por UVR],"",0,1)),"") -> 396.0619 | W125: =IF(C125="","",IF(CONCATENATE(DAY(C125),"/",MONTH(C125),"/",2000)-CONCATENATE(DAY(J125),"/",MONTH(J125),"/",2000)<0,K125%*ABS(S125),0)) -> 0 | X125: =IF(S125<0,-W125,W125) -> 0 | AB125: =IF(C125="","",ROUND(V125*(1+'Inflación observada '!$B$390%)^(("31-12-2025"-C125)/365),3)) -> 398.888 | AD125: =IF(C125="","",IF(G125="UVR",Q125*AB125-S125,0)) -> 0 | AE125: =IF(C125="","",P125/+(O125+P125)) -> 0.70408778 | AF125: =IF(C125="","",AE125*Q125*K125%) -> 1.5141408e+10 | AG125: =(Tabla6[[#This Row],[Fecha Vto]]-TODAY())/365 -> 20.630137 | AJ125: =IF(C125="","",IF(G125="UVR",Q125*AI125-S125,0)) -> 0
A126: =IF(C126="","",YEAR(C126)) -> 2025 | B126: 644 | C126: 45980 | D126: Tesorería | E126: Títulos Recogidos por la Nación | F126: COL17CT03987 | G126: =+_xlfn.XLOOKUP(F126,Emisiones[Mnemotécnico SEN],Emisiones[Moneda],"",0,1) -> COP | J126: =+_xlfn.XLOOKUP(F126,Emisiones[Mnemotécnico SEN],Emisiones[Fecha Vencim.],"",0,1) -> 46084 | K126: =+_xlfn.XLOOKUP(F126,Emisiones[Mnemotécnico SEN],Emisiones[Tasa de Interés],"",0,1) -> 0 | L126: 9.15 | M126: 97.536 | N126: =IF(C126="","",PRICE(C126,J126,K126%,L126%,100,1,3)) -> 97.459121 | O126: =IF(C126="","",M126-N126) -> 0.076879428 | P126: =IF(C126="","",100*K126%-O126) -> -0.076879428 | Q126: =IF(C126="","",IF(G126="UVR",S126/V126,S126)) -> -35568000000 | R126: =IF(C126="","",IF('Canjes desagregado'!$G126="UVR",'Canjes desagregado'!$V126*Q126*M126%,Q126*M126%)) -> -34691604480 | S126: -35568000000 | T126: =IFERROR(IF(RIGHT(F126,2)=RIGHT(YEAR(J126),2),1,0),"") -> 0 | U126: =+IF(R126="","",R126) -> -34691604480 | V126: =+IF(F126<>"",(_xlfn.XLOOKUP(C126,UVR[Fecha (dd/mm/aaaa)],UVR[Pesos colombianos por UVR],"",0,1)),"") -> 396.361 | W126: =IF(C126="","",IF(CONCATENATE(DAY(C126),"/",MONTH(C126),"/",2000)-CONCATENATE(DAY(J126),"/",MONTH(J126),"/",2000)<0,K126%*ABS(S126),0)) -> 0 | X126: =IF(S126<0,-W126,W126) -> 0 | AB126: =IF(C126="","",ROUND(V126*(1+'Inflación observada '!$B$390%)^(("31-12-2025"-C126)/365),3)) -> 398.689 | AD126: =IF(C126="","",IF(G126="UVR",Q126*AB126-S126,0)) -> 0 | AE126: =IF(C126="","",P126/+(O126+P126)) -> #DIV/0! | AF126: =IF(C126="","",AE126*Q126*K126%) -> #DIV/0! | AG126: =(Tabla6[[#This Row],[Fecha Vto]]-TODAY())/365 -> 0.22191781 | AJ126: =IF(C126="","",IF(G126="UVR",Q126*AI126-S126,0)) -> 0
A127: =IF(C127="","",YEAR(C127)) -> 2025 | B127: 644 | C127: 45980 | D127: Tesorería | E127: Títulos Recogidos por la Nación | F127: TFIT15260826 | G127: =+_xlfn.XLOOKUP(F127,Emisiones[Mnemotécnico SEN],Emisiones[Moneda],"",0,1) -> COP | J127: =+_xlfn.XLOOKUP(F127,Emisiones[Mnemotécnico SEN],Emisiones[Fecha Vencim.],"",0,1) -> 46260 | K127: =+_xlfn.XLOOKUP(F127,Emisiones[Mnemotécnico SEN],Emisiones[Tasa de Interés],"",0,1) -> 7.5 | L127: 9.21 | M127: 100.475 | N127: =IF(C127="","",PRICE(C127,J127,K127%,L127%,100,1,3)) -> 98.659527 | O127: =IF(C127="","",M127-N127) -> 1.8154728 | P127: =IF(C127="","",100*K127%-O127) -> 5.6845272 | Q127: =IF(C127="","",IF(G127="UVR",S127/V127,S127)) -> -192432000000 | R127: =IF(C127="","",IF('Canjes desagregado'!$G127="UVR",'Canjes desagregado'!$V127*Q127*M127%,Q127*M127%)) -> -193346052000 | S127: -192432000000 | T127: =IFERROR(IF(RIGHT(F127,2)=RIGHT(YEAR(J127),2),1,0),"") -> 1 | U127: =+IF(R127="","",R127) -> -193346052000 | V127: =+IF(F127<>"",(_xlfn.XLOOKUP(C127,UVR[Fecha (dd/mm/aaaa)],UVR[Pesos colombianos por UVR],"",0,1)),"") -> 396.361 | W127: =IF(C127="","",IF(CONCATENATE(DAY(C127),"/",MONTH(C127),"/",2000)-CONCATENATE(DAY(J127),"/",MONTH(J127),"/",2000)<0,K127%*ABS(S127),0)) -> 0 | X127: =IF(S127<0,-W127,W127) -> 0 | AB127: =IF(C127="","",ROUND(V127*(1+'Inflación observada '!$B$390%)^(("31-12-2025"-C127)/365),3)) -> 398.689 | AD127: =IF(C127="","",IF(G127="UVR",Q127*AB127-S127,0)) -> 0 | AE127: =IF(C127="","",P127/+(O127+P127)) -> 0.75793696 | AF127: =IF(C127="","",AE127*Q127*K127%) -> -1.0938849e+10 | AG127: =(Tabla6[[#This Row],[Fecha Vto]]-TODAY())/365 -> 0.70410959 | AJ127: =IF(C127="","",IF(G127="UVR",Q127*AI127-S127,0)) -> 0
A128: =IF(C128="","",YEAR(C128)) -> 2025 | B128: 644 | C128: 45980 | D128: Tesorería | E128: Títulos Entregados por la Nación | F128: TFIT05220829 | G128: =+_xlfn.XLOOKUP(F128,Emisiones[Mnemotécnico SEN],Emisiones[Moneda],"",0,1) -> COP | J128: =+_xlfn.XLOOKUP(F128,Emisiones[Mnemotécnico SEN],Emisiones[Fecha Vencim.],"",0,1) -> 47352 | K128: =+_xlfn.XLOOKUP(F128,Emisiones[Mnemotécnico SEN],Emisiones[Tasa de Interés],"",0,1) -> 11 | L128: 11.882 | M128: 100.015 | N128: =IF(C128="","",PRICE(C128,J128,K128%,L128%,100,1,3)) -> 97.333128 | O128: =IF(C128="","",M128-N128) -> 2.6818721 | P128: =IF(C128="","",100*K128%-O128) -> 8.3181279 | Q128: =IF(C128="","",IF(G128="UVR",S128/V128,S128)) -> 228000000000 | R128: =IF(C128="","",IF('Canjes desagregado'!$G128="UVR",'Canjes desagregado'!$V128*Q128*M128%,Q128*M128%)) -> 2.280342e+11 | S128: 228000000000 | T128: =IFERROR(IF(RIGHT(F128,2)=RIGHT(YEAR(J128),2),1,0),"") -> 1 | U128: =+IF(R128="","",R128) -> 2.280342e+11 | V128: =+IF(F128<>"",(_xlfn.XLOOKUP(C128,UVR[Fecha (dd/mm/aaaa)],UVR[Pesos colombianos por UVR],"",0,1)),"") -> 396.361 | W128: =IF(C128="","",IF(CONCATENATE(DAY(C128),"/",MONTH(C128),"/",2000)-CONCATENATE(DAY(J128),"/",MONTH(J128),"/",2000)<0,K128%*ABS(S128),0)) -> 0 | X128: =IF(S128<0,-W128,W128) -> 0 | AB128: =IF(C128="","",ROUND(V128*(1+'Inflación observada '!$B$390%)^(("31-12-2025"-C128)/365),3)) -> 398.689 | AD128: =IF(C128="","",IF(G128="UVR",Q128*AB128-S128,0)) -> 0 | AE128: =IF(C128="","",P128/+(O128+P128)) -> 0.75619345 | AF128: =IF(C128="","",AE128*Q128*K128%) -> 1.8965332e+10 | AG128: =(Tabla6[[#This Row],[Fecha Vto]]-TODAY())/365 -> 3.6958904 | AJ128: =IF(C128="","",IF(G128="UVR",Q128*AI128-S128,0)) -> 0
A129: =IF(C129="","",YEAR(C129)) -> 2025 | B129: 645 | C129: 45981 | D129: Tesorería | E129: Títulos Recogidos por la Nación | F129: COL17CT03987 | G129: =+_xlfn.XLOOKUP(F129,Emisiones[Mnemotécnico SEN],Emisiones[Moneda],"",0,1) -> COP | J129: =+_xlfn.XLOOKUP(F129,Emisiones[Mnemotécnico SEN],Emisiones[Fecha Vencim.],"",0,1) -> 46084 | K129: =+_xlfn.XLOOKUP(F129,Emisiones[Mnemotécnico SEN],Emisiones[Tasa de Interés],"",0,1) -> 0 | L129: 9.159 | M129: 97.557 | N129: =IF(C129="","",PRICE(C129,J129,K129%,L129%,100,1,3)) -> 97.480524 | O129: =IF(C129="","",M129-N129) -> 0.076476275 | P129: =IF(C129="","",100*K129%-O129) -> -0.076476275 | Q129: =IF(C129="","",IF(G129="UVR",S129/V129,S129)) -> -28215000000 | R129: =IF(C129="","",IF('Canjes desagregado'!$G129="UVR",'Canjes desagregado'!$V129*Q129*M129%,Q129*M129%)) -> -27525707550 | S129: -28215000000 | T129: =IFERROR(IF(RIGHT(F129,2)=RIGHT(YEAR(J129),2),1,0),"") -> 0 | U129: =+IF(R129="","",R129) -> -27525707550 | V129: =+IF(F129<>"",(_xlfn.XLOOKUP(C129,UVR[Fecha (dd/mm/aaaa)],UVR[Pesos colombianos por UVR],"",0,1)),"") -> 396.3848 | W129: =IF(C129="","",IF(CONCATENATE(DAY(C129),"/",MONTH(C129),"/",2000)-CONCATENATE(DAY(J129),"/",MONTH(J129),"/",2000)<0,K129%*ABS(S129),0)) -> 0 | X129: =IF(S129<0,-W129,W129) -> 0 | AB129: =IF(C129="","",ROUND(V129*(1+'Inflación observada '!$B$390%)^(("31-12-2025"-C129)/365),3)) -> 398.657 | AD129: =IF(C129="","",IF(G129="UVR",Q129*AB129-S129,0)) -> 0 | AE129: =IF(C129="","",P129/+(O129+P129)) -> #DIV/0! | AF129: =IF(C129="","",AE129*Q129*K129%) -> #DIV/0! | AG129: =(Tabla6[[#This Row],[Fecha Vto]]-TODAY())/365 -> 0.22191781 | AJ129: =IF(C129="","",IF(G129="UVR",Q129*AI129-S129,0)) -> 0
A130: =IF(C130="","",YEAR(C130)) -> 2025 | B130: 645 | C130: 45981 | D130: Tesorería | E130: Títulos Recogidos por la Nación | F130: TFIT15260826 | G130: =+_xlfn.XLOOKUP(F130,Emisiones[Mnemotécnico SEN],Emisiones[Moneda],"",0,1) -> COP | J130: =+_xlfn.XLOOKUP(F130,Emisiones[Mnemotécnico SEN],Emisiones[Fecha Vencim.],"",0,1) -> 46260 | K130: =+_xlfn.XLOOKUP(F130,Emisiones[Mnemotécnico SEN],Emisiones[Tasa de Interés],"",0,1) -> 7.5 | L130: 9.24 | M130: 100.478 | N130: =IF(C130="","",PRICE(C130,J130,K130%,L130%,100,1,3)) -> 98.641138 | O130: =IF(C130="","",M130-N130) -> 1.8368625 | P130: =IF(C130="","",100*K130%-O130) -> 5.6631375 | Q130: =IF(C130="","",IF(G130="UVR",S130/V130,S130)) -> -142785000000 | R130: =IF(C130="","",IF('Canjes desagregado'!$G130="UVR",'Canjes desagregado'!$V130*Q130*M130%,Q130*M130%)) -> -143467512300 | S130: -142785000000 | T130: =IFERROR(IF(RIGHT(F130,2)=RIGHT(YEAR(J130),2),1,0),"") -> 1 | U130: =+IF(R130="","",R130) -> -143467512300 | V130: =+IF(F130<>"",(_xlfn.XLOOKUP(C130,UVR[Fecha (dd/mm/aaaa)],UVR[Pesos colombianos por UVR],"",0,1)),"") -> 396.3848 | W130: =IF(C130="","",IF(CONCATENATE(DAY(C130),"/",MONTH(C130),"/",2000)-CONCATENATE(DAY(J130),"/",MONTH(J130),"/",2000)<0,K130%*ABS(S130),0)) -> 0 | X130: =IF(S130<0,-W130,W130) -> 0 | AB130: =IF(C130="","",ROUND(V130*(1+'Inflación observada '!$B$390%)^(("31-12-2025"-C130)/365),3)) -> 398.657 | AD130: =IF(C130="","",IF(G130="UVR",Q130*AB130-S130,0)) -> 0 | AE130: =IF(C130="","",P130/+(O130+P130)) -> 0.755085 | AF130: =IF(C130="","",AE130*Q130*K130%) -> -8.0861109e+09 | AG130: =(Tabla6[[#This Row],[Fecha Vto]]-TODAY())/365 -> 0.70410959 | AJ130: =IF(C130="","",IF(G130="UVR",Q130*AI130-S130,0)) -> 0
... A172: =IF(C172="","",YEAR(C172)) -> 2025 | B172: 657 | C172: 46003 | D172: Tesorería | E172: Títulos Entregados por la Nación | F172: TFIT05220829 | G172: =+_xlfn.XLOOKUP(F172,Emisiones[Mnemotécnico SEN],Emisiones[Moneda],"",0,1) -> COP | J172: =+_xlfn.XLOOKUP(F172,Emisiones[Mnemotécnico SEN],Emisiones[Fecha Vencim.],"",0,1) -> 47352 | K172: =+_xlfn.XLOOKUP(F172,Emisiones[Mnemotécnico SEN],Emisiones[Tasa de Interés],"",0,1) -> 11 | L172: 12.375 | M172: 99.35 | N172: =IF(C172="","",PRICE(C172,J172,K172%,L172%,100,1,3)) -> 95.97495 | O172: =IF(C172="","",M172-N172) -> 3.3750496 | P172: =IF(C172="","",100*K172%-O172) -> 7.6249504 | Q172: =IF(C172="","",IF(G172="UVR",S172/V172,S172)) -> 206000000000 | R172: =IF(C172="","",IF('Canjes desagregado'!$G172="UVR",'Canjes desagregado'!$V172*Q172*M172%,Q172*M172%)) -> 204661000000 | S172: 206000000000 | T172: =IFERROR(IF(RIGHT(F172,2)=RIGHT(YEAR(J172),2),1,0),"") -> 1 | U172: =+IF(R172="","",R172) -> 204661000000 | V172: =+IF(F172<>"",(_xlfn.XLOOKUP(C172,UVR[Fecha (dd/mm/aaaa)],UVR[Pesos colombianos por UVR],"",0,1)),"") -> 396.9079 | W172: =IF(C172="","",IF(CONCATENATE(DAY(C172),"/",MONTH(C172),"/",2000)-CONCATENATE(DAY(J172),"/",MONTH(J172),"/",2000)<0,K172%*ABS(S172),0)) -> 0 | X172: =IF(S172<0,-W172,W172) -> 0 | AB172: =IF(C172="","",ROUND(V172*(1+'Inflación observada '!$B$390%)^(("31-12-2025"-C172)/365),3)) -> 397.961 | AD172: =IF(C172="","",IF(G172="UVR",Q172*AB172-S172,0)) -> 0 | AE172: =IF(C172="","",P172/+(O172+P172)) -> 0.69317731 | AF172: =IF(C172="","",AE172*Q172*K172%) -> 1.5707398e+10 | AG172: =(Tabla6[[#This Row],[Fecha Vto]]-TODAY())/365 -> 3.6958904 | AJ172: =IF(C172="","",IF(G172="UVR",Q172*AI172-S172,0)) -> 0

Sheet HISTORICO
C2: Macro Canjes | U2: Efecto fiscal neto como % del monto canjeado
C3: Micro Canjes
V4: DGCPTN | W4: Mercado
A5: año | B5: Operación | C5: Canje | D5: Etiqueta | E5: Año | F5: Denomicación canjeada 2025 | G5: Fecha | H5: Monto Canejado (MC) | I5: Valor de giro (Eje Izquierdo) | J5: Efecto cupones (Eje Izquierdo) | K5: Costo Fiscal Neto (CFN) | L5: Indexaciones (Eje Izquierdo) | M5: CFN+IND | N5: Saldo de la deuda (Eje izquierdo) | O5: Resultado General | P5: CFN/MC | Q5: CFN+INX/mc | R5: Ponderación | S5: CFN Riesgo | T5: Costo Oportunidad Riesgo | U5: Suma de efectos | V5: Efecto fiscal neto (tesorería) | W5: Efecto fiscal neto (mercado) | X5: Efecto fiscal neto como % del monto canjeado (eje derecho) | Z5: Max | AA5: Min | AB5: Maduración | AC5: Valor a girar % MC | AD5: Monto Canejado (COP) | AE5: Monto Canejado (UVR) | AF5: Monto Canejado (MC) | AG5: Valor de giro (Eje Izquierdo) | AH5: Efecto cupones (Eje Izquierdo) | AI5: Costo Fiscal Neto (CFN) | AJ5: Indexaciones (Eje Izquierdo) | AK5: CFN+IND | AL5: Saldo de la deuda (Eje izquierdo) | AM5: Resultado General | AN5: CFN/MC | AO5: CFN+INX/mc | AP5: Suma de efectos | AQ5: Efecto fiscal neto (tesorería) | AR5: Efecto fiscal neto (mercado) | AS5: Efecto fiscal neto como % del monto canjeado (eje derecho) | AV5: VERIFICADOR
A6: 2011 | B6: 1 | C6: Mercado | D6: 20-sep-11 | E6: 2011 | F6: 0 | G6: 40806 | H6: 5961843400000 | I6: 20428039516 | J6: 250733664000 | K6: 271161703516 | L6: 0 | M6: 271161703516 | N6: -291580800000 | O6: -20419096484 | P6: 0.045482862 | Q6: 0.045482862 | U6: -20419096484 | W6: -20419096484 | X6: -0.0034249636 | Y6: 5.9618434 | Z6: 0 | AA6: 0 | AB6: #VALUE! | AC6: 0.0034264636 | AD6: 0 | AE6: 0 | AV6: CORRECTO
A7: 2014 | B7: 2 | C7: Mercado | D7: 2-oct-14 | E7: 2014 | F7: UVR | G7: 41914 | H7: 5.9308923e+12 | I7: 2.146364e+11 | J7: -430158238250 | K7: -2.1552184e+11 | L7: -51699978 | M7: -2.1557354e+11 | N7: -6.3724197e+10 | O7: -2.7929774e+11 | P7: -0.036338856 | Q7: -0.036347573 | U7: -2.7929774e+11 | W7: -2.7929774e+11 | X7: -0.047092027 | Y7: 5.9308923 | Z7: 0 | AA7: 0 | AB7: #VALUE! | AC7: 0.036189563 | AD7: 4031128400000 | AE7: 1.8997639e+12 | AV7: CORRECTO
A8: 2016 | B8: 3 | C8: Tesorería | D8: 17-may-16 | E8: 2016 | F8: UVR | G8: 42507 | H8: 3.2425079e+12 | I8: 3.6201975e+09 | J8: 291400000000 | K8: 2.950202e+11 | L8: -5.2260771e+10 | M8: 2.4275943e+11 | N8: -5.025079e+11 | O8: -2.5974847e+11 | P8: 0.09098519 | Q8: 0.074867798 | U8: -2.5974847e+11 | V8: -2.5974847e+11 | X8: -0.080107274 | Y8: 3.2425079 | Z8: 0 | AA8: 0 | AB8: #VALUE! | AC8: 0.0011164807 | AD8: 0 | AE8: 3.2425079e+12 | AV8: CORRECTO
A9: 2018 | B9: 4 | C9: Tesorería | D9: 4-oct-18 | E9: 2018 | F9: COP | G9: 43377 | H9: 12306349733525 | I9: 7.8772626e+08 | J9: -245489601250 | K9: -2.4470187e+11 | L9: 2.0348094e+10 | M9: -2.2435378e+11 | N9: -4.1842234e+10 | O9: -2.6619601e+11 | P9: -0.019884196 | Q9: -0.018230733 | U9: -2.6619601e+11 | V9: -2.6619601e+11 | X9: -0.021630786 | Y9: 12.30635 | Z9: 0 | AA9: 0 | AB9: #VALUE! | AC9: 6.4009741e-05 | AD9: 11808100500000 | AE9: 4.9824923e+11 | AV9: CORRECTO
A10: 2019 | B10: 5 | C10: Mercado/mix | D10: 19-mar-19 | E10: 2019 | F10: UVR | G10: 43543 | H10: 1.0973904e+13 | I10: 2.8229568e+11 | J10: -3.2417214e+11 | K10: -4.1876465e+10 | L10: -3.5753929e+09 | M10: -4.5451858e+10 | N10: -1.2809638e+11 | O10: -1.7354824e+11 | P10: -0.0038160043 | Q10: -0.004141813 | R10: 0.59517542 | U10: -1.7354824e+11 | W10: -1.7354824e+11 | X10: -0.015814631 | Y10: 10.973904 | Z10: 0 | AA10: 0 | AB10: #VALUE! | AC10: 0.025724271 | AD10: 7958925400000 | AE10: 3.0149785e+12 | AV10: CORRECTO
A11: 2019 | B11: 6 | C11: Mercado | D11: 22-oct-19 | E11: 2019 | F11: UVR | G11: 43760 | H11: 4.9625182e+12 | I11: 11771599 | J11: 0 | K11: 11771599 | L11: -8.5871033e+08 | M11: -8.4693873e+08 | N11: -2.201569e+11 | O11: -2.2100384e+11 | P11: 2.3721019e-06 | Q11: -0.00017066713 | R11: 0.26914477 | U11: -2.2100384e+11 | W11: -2.2100384e+11 | X11: -0.044534615 | Y11: 4.9625182 | Z11: 0 | AA11: 0 | AB11: #VALUE! | AC11: 2.3721019e-06 | AD11: 0 | AE11: 4.9625182e+12 | AV11: CORRECTO
A12: 2020 | B12: 7 | C12: Tesorería | D12: 23-abr-20 | E12: 2020 | F12: COP | G12: 43944 | H12: 1493099300000 | I12: 1.203465e+11 | J12: -102370623000 | K12: 1.7975874e+10 | L12: 2.4767111e+08 | M12: 1.8223545e+10 | N12: -82535.2 | O12: 1.8223463e+10 | P12: 0.012039303 | Q12: 0.01220518 | R12: 0.080979021 | U12: 1.8223463e+10 | V12: 1.8223463e+10 | X12: 0.012205125 | Y12: 1.4930993 | Z12: 0 | AA12: 0 | AB12: #VALUE! | AC12: 0.080601804 | AD12: 1493099300000 | AE12: 0 | AV12: CORRECTO
A13: 2020 | B13: 8 | C13: Tesorería | D13: 12-may-20 | E13: 2020 | F13: UVR | G13: 43963 | H13: 1.4999999e+12 | I13: 209655.74 | J13: 98848839750 | K13: 9.8849049e+10 | L13: 4.6817269e+09 | M13: 1.0353078e+11 | N13: -1.3583536e+11 | O13: -3.2304587e+10 | P13: 0.065899372 | Q13: 0.069020524 | R13: 0.081353277 | U13: -3.2304587e+10 | V13: -3.2304587e+10 | X13: -0.021536393 | Y13: 1.4999999 | Z13: 0 | AA13: 0 | AB13: #VALUE! | AC13: 1.3977051e-07 | AD13: 0 | AE13: 1.4999999e+12 | AV13: CORRECTO
A14: 2020 | B14: 9 | C14: Banco República | D14: 14-may-20 | E14: 2020 | F14: COP | G14: 43965 | H14: 1.7656486e+12 | I14: 354431.07 | J14: -4.8521896e+10 | K14: -4.8521542e+10 | L14: 1.6871069e+08 | M14: -4.8352831e+10 | N14: -1.1248008e+11 | O14: -1.6083291e+11 | P14: -0.02748086 | Q14: -0.027385309 | R14: 0.095760874 | U14: -1.6083291e+11 | W14: -1.6083291e+11 | X14: -0.091089991 | Y14: 1.7656486 | Z14: 0 | AA14: 0 | AB14: 0 | AC14: 2.0073704e-07 | AD14: 1.3196931e+12 | AE14: 4.4595546e+11 | AV14: CORRECTO
A15: 2020 | B15: 10 | C15: Tesorería | D15: 20-may-20 | E15: 2020 | F15: UVR | G15: 43971 | H15: 4.9876053e+11 | I15: 266451.46 | J15: 32820842000 | K15: 3.2821108e+10 | L15: 1967215012 | M15: 3.4788323e+10 | N15: -4.5771027e+10 | O15: -1.0982704e+10 | P15: 0.065805345 | Q15: 0.069749552 | R15: 0.027050538 | U15: -1.0982704e+10 | V15: -1.0982704e+10 | X15: -0.022019994 | Y15: 0.49876053 | Z15: 0 | AA15: 0 | AB15: #VALUE! | AC15: 5.3422725e-07 | AD15: 0 | AE15: 4.9876053e+11 | AV15: CORRECTO
A16: 2020 | B16: 11 | C16: Tesorería | D16: 21-jul-20 | E16: 2020 | F16: UVR | G16: 44033 | H16: 3.9029054e+12 | I16: 45294.479 | J16: 156458818500 | K16: 1.5645886e+11 | L16: 5268406000 | M16: 1.6172727e+11 | N16: -2.6144725e+11 | O16: -9.9719978e+10 | P16: 0.040087793 | Q16: 0.04143766 | R16: 0.21167612 | U16: -9.9719978e+10 | V16: -9.9719978e+10 | X16: -0.025550191 | Y16: 3.9029054 | Z16: 0 | AA16: 0 | AB16: #VALUE! | AC16: 1.1605323e-08 | AD16: 0 | AE16: 3.9029054e+12 | AV16: CORRECTO
A17: 2020 | B17: 12 | C17: Caja Honor | D17: 4-sep-20 | E17: 2020 | F17: UVR | G17: 44078 | H17: 6.8038432e+11 | I17: 360903.53 | J17: 15734903750 | K17: 1.5735265e+10 | L17: -6.5317904e+08 | M17: 1.5082086e+10 | N17: -1.7152115e+10 | O17: -2.0700296e+09 | P17: 0.023127024 | Q17: 0.022167009 | R17: 0.036900999 | U17: -2.0700296e+09 | W17: -2.0700296e+09 | X17: -0.0030424417 | Y17: 0.68038432 | Z17: 0 | AA17: 0 | AB17: 0 | AC17: 5.3044069e-07 | AD17: 0 | AE17: 6.8038432e+11 | AV17: CORRECTO
A18: 2020 | B18: 13 | C18: Tesorería | D18: 44085 | E18: 2020 | F18: UVR | G18: 44085 | H18: 159904191420 | I18: 60885.283 | J18: 5661954500 | K18: 5.6620154e+09 | L18: -2.7521294e+08 | M18: 5.3868024e+09 | N18: -15486291420 | O18: -1.0099489e+10 | P18: 0.035408799 | Q18: 0.033687688 | R18: 0.0086724874 | U18: -1.0099489e+10 | V18: -1.0099489e+10 | X18: -0.063159626 | Y18: 0.15990419 | Z18: 0 | AA18: 0 | AB18: #VALUE! | AC18: 3.8076102e-07 | AD18: 0 | AE18: 159904191420 | AV18: CORRECTO
A19: 2020 | B19: 14 | C19: Tesorería | D19: 44085 | E19: 2020 | F19: COP | G19: 44085 | H19: 4232899500000 | I19: 2123 | J19: 158879092500 | K19: 158879094623 | L19: 0 | M19: 158879094623 | N19: -180414500000 | O19: -21535405377 | P19: 0.037534341 | Q19: 0.037534341 | R19: 0.22957352 | U19: -21535405377 | V19: -21535405377 | X19: -0.005087625 | Y19: 4.2328995 | Z19: 0 | AA19: 0 | AB19: #VALUE! | AC19: 5.0154746e-10 | AD19: 4232899500000 | AE19: 0 | AV19: CORRECTO
A20: 2020 | B20: 15 | C20: Mercado | D20: 22-oct-20 | E20: 2020 | F20: UVR | G20: 44126 | H20: 1998812104850 | I20: 1.049612e+10 | J20: 50229125000 | K20: 6.0725245e+10 | L20: -24971048 | M20: 6.0700274e+10 | N20: -3.6374613e+10 | O20: 2.4325661e+10 | P20: 0.030380667 | Q20: 0.030368174 | R20: 0.10840662 | U20: 2.4325661e+10 | W20: 2.4325661e+10 | X20: 0.012170059 | Y20: 1.9988121 | Z20: 0 | AA20: 0 | AB20: #VALUE! | AC20: 0.0052511788 | AD20: 1322210000000 | AE20: 676602104850 | AV20: CORRECTO
A21: 2020 | B21: 16 | C21: Tesorería | D21: 16-dic-20 | E21: 2020 | F21: UVR | G21: 44181 | H21: 309670312500 | I21: 95087.5 | J21: 0 | K21: 95087.5 | L21: 224887500 | M21: 2.2498259e+08 | N21: -24396012500 | O21: -2.417103e+10 | P21: 3.0706043e-07 | Q21: 0.00072652295 | R21: 0.016795131 | U21: -2.417103e+10 | V21: -2.417103e+10 | X21: -0.078054075 | Y21: 0.30967031 | Z21: 0 | AA21: 0 | AB21: #VALUE! | AC21: 3.0706043e-07 | AD21: 0 | AE21: 309670312500 | AV21: CORRECTO
A22: 2021 | B22: 17 | C22: Tesorería | D22: 12-mar-21 | E22: 2021 | F22: COP | G22: 44267 | H22: 4272241000000 | I22: 1.0340223e+11 | J22: -6.8355912e+10 | K22: 3.5046319e+10 | L22: 7.221411e+10 | M22: 1.0726043e+11 | N22: -1082723.2 | O22: 1.0725935e+11 | P22: 0.0082032637 | Q22: 0.025106362 | R22: 0.23170722 | U22: 1.0725935e+11 | V22: 1.0725935e+11 | X22: 0.025106109 | Y22: 4.272241 | Z22: 0 | AA22: 0 | AB22: #VALUE! | AC22: 0.024203277 | AD22: 4272241000000 | AE22: 0 | AV22: CORRECTO
A23: 2021 | B23: 18 | C23: Caja Honor | D23: 13-ago-21 | E23: 2021 | F23: UVR | G23: 44421 | H23: 2.5956265e+11 | I23: 53664.701 | J23: 0 | K23: 53664.701 | L23: -1.3211418e+08 | M23: -1.3206051e+08 | N23: -9.2910108e+09 | O23: -9.4230713e+09 | P23: 2.0675047e-07 | Q23: -0.00050878088 | R23: 0.014077516 | U23: -9.4230713e+09 | W23: -9.4230713e+09 | X23: -0.036303649 | Y23: 0.25956265 | Z23: 0 | AA23: 0 | AB23: 0 | AC23: 2.0675047e-07 | AD23: 0 | AE23: 2.5956265e+11 | AV23: CORRECTO
A24: 2021 | B24: 19 | C24: Tesorería | D24: 26-ago-21 | E24: 2021 | F24: COP | G24: 44434 | H24: 6000000000000 | I24: 3.3449698e+11 | J24: 0 | K24: 3.3449698e+11 | L24: 1.0482498e+10 | M24: 3.4497948e+11 | N24: -236104.4 | O24: 3.4497925e+11 | P24: 0.055749497 | Q24: 0.05749658 | R24: 0.32541314 | U24: 3.4497925e+11 | V24: 3.4497925e+11 | X24: 0.057496541 | Y24: 6 | Z24: 0 | AA24: 0 | AB24: #VALUE! | AC24: 0.055749497 | AD24: 6000000000000 | AE24: 0 | AV24: CORRECTO
A25: 2021 | B25: 20 | C25: Tesorería | D25: 21-sep-21 | E25: 2021 | F25: COP | G25: 44460 | H25: 1500000000000 | I25: 5.9848872e+10 | J25: 0 | K25: 5.9848872e+10 | L25: 4.5489731e+09 | M25: 6.4397845e+10 | N25: -31037139 | O25: 6.4366808e+10 | P25: 0.039899248 | Q25: 0.042931897 | R25: 0.081353284 | U25: 6.4366808e+10 | V25: 6.4366808e+10 | X25: 0.042911205 | Y25: 1.5 | Z25: 0 | AA25: 0 | AB25: #VALUE! | AC25: 0.039899248 | AD25: 1500000000000 | AE25: 0 | AV25: CORRECTO
A26: 2021 | B26: 21 | C26: Tesorería | D26: 1-oct-21 | E26: 2021 | F26: COP | G26: 44470 | H26: 1500000000000 | I26: 6.0717971e+10 | J26: 0 | K26: 6.0717971e+10 | L26: 4.2993572e+09 | M26: 6.5017329e+10 | N26: -21468094 | O26: 6.4995861e+10 | P26: 0.040478648 | Q26: 0.043344886 | R26: 0.081353284 | U26: 6.4995861e+10 | V26: 6.4995861e+10 | X26: 0.043330574 | Y26: 1.5 | Z26: 0 | AA26: 0 | AB26: #VALUE! | AC26: 0.040478648 | AD26: 1500000000000 | AE26: 0 | AV26: CORRECTO
A27: 2021 | B27: 22 | C27: Caja Honor | D27: 22-oct-21 | E27: 2021 | F27: UVR | G27: 44491 | H27: 5.8318662e+11 | I27: 1.8965551e+09 | J27: 0 | K27: 1.8965551e+09 | L27: 6.8454117e+08 | M27: 2.5810962e+09 | N27: -198156.9 | O27: 2.5808981e+09 | P27: 0.0032520552 | Q27: 0.0044258495 | R27: 0.031629431 | U27: 2.5808981e+09 | W27: 2.5808981e+09 | X27: 0.0044255097 | Y27: 0.58318662 | Z27: 0 | AA27: 0 | AB27: 0 | AC27: 0.0032520552 | AD27: 121666200000 | AE27: 4.6152042e+11 | AV27: CORRECTO
A28: 2021 | B28: 23 | C28: Tesorería | D28: 13-dic-21 | E28: 2021 | F28: COP | G28: 44543 | H28: 1094007500000 | I28: 3316480.3 | J28: 0 | K28: 3316480.3 | L28: 2771741644 | M28: 2.7750581e+09 | N28: -21396019808 | O28: -1.8620962e+10 | P28: 3.0314968e-06 | Q28: 0.0025365988 | R28: 0.059334069 | U28: -1.8620962e+10 | V28: -1.8620962e+10 | X28: -0.017020872 | Y28: 1.0940075 | Z28: 0 | AA28: 0 | AB28: #VALUE! | AC28: 3.0314968e-06 | AD28: 1094007500000 | AE28: 0 | AV28: CORRECTO
A29: 2022 | B29: 24 | C29: Tesorería | D29: 14-mar-22 | E29: 2022 | F29: COP | G29: 44634 | H29: 30922500000 | I29: 1.467371e+09 | J29: 2.8858205e+08 | K29: 1.755953e+09 | L29: 400810000 | M29: 2.156763e+09 | N29: -98000 | O29: 2.156665e+09 | P29: 0.056785611 | Q29: 0.06974737 | R29: 0.001677098 | U29: 2.156665e+09 | V29: 2.156665e+09 | X29: 0.069744201 | Z29: 0 | AA29: 0 | AB29: #VALUE! | AC29: 0.047453181 | AD29: 30922500000 | AE29: 0 | AV29: CORRECTO
A30: 2022 | B30: 25 | C30: Tesorería | D30: 15-mar-22 | E30: 2022 | F30: COP | G30: 44635 | H30: 245370300000 | I30: 1.0071305e+10 | J30: 2.0578717e+09 | K30: 1.2129177e+10 | L30: 3.396838e+09 | M30: 1.5526015e+10 | N30: -82000 | O30: 1.5525933e+10 | P30: 0.04943213 | Q30: 0.063275851 | R30: 0.013307787 | U30: 1.5525933e+10 | V30: 1.5525933e+10 | X30: 0.063275517 | Z30: 0 | AA30: 0 | AB30: #VALUE! | AC30: 0.04104533 | AD30: 245370300000 | AE30: 0 | AV30: CORRECTO
A31: 2022 | B31: 26 | C31: Tesorería | D31: 16-mar-22 | E31: 2022 | F31: COP | G31: 44636 | H31: 271825600000 | I31: 11563784356 | J31: 2243688625 | K31: 13807472981 | L31: 3784971000 | M31: 17592443981 | N31: -100000 | O31: 17592343981 | P31: 0.050795337 | Q31: 0.0647196 | R31: 0.014742604 | U31: 17592343981 | V31: 17592343981 | X31: 0.064719232 | Z31: 0 | AA31: 0 | AB31: #VALUE! | AC31: 0.042541189 | AD31: 271825600000 | AE31: 0 | AV31: CORRECTO
A32: 2022 | B32: 27 | C32: Tesorería | D32: 17-mar-22 | E32: 2022 | F32: COP | G32: 44637 | H32: 355185200000 | I32: 1.5060504e+10 | J32: 3.0976822e+09 | K32: 1.8158186e+10 | L32: 4766472000 | M32: 2.2924658e+10 | N32: -96000 | O32: 2.2924562e+10 | P32: 0.051123149 | Q32: 0.06454283 | R32: 0.019263655 | U32: 2.2924562e+10 | V32: 2.2924562e+10 | X32: 0.064542559 | AB32: #VALUE! | AC32: 0.042401833 | AD32: 355185200000 | AE32: 0 | AV32: CORRECTO
A33: 2022 | B33: 28 | C33: Tesorería | D33: 18-mar-22 | E33: 2022 | F33: COP | G33: 44638 | H33: 148676000000 | I33: 6.7717521e+09 | J33: 1.3049836e+09 | K33: 8.0767356e+09 | L33: 1.97997e+09 | M33: 1.0056706e+10 | N33: -60000 | O33: 1.0056646e+10 | P33: 0.054324408 | Q33: 0.067641755 | R33: 0.0080635206 | U33: 1.0056646e+10 | V33: 1.0056646e+10 | X33: 0.067641352 | AB33: #VALUE! | AC33: 0.045547042 | AD33: 148676000000 | AE33: 0 | AV33: CORRECTO
A34: 2022 | B34: 29 | C34: Tesorería | D34: 29-mar-22 | E34: 2022 | F34: UVR | G34: 44649 | H34: 3.5257256e+11 | I34: 6.915915e+09 | J34: 21226439875 | K34: 2.8142355e+10 | L34: -1.1023699e+10 | M34: 1.7118656e+10 | N34: -149037.2 | O34: 1.7118507e+10 | P34: 0.079820036 | Q34: 0.048553569 | R34: 0.019121957 | U34: 1.7118507e+10 | V34: 1.7118507e+10 | X34: 0.048553146 | AB34: #VALUE! | AC34: 0.019615579 | AD34: 0 | AE34: 3.5257256e+11 | AV34: CORRECTO
A35: 2022 | B35: 30 | C35: Tesorería | D35: 30-mar-22 | E35: 2022 | F35: UVR | G35: 44650 | H35: 4.4247388e+11 | I35: 8.6013616e+09 | J35: 2.6803981e+10 | K35: 3.5405343e+10 | L35: -1.4047627e+10 | M35: 2.1357716e+10 | N35: -47381.6 | O35: 2.1357668e+10 | P35: 0.080016796 | Q35: 0.048268873 | R35: 0.023997803 | U35: 2.1357668e+10 | V35: 2.1357668e+10 | X35: 0.048268766 | AB35: #VALUE! | AC35: 0.019439253 | AD35: 0 | AE35: 4.4247388e+11 | AV35: CORRECTO
A36: 2022 | B36: 31 | C36: Tesorería | D36: 31-mar-22 | E36: 2022 | F36: COP | G36: 44651 | H36: 535084800000 | I36: 2.5908466e+10 | J36: -5.08215e+09 | K36: 2.0826316e+10 | L36: 1.7019446e+10 | M36: 3.7845762e+10 | N36: -86606.4 | O36: 3.7845676e+10 | P36: 0.038921524 | Q36: 0.070728532 | R36: 0.029020604 | U36: 3.7845676e+10 | V36: 3.7845676e+10 | X36: 0.07072837 | AB36: #VALUE! | AC36: 0.048419364 | AD36: 535084800000 | AE36: 0 | AV36: CORRECTO
A37: 2022 | B37: 32 | C37: Tesorería | D37: 1-abr-22 | E37: 2022 | F37: UVR | G37: 44652 | H37: 696763904583 | I37: 1.9530612e+10 | J37: 4.2101572e+10 | K37: 6.1632183e+10 | L37: -2.2181435e+10 | M37: 3.9450749e+10 | N37: -232583 | O37: 3.9450516e+10 | P37: 0.088454903 | Q37: 0.056619966 | R37: 0.037789355 | U37: 3.9450516e+10 | V37: 3.9450516e+10 | X37: 0.056619632 | AB37: #VALUE! | AC37: 0.028030459 | AD37: 0 | AE37: 696763904583 | AV37: CORRECTO
A38: 2022 | B38: 33 | C38: Tesorería | D38: 4-abr-22 | E38: 2022 | F38: UVR | G38: 44655 | H38: 4.2058478e+11 | I38: 1.6723503e+10 | J38: 19656250000 | K38: 3.6379753e+10 | L38: -1.3315369e+10 | M38: 2.3064384e+10 | N38: -183620.4 | O38: 2.30642e+10 | P38: 0.086498025 | Q38: 0.054838845 | R38: 0.022810636 | U38: 2.30642e+10 | V38: 2.30642e+10 | X38: 0.054838408 | AB38: #VALUE! | AC38: 0.039762501 | AD38: 0 | AE38: 4.2058478e+11 | AV38: CORRECTO
A39: 2022 | B39: 34 | C39: Tesorería | D39: 5-abr-22 | E39: 2022 | F39: UVR | G39: 44656 | H39: 398457738775 | I39: 1.6212772e+10 | J39: 18500000000 | K39: 3.4712772e+10 | L39: -1.3497413e+10 | M39: 2.121536e+10 | N39: -232525 | O39: 2.1215127e+10 | P39: 0.087117827 | Q39: 0.053243689 | R39: 0.021610564 | U39: 2.1215127e+10 | V39: 2.1215127e+10 | X39: 0.053243105 | AB39: #VALUE! | AC39: 0.040688813 | AD39: 0 | AE39: 398457738775 | AV39: CORRECTO
A40: 2022 | B40: 35 | C40: Tesorería | D40: 6-abr-22 | E40: 2022 | F40: UVR | G40: 44657 | H40: 288863325951 | I40: 1.3119615e+10 | J40: 13412500000 | K40: 2.6532115e+10 | L40: -9.7481588e+09 | M40: 1.6783956e+10 | N40: -221951 | O40: 1.6783734e+10 | P40: 0.091850063 | Q40: 0.05810345 | R40: 0.015666654 | U40: 1.6783734e+10 | V40: 1.6783734e+10 | X40: 0.058102681 | AB40: #VALUE! | AC40: 0.045418069 | AD40: 0 | AE40: 288863325951 | AV40: CORRECTO
A41: 2022 | B41: 36 | C41: Tesorería | D41: 7-abr-22 | E41: 2022 | F41: UVR | G41: 44658 | H41: 1.8796017e+11 | I41: 7.5302691e+09 | J41: 8787500000 | K41: 1.6317769e+10 | L41: -6.3621962e+09 | M41: 9.9555728e+09 | N41: -95773.6 | O41: 9.9554771e+09 | P41: 0.086815038 | Q41: 0.052966397 | R41: 0.010194118 | U41: 9.9554771e+09 | V41: 9.9554771e+09 | X41: 0.052965887 | AB41: #VALUE! | AC41: 0.040063111 | AD41: 0 | AE41: 1.8796017e+11 | AV41: CORRECTO
A42: 2022 | B42: 37 | C42: Tesorería | D42: 8-abr-22 | E42: 2022 | F42: UVR | G42: 44659 | H42: 156007451365 | I42: 7.3731114e+09 | J42: 7215000000 | K42: 1.4588111e+10 | L42: -5.2035956e+09 | M42: 9.3845158e+09 | N42: -275365 | O42: 9.3842404e+09 | P42: 0.093509068 | Q42: 0.060154279 | R42: 0.0084611457 | U42: 9.3842404e+09 | V42: 9.3842404e+09 | X42: 0.060152514 | AB42: #VALUE! | AC42: 0.047261277 | AD42: 0 | AE42: 156007451365 | AV42: CORRECTO
A43: 2022 | B43: 38 | C43: Tesorería | D43: 19-abr-22 | E43: 2022 | F43: UVR | G43: 44670 | H43: 4.7018963e+11 | I43: 2.2400928e+10 | J43: 21737500000 | K43: 4.4138428e+10 | L43: -1.5011347e+10 | M43: 2.9127081e+10 | N43: -287950.4 | O43: 2.9126793e+10 | P43: 0.093873674 | Q43: 0.061947518 | R43: 0.025500981 | U43: 2.9126793e+10 | V43: 2.9126793e+10 | X43: 0.061946906 | AB43: #VALUE! | AC43: 0.047642327 | AD43: 0 | AE43: 4.7018963e+11 | AV43: CORRECTO
A44: 2022 | B44: 39 | C44: Mercado | D44: 16-may-22 | E44: 2022 | F44: UVR | G44: 44697 | H44: 2.5739279e+12 | I44: 1.3172891e+11 | J44: 22824634000 | K44: 1.5455354e+11 | L44: -1.3813601e+10 | M44: 1.4073994e+11 | N44: -600200 | O44: 1.4073934e+11 | P44: 0.060045793 | Q44: 0.054679054 | R44: 0.13959833 | U44: 1.4073934e+11 | W44: 1.4073934e+11 | X44: 0.054678821 | AB44: 0 | AC44: 0.051178166 | AD44: 0 | AE44: 2.5739279e+12 | AV44: CORRECTO
A45: 2022 | B45: 40 | C45: Tesorería | D45: 17-may-22 | E45: 2022 | F45: UVR | G45: 44698 | H45: 8.439821e+10 | I45: 5.6967827e+09 | J45: 1650000000 | K45: 7.3467827e+09 | L45: -1.2260759e+09 | M45: 6.1207068e+09 | N45: -289247.9 | O45: 6.1204176e+09 | P45: 0.087049035 | Q45: 0.072521761 | R45: 0.004577381 | U45: 6.1204176e+09 | V45: 6.1204176e+09 | X45: 0.072518334 | AB45: #VALUE! | AC45: 0.067498858 | AD45: 0 | AE45: 8.439821e+10 | AV45: CORRECTO
A46: 2022 | B46: 41 | C46: Tesorería | D46: 18-may-22 | E46: 2022 | F46: UVR | G46: 44699 | H46: 2.2681874e+11 | I46: 1.6108435e+10 | J46: 5250000000 | K46: 2.1358435e+10 | L46: -3883545354 | M46: 1.747489e+10 | N46: -160756.4 | O46: 1.7474729e+10 | P46: 0.094165212 | Q46: 0.077043411 | R46: 0.012301633 | U46: 1.7474729e+10 | V46: 1.7474729e+10 | X46: 0.077042702 | AB46: #VALUE! | AC46: 0.071018977 | AD46: 0 | AE46: 2.2681874e+11 | AV46: CORRECTO
